Workbook

Sheet README
A1: Case 03 — Finding Where Margin Is Quietly Leaking
A2: Finance & Budgeting case study — budget vs. actual profitability by region and category
A4: Business problem: the business is profitable overall, but budget-to-actual reviews keep
A5: coming in over on cost-to-serve in specific regions and categories. This workbook finds where.
A7: Sheet guide:
A8: Monthly Detail 576 rows (4 regions x 6 categories x 24 months), budget vs. actual,
A9: with live formulas for revenue/discount/COGS variance and a 3-part
A10: profit-variance bridge (Volume, Discount, COGS effects).
A11: Region x Category Summary Flat SUMIFS table + a pivoted heatmap matrix flagging the leaks.
A12: Margin Bridge Total budget profit -> Volume -> Discount -> COGS -> actual profit,
A13: with a chart. All three effects are provably additive to the total
A14: variance (see the Check column in Monthly Detail).
... A25: Sporting. Everything else moves with ordinary month-to-month noise around budget.

Sheet Monthly Detail
A1: Month | B1: Region | C1: Category | D1: Budget Gross Rev | E1: Budget Discount % | F1: Budget COGS % | G1: Budget Net Rev | H1: Budget COGS $ | I1: Budget Profit | J1: Actual Gross Rev | K1: Actual Discount % | L1: Actual COGS % | M1: Actual Net Rev | N1: Actual COGS $ | O1: Actual Profit | P1: Profit Variance $ | Q1: Volume Effect $ | R1: Discount Effect $ | S1: COGS Effect $ | T1: Check (should = 0)
A2: 2024-01 | B2: Northeast | C2: Electronics Accessories | D2: 156793.46 | E2: 0.1 | F2: 0.62 | G2: =D2*(1-E2) -> 141114.11 | H2: =G2*F2 -> 87490.751 | I2: =G2-H2 -> 53623.363 | J2: 153721.33 | K2: 0.1107 | L2: 0.6207 | M2: =J2*(1-K2) -> 136704.38 | N2: =M2*L2 -> 84852.408 | O2: =M2-N2 -> 51851.971 | P2: =O2-I2 -> -1771.3925 | Q2: =(J2-D2)*(1-E2)*(1-F2) -> -1050.6685 | R2: =J2*(E2-K2)*(1-F2) -> -625.03093 | S2: =M2*(F2-L2) -> -95.693065 | T2: =ROUND(P2-(Q2+R2+S2),2) -> 0
A3: 2024-02 | B3: Northeast | C3: Electronics Accessories | D3: 154535.63 | E3: 0.1 | F3: 0.62 | G3: =D3*(1-E3) -> 139082.07 | H3: =G3*F3 -> 86230.882 | I3: =G3-H3 -> 52851.185 | J3: 154921.35 | K3: 0.11 | L3: 0.6537 | M3: =J3*(1-K3) -> 137880 | N3: =M3*L3 -> 90132.157 | O3: =M3-N3 -> 47747.845 | P3: =O3-I3 -> -5103.3409 | Q3: =(J3-D3)*(1-E3)*(1-F3) -> 131.91624 | R3: =J3*(E3-K3)*(1-F3) -> -588.70113 | S3: =M3*(F3-L3) -> -4646.5561 | T3: =ROUND(P3-(Q3+R3+S3),2) -> 0
A4: 2024-03 | B4: Northeast | C4: Electronics Accessories | D4: 168152.27 | E4: 0.1 | F4: 0.62 | G4: =D4*(1-E4) -> 151337.04 | H4: =G4*F4 -> 93828.967 | I4: =G4-H4 -> 57508.076 | J4: 166763.41 | K4: 0.104 | L4: 0.6318 | M4: =J4*(1-K4) -> 149420.02 | N4: =M4*L4 -> 94403.566 | O4: =M4-N4 -> 55016.45 | P4: =O4-I4 -> -2491.6267 | Q4: =(J4-D4)*(1-E4)*(1-F4) -> -474.99012 | R4: =J4*(E4-K4)*(1-F4) -> -253.48038 | S4: =M4*(F4-L4) -> -1763.1562 | T4: =ROUND(P4-(Q4+R4+S4),2) -> 0
A5: 2024-04 | B5: Northeast | C5: Electronics Accessories | D5: 174828.19 | E5: 0.1 | F5: 0.62 | G5: =D5*(1-E5) -> 157345.37 | H5: =G5*F5 -> 97554.13 | I5: =G5-H5 -> 59791.241 | J5: 173359.9 | K5: 0.0975 | L5: 0.6332 | M5: =J5*(1-K5) -> 156457.31 | N5: =M5*L5 -> 99068.769 | O5: =M5-N5 -> 57388.541 | P5: =O5-I5 -> -2402.6998 | Q5: =(J5-D5)*(1-E5)*(1-F5) -> -502.15518 | R5: =J5*(E5-K5)*(1-F5) -> 164.6919 | S5: =M5*(F5-L5) -> -2065.2365 | T5: =ROUND(P5-(Q5+R5+S5),2) -> 0
A6: 2024-05 | B6: Northeast | C6: Electronics Accessories | D6: 179789.83 | E6: 0.1 | F6: 0.62 | G6: =D6*(1-E6) -> 161810.85 | H6: =G6*F6 -> 100322.73 | I6: =G6-H6 -> 61488.122 | J6: 180352.71 | K6: 0.101 | L6: 0.6419 | M6: =J6*(1-K6) -> 162137.09 | N6: =M6*L6 -> 104075.8 | O6: =M6-N6 -> 58061.291 | P6: =O6-I6 -> -3426.8313 | Q6: =(J6-D6)*(1-E6)*(1-F6) -> 192.50496 | R6: =J6*(E6-K6)*(1-F6) -> -68.53403 | S6: =M6*(F6-L6) -> -3550.8022 | T6: =ROUND(P6-(Q6+R6+S6),2) -> 0
A7: 2024-06 | B7: Northeast | C7: Electronics Accessories | D7: 184807.22 | E7: 0.1 | F7: 0.62 | G7: =D7*(1-E7) -> 166326.5 | H7: =G7*F7 -> 103122.43 | I7: =G7-H7 -> 63204.069 | J7: 182721.57 | K7: 0.0918 | L7: 0.6449 | M7: =J7*(1-K7) -> 165947.73 | N7: =M7*L7 -> 107019.69 | O7: =M7-N7 -> 58928.039 | P7: =O7-I7 -> -4276.0304 | Q7: =(J7-D7)*(1-E7)*(1-F7) -> -713.2923 | R7: =J7*(E7-K7)*(1-F7) -> 569.36041 | S7: =M7*(F7-L7) -> -4132.0985 | T7: =ROUND(P7-(Q7+R7+S7),2) -> 0
A8: 2024-07 | B8: Northeast | C8: Electronics Accessories | D8: 182577.27 | E8: 0.1 | F8: 0.62 | G8: =D8*(1-E8) -> 164319.54 | H8: =G8*F8 -> 101878.12 | I8: =G8-H8 -> 62441.426 | J8: 185287.84 | K8: 0.1176 | L8: 0.6378 | M8: =J8*(1-K8) -> 163497.99 | N8: =M8*L8 -> 104279.02 | O8: =M8-N8 -> 59218.972 | P8: =O8-I8 -> -3222.4544 | Q8: =(J8-D8)*(1-E8)*(1-F8) -> 927.01494 | R8: =J8*(E8-K8)*(1-F8) -> -1239.2051 | S8: =M8*(F8-L8) -> -2910.2642 | T8: =ROUND(P8-(Q8+R8+S8),2) -> 0
A9: 2024-08 | B9: Northeast | C9: Electronics Accessories | D9: 189490.12 | E9: 0.1 | F9: 0.62 | G9: =D9*(1-E9) -> 170541.11 | H9: =G9*F9 -> 105735.49 | I9: =G9-H9 -> 64805.621 | J9: 189026.88 | K9: 0.0984 | L9: 0.6357 | M9: =J9*(1-K9) -> 170426.64 | N9: =M9*L9 -> 108340.21 | O9: =M9-N9 -> 62086.423 | P9: =O9-I9 -> -2719.1979 | Q9: =(J9-D9)*(1-E9)*(1-F9) -> -158.42808 | R9: =J9*(E9-K9)*(1-F9) -> 114.92834 | S9: =M9*(F9-L9) -> -2675.6982 | T9: =ROUND(P9-(Q9+R9+S9),2) -> 0
A10: 2024-09 | B10: Northeast | C10: Electronics Accessories | D10: 194632.94 | E10: 0.1 | F10: 0.62 | G10: =D10*(1-E10) -> 175169.65 | H10: =G10*F10 -> 108605.18 | I10: =G10-H10 -> 66564.465 | J10: 200161.19 | K10: 0.1012 | L10: 0.6463 | M10: =J10*(1-K10) -> 179904.88 | N10: =M10*L10 -> 116272.52 | O10: =M10-N10 -> 63632.355 | P10: =O10-I10 -> -2932.1103 | Q10: =(J10-D10)*(1-E10)*(1-F10) -> 1890.6615 | R10: =J10*(E10-K10)*(1-F10) -> -91.273503 | S10: =M10*(F10-L10) -> -4731.4983 | T10: =ROUND(P10-(Q10+R10+S10),2) -> 0
A11: 2024-10 | B11: Northeast | C11: Electronics Accessories | D11: 205434.27 | E11: 0.1 | F11: 0.62 | G11: =D11*(1-E11) -> 184890.84 | H11: =G11*F11 -> 114632.32 | I11: =G11-H11 -> 70258.52 | J11: 198685.42 | K11: 0.0951 | L11: 0.6553 | M11: =J11*(1-K11) -> 179790.44 | N11: =M11*L11 -> 117816.67 | O11: =M11-N11 -> 61973.763 | P11: =O11-I11 -> -8284.7569 | Q11: =(J11-D11)*(1-E11)*(1-F11) -> -2308.1067 | R11: =J11*(E11-K11)*(1-F11) -> 369.95225 | S11: =M11*(F11-L11) -> -6346.6024 | T11: =ROUND(P11-(Q11+R11+S11),2) -> 0
A12: 2024-11 | B12: Northeast | C12: Electronics Accessories | D12: 244597.79 | E12: 0.1 | F12: 0.62 | G12: =D12*(1-E12) -> 220138.01 | H12: =G12*F12 -> 136485.57 | I12: =G12-H12 -> 83652.444 | J12: 240186.96 | K12: 0.0973 | L12: 0.6565 | M12: =J12*(1-K12) -> 216816.77 | N12: =M12*L12 -> 142340.21 | O12: =M12-N12 -> 74476.56 | P12: =O12-I12 -> -9175.8841 | Q12: =(J12-D12)*(1-E12)*(1-F12) -> -1508.5039 | R12: =J12*(E12-K12)*(1-F12) -> 246.43182 | S12: =M12*(F12-L12) -> -7913.8121 | T12: =ROUND(P12-(Q12+R12+S12),2) -> 0
A13: 2024-12 | B13: Northeast | C13: Electronics Accessories | D13: 231245.96 | E13: 0.1 | F13: 0.62 | G13: =D13*(1-E13) -> 208121.36 | H13: =G13*F13 -> 129035.25 | I13: =G13-H13 -> 79086.118 | J13: 221347.67 | K13: 0.1032 | L13: 0.6591 | M13: =J13*(1-K13) -> 198504.59 | N13: =M13*L13 -> 130834.38 | O13: =M13-N13 -> 67670.215 | P13: =O13-I13 -> -11415.903 | Q13: =(J13-D13)*(1-E13)*(1-F13) -> -3385.2152 | R13: =J13*(E13-K13)*(1-F13) -> -269.15877 | S13: =M13*(F13-L13) -> -7761.5295 | T13: =ROUND(P13-(Q13+R13+S13),2) -> 0
... A577: 2025-12 | B577: West | C577: Pet Supplies | D577: 197624.03 | E577: 0.09 | F577: 0.56 | G577: =D577*(1-E577) -> 179837.87 | H577: =G577*F577 -> 100709.21 | I577: =G577-H577 -> 79128.662 | J577: 199553.85 | K577: 0.0735 | L577: 0.553 | M577: =J577*(1-K577) -> 184886.64 | N577: =M577*L577 -> 102242.31 | O577: =M577-N577 -> 82644.329 | P577: =O577-I577 -> 3515.6674 | Q577: =(J577-D577)*(1-E577)*(1-F577) -> 772.69993 | R577: =J577*(E577-K577)*(1-F577) -> 1448.761 | S577: =M577*(F577-L577) -> 1294.2065 | T577: =ROUND(P577-(Q577+R577+S577),2) -> 0

Sheet Region x Category Summary
A1: Total Profit Variance by Region x Category (24 months)
A2: Flat table (left) drives the heatmap matrix (below) via SUMIFS against Monthly Detail.
A4: Category | B4: Region | C4: Budget Profit | D4: Actual Profit | E4: Variance $ | F4: Variance % | H4: Tiebreak Key
A5: Electronics Accessories | B5: Midwest | C5: =SUMIFS('Monthly Detail'!$I$2:$I$577,'Monthly Detail'!$C$2:$C$577,A5,'Monthly Detail'!$B$2:$B$577,B5) -> 1995639.4 | D5: =SUMIFS('Monthly Detail'!$O$2:$O$577,'Monthly Detail'!$C$2:$C$577,A5,'Monthly Detail'!$B$2:$B$577,B5) -> 2000365.3 | E5: =D5-C5 -> 4725.8154 | F5: =IFERROR(E5/C5,0) -> 0.0023680708 | H5: =E5+ROW()/1000000 -> 4725.8154
A6: Electronics Accessories | B6: Northeast | C6: =SUMIFS('Monthly Detail'!$I$2:$I$577,'Monthly Detail'!$C$2:$C$577,A6,'Monthly Detail'!$B$2:$B$577,B6) -> 1621646.7 | D6: =SUMIFS('Monthly Detail'!$O$2:$O$577,'Monthly Detail'!$C$2:$C$577,A6,'Monthly Detail'!$B$2:$B$577,B6) -> 1513848.9 | E6: =D6-C6 -> -107797.79 | F6: =IFERROR(E6/C6,0) -> -0.066474277 | H6: =E6+ROW()/1000000 -> -107797.79
A7: Electronics Accessories | B7: South | C7: =SUMIFS('Monthly Detail'!$I$2:$I$577,'Monthly Detail'!$C$2:$C$577,A7,'Monthly Detail'!$B$2:$B$577,B7) -> 2557952.3 | D7: =SUMIFS('Monthly Detail'!$O$2:$O$577,'Monthly Detail'!$C$2:$C$577,A7,'Monthly Detail'!$B$2:$B$577,B7) -> 2570412.2 | E7: =D7-C7 -> 12459.841 | F7: =IFERROR(E7/C7,0) -> 0.0048710214 | H7: =E7+ROW()/1000000 -> 12459.841
A8: Electronics Accessories | B8: West | C8: =SUMIFS('Monthly Detail'!$I$2:$I$577,'Monthly Detail'!$C$2:$C$577,A8,'Monthly Detail'!$B$2:$B$577,B8) -> 2167251 | D8: =SUMIFS('Monthly Detail'!$O$2:$O$577,'Monthly Detail'!$C$2:$C$577,A8,'Monthly Detail'!$B$2:$B$577,B8) -> 1963995.4 | E8: =D8-C8 -> -203255.55 | F8: =IFERROR(E8/C8,0) -> -0.093784963 | H8: =E8+ROW()/1000000 -> -203255.55
A9: Home & Kitchen | B9: Midwest | C9: =SUMIFS('Monthly Detail'!$I$2:$I$577,'Monthly Detail'!$C$2:$C$577,A9,'Monthly Detail'!$B$2:$B$577,B9) -> 1336444 | D9: =SUMIFS('Monthly Detail'!$O$2:$O$577,'Monthly Detail'!$C$2:$C$577,A9,'Monthly Detail'!$B$2:$B$577,B9) -> 1317665.1 | E9: =D9-C9 -> -18778.927 | F9: =IFERROR(E9/C9,0) -> -0.014051413 | H9: =E9+ROW()/1000000 -> -18778.927
A10: Home & Kitchen | B10: Northeast | C10: =SUMIFS('Monthly Detail'!$I$2:$I$577,'Monthly Detail'!$C$2:$C$577,A10,'Monthly Detail'!$B$2:$B$577,B10) -> 1727361.1 | D10: =SUMIFS('Monthly Detail'!$O$2:$O$577,'Monthly Detail'!$C$2:$C$577,A10,'Monthly Detail'!$B$2:$B$577,B10) -> 1715966 | E10: =D10-C10 -> -11395.122 | F10: =IFERROR(E10/C10,0) -> -0.0065968385 | H10: =E10+ROW()/1000000 -> -11395.122
A11: Home & Kitchen | B11: South | C11: =SUMIFS('Monthly Detail'!$I$2:$I$577,'Monthly Detail'!$C$2:$C$577,A11,'Monthly Detail'!$B$2:$B$577,B11) -> 1723221 | D11: =SUMIFS('Monthly Detail'!$O$2:$O$577,'Monthly Detail'!$C$2:$C$577,A11,'Monthly Detail'!$B$2:$B$577,B11) -> 1717158.1 | E11: =D11-C11 -> -6062.914 | F11: =IFERROR(E11/C11,0) -> -0.0035183612 | H11: =E11+ROW()/1000000 -> -6062.914
A12: Home & Kitchen | B12: West | C12: =SUMIFS('Monthly Detail'!$I$2:$I$577,'Monthly Detail'!$C$2:$C$577,A12,'Monthly Detail'!$B$2:$B$577,B12) -> 1860870 | D12: =SUMIFS('Monthly Detail'!$O$2:$O$577,'Monthly Detail'!$C$2:$C$577,A12,'Monthly Detail'!$B$2:$B$577,B12) -> 1884925.8 | E12: =D12-C12 -> 24055.803 | F12: =IFERROR(E12/C12,0) -> 0.012927181 | H12: =E12+ROW()/1000000 -> 24055.803
A13: Office Supplies | B13: Midwest | C13: =SUMIFS('Monthly Detail'!$I$2:$I$577,'Monthly Detail'!$C$2:$C$577,A13,'Monthly Detail'!$B$2:$B$577,B13) -> 1148097.3 | D13: =SUMIFS('Monthly Detail'!$O$2:$O$577,'Monthly Detail'!$C$2:$C$577,A13,'Monthly Detail'!$B$2:$B$577,B13) -> 1168841.8 | E13: =D13-C13 -> 20744.439 | F13: =IFERROR(E13/C13,0) -> 0.018068537 | H13: =E13+ROW()/1000000 -> 20744.439
A14: Office Supplies | B14: Northeast | C14: =SUMIFS('Monthly Detail'!$I$2:$I$577,'Monthly Detail'!$C$2:$C$577,A14,'Monthly Detail'!$B$2:$B$577,B14) -> 1232717.6 | D14: =SUMIFS('Monthly Detail'!$O$2:$O$577,'Monthly Detail'!$C$2:$C$577,A14,'Monthly Detail'!$B$2:$B$577,B14) -> 1258348.9 | E14: =D14-C14 -> 25631.311 | F14: =IFERROR(E14/C14,0) -> 0.020792525 | H14: =E14+ROW()/1000000 -> 25631.311
A15: Office Supplies | B15: South | C15: =SUMIFS('Monthly Detail'!$I$2:$I$577,'Monthly Detail'!$C$2:$C$577,A15,'Monthly Detail'!$B$2:$B$577,B15) -> 1556227.6 | D15: =SUMIFS('Monthly Detail'!$O$2:$O$577,'Monthly Detail'!$C$2:$C$577,A15,'Monthly Detail'!$B$2:$B$577,B15) -> 1562236.6 | E15: =D15-C15 -> 6008.9414 | F15: =IFERROR(E15/C15,0) -> 0.0038612226 | H15: =E15+ROW()/1000000 -> 6008.9414
A16: Office Supplies | B16: West | C16: =SUMIFS('Monthly Detail'!$I$2:$I$577,'Monthly Detail'!$C$2:$C$577,A16,'Monthly Detail'!$B$2:$B$577,B16) -> 1846654.3 | D16: =SUMIFS('Monthly Detail'!$O$2:$O$577,'Monthly Detail'!$C$2:$C$577,A16,'Monthly Detail'!$B$2:$B$577,B16) -> 1832904.2 | E16: =D16-C16 -> -13750.192 | F16: =IFERROR(E16/C16,0) -> -0.0074460023 | H16: =E16+ROW()/1000000 -> -13750.192
... A28: Pet Supplies | B28: West | C28: =SUMIFS('Monthly Detail'!$I$2:$I$577,'Monthly Detail'!$C$2:$C$577,A28,'Monthly Detail'!$B$2:$B$577,B28) -> 1490963.5 | D28: =SUMIFS('Monthly Detail'!$O$2:$O$577,'Monthly Detail'!$C$2:$C$577,A28,'Monthly Detail'!$B$2:$B$577,B28) -> 1495901 | E28: =D28-C28 -> 4937.5267 | F28: =IFERROR(E28/C28,0) -> 0.0033116349 | H28: =E28+ROW()/1000000 -> 4937.5267
A31: Variance $ Matrix
A32: Category | B32: Midwest | C32: Northeast | D32: South | E32: West
A33: Electronics Accessories | B33: =E5 -> 4725.8154 | C33: =E6 -> -107797.79 | D33: =E7 -> 12459.841 | E33: =E8 -> -203255.55
A34: Home & Kitchen | B34: =E9 -> -18778.927 | C34: =E10 -> -11395.122 | D34: =E11 -> -6062.914 | E34: =E12 -> 24055.803
A35: Office Supplies | B35: =E13 -> 20744.439 | C35: =E14 -> 25631.311 | D35: =E15 -> 6008.9414 | E35: =E16 -> -13750.192
A36: Outdoor & Sporting | B36: =E17 -> -30786.086 | C36: =E18 -> -8112.9377 | D36: =E19 -> -59198.84 | E36: =E20 -> 2191.8663
A37: Personal Care | B37: =E21 -> 22898.07 | C37: =E22 -> 7970.0408 | D37: =E23 -> -15643.554 | E37: =E24 -> 7455.3053
A38: Pet Supplies | B38: =E25 -> 5932.0258 | C38: =E26 -> -3338.1881 | D38: =E27 -> 451.99322 | E38: =E28 -> 4937.5267

Sheet Margin Bridge
A1: Margin Bridge — Budget Profit to Actual Profit (24 months, network-wide)
A2: Each effect isolates one lever, holding the others at budget/actual as noted — the three effects sum exactly to total variance.
A4: Step | B4: Amount
A5: Budget Profit | B5: =SUM('Monthly Detail'!I2:I577) -> 35503414
A6: Volume/Revenue Effect | B6: =SUM('Monthly Detail'!Q2:Q577) -> 38621.956
A7: Discount Effect | B7: =SUM('Monthly Detail'!R2:R577) -> -68136.923
A8: COGS Effect | B8: =SUM('Monthly Detail'!S2:S577) -> -303142.16
A9: Actual Profit | B9: =B5+B6+B7+B8 -> 35170757

Sheet Top Variance Drivers
A1: Top 8 Variance Drivers (most negative first)
A2: Ranked with SMALL() over a tie-broken key, pulled back with INDEX/MATCH — no manual sorting.
A4: Rank | B4: Category | C4: Region | D4: Variance $ | E4: Variance % | F4: Chart Label
A5: 1 | B5: =INDEX('Region x Category Summary'!$A$5:$A$28,MATCH(SMALL('Region x Category Summary'!$H$5:$H$28,1),'Region x Category Summary'!$H$5:$H$28,0)) -> Electronics Accessories | C5: =INDEX('Region x Category Summary'!$B$5:$B$28,MATCH(SMALL('Region x Category Summary'!$H$5:$H$28,1),'Region x Category Summary'!$H$5:$H$28,0)) -> West | D5: =INDEX('Region x Category Summary'!$E$5:$E$28,MATCH(SMALL('Region x Category Summary'!$H$5:$H$28,1),'Region x Category Summary'!$H$5:$H$28,0)) -> -203255.55 | E5: =INDEX('Region x Category Summary'!$F$5:$F$28,MATCH(SMALL('Region x Category Summary'!$H$5:$H$28,1),'Region x Category Summary'!$H$5:$H$28,0)) -> -0.093784963 | F5: =B5&" - "&C5 -> Electronics Accessories - West
A6: 2 | B6: =INDEX('Region x Category Summary'!$A$5:$A$28,MATCH(SMALL('Region x Category Summary'!$H$5:$H$28,2),'Region x Category Summary'!$H$5:$H$28,0)) -> Electronics Accessories | C6: =INDEX('Region x Category Summary'!$B$5:$B$28,MATCH(SMALL('Region x Category Summary'!$H$5:$H$28,2),'Region x Category Summary'!$H$5:$H$28,0)) -> Northeast | D6: =INDEX('Region x Category Summary'!$E$5:$E$28,MATCH(SMALL('Region x Category Summary'!$H$5:$H$28,2),'Region x Category Summary'!$H$5:$H$28,0)) -> -107797.79 | E6: =INDEX('Region x Category Summary'!$F$5:$F$28,MATCH(SMALL('Region x Category Summary'!$H$5:$H$28,2),'Region x Category Summary'!$H$5:$H$28,0)) -> -0.066474277 | F6: =B6&" - "&C6 -> Electronics Accessories - Northeast
A7: 3 | B7: =INDEX('Region x Category Summary'!$A$5:$A$28,MATCH(SMALL('Region x Category Summary'!$H$5:$H$28,3),'Region x Category Summary'!$H$5:$H$28,0)) -> Outdoor & Sporting | C7: =INDEX('Region x Category Summary'!$B$5:$B$28,MATCH(SMALL('Region x Category Summary'!$H$5:$H$28,3),'Region x Category Summary'!$H$5:$H$28,0)) -> South | D7: =INDEX('Region x Category Summary'!$E$5:$E$28,MATCH(SMALL('Region x Category Summary'!$H$5:$H$28,3),'Region x Category Summary'!$H$5:$H$28,0)) -> -59198.84 | E7: =INDEX('Region x Category Summary'!$F$5:$F$28,MATCH(SMALL('Region x Category Summary'!$H$5:$H$28,3),'Region x Category Summary'!$H$5:$H$28,0)) -> -0.059795855 | F7: =B7&" - "&C7 -> Outdoor & Sporting - South
A8: 4 | B8: =INDEX('Region x Category Summary'!$A$5:$A$28,MATCH(SMALL('Region x Category Summary'!$H$5:$H$28,4),'Region x Category Summary'!$H$5:$H$28,0)) -> Outdoor & Sporting | C8: =INDEX('Region x Category Summary'!$B$5:$B$28,MATCH(SMALL('Region x Category Summary'!$H$5:$H$28,4),'Region x Category Summary'!$H$5:$H$28,0)) -> Midwest | D8: =INDEX('Region x Category Summary'!$E$5:$E$28,MATCH(SMALL('Region x Category Summary'!$H$5:$H$28,4),'Region x Category Summary'!$H$5:$H$28,0)) -> -30786.086 | E8: =INDEX('Region x Category Summary'!$F$5:$F$28,MATCH(SMALL('Region x Category Summary'!$H$5:$H$28,4),'Region x Category Summary'!$H$5:$H$28,0)) -> -0.034202019 | F8: =B8&" - "&C8 -> Outdoor & Sporting - Midwest
A9: 5 | B9: =INDEX('Region x Category Summary'!$A$5:$A$28,MATCH(SMALL('Region x Category Summary'!$H$5:$H$28,5),'Region x Category Summary'!$H$5:$H$28,0)) -> Home & Kitchen | C9: =INDEX('Region x Category Summary'!$B$5:$B$28,MATCH(SMALL('Region x Category Summary'!$H$5:$H$28,5),'Region x Category Summary'!$H$5:$H$28,0)) -> Midwest | D9: =INDEX('Region x Category Summary'!$E$5:$E$28,MATCH(SMALL('Region x Category Summary'!$H$5:$H$28,5),'Region x Category Summary'!$H$5:$H$28,0)) -> -18778.927 | E9: =INDEX('Region x Category Summary'!$F$5:$F$28,MATCH(SMALL('Region x Category Summary'!$H$5:$H$28,5),'Region x Category Summary'!$H$5:$H$28,0)) -> -0.014051413 | F9: =B9&" - "&C9 -> Home & Kitchen - Midwest
A10: 6 | B10: =INDEX('Region x Category Summary'!$A$5:$A$28,MATCH(SMALL('Region x Category Summary'!$H$5:$H$28,6),'Region x Category Summary'!$H$5:$H$28,0)) -> Personal Care | C10: =INDEX('Region x Category Summary'!$B$5:$B$28,MATCH(SMALL('Region x Category Summary'!$H$5:$H$28,6),'Region x Category Summary'!$H$5:$H$28,0)) -> South | D10: =INDEX('Region x Category Summary'!$E$5:$E$28,MATCH(SMALL('Region x Category Summary'!$H$5:$H$28,6),'Region x Category Summary'!$H$5:$H$28,0)) -> -15643.554 | E10: =INDEX('Region x Category Summary'!$F$5:$F$28,MATCH(SMALL('Region x Category Summary'!$H$5:$H$28,6),'Region x Category Summary'!$H$5:$H$28,0)) -> -0.0086340893 | F10: =B10&" - "&C10 -> Personal Care - South
A11: 7 | B11: =INDEX('Region x Category Summary'!$A$5:$A$28,MATCH(SMALL('Region x Category Summary'!$H$5:$H$28,7),'Region x Category Summary'!$H$5:$H$28,0)) -> Office Supplies | C11: =INDEX('Region x Category Summary'!$B$5:$B$28,MATCH(SMALL('Region x Category Summary'!$H$5:$H$28,7),'Region x Category Summary'!$H$5:$H$28,0)) -> West | D11: =INDEX('Region x Category Summary'!$E$5:$E$28,MATCH(SMALL('Region x Category Summary'!$H$5:$H$28,7),'Region x Category Summary'!$H$5:$H$28,0)) -> -13750.192 | E11: =INDEX('Region x Category Summary'!$F$5:$F$28,MATCH(SMALL('Region x Category Summary'!$H$5:$H$28,7),'Region x Category Summary'!$H$5:$H$28,0)) -> -0.0074460023 | F11: =B11&" - "&C11 -> Office Supplies - West
A12: 8 | B12: =INDEX('Region x Category Summary'!$A$5:$A$28,MATCH(SMALL('Region x Category Summary'!$H$5:$H$28,8),'Region x Category Summary'!$H$5:$H$28,0)) -> Home & Kitchen | C12: =INDEX('Region x Category Summary'!$B$5:$B$28,MATCH(SMALL('Region x Category Summary'!$H$5:$H$28,8),'Region x Category Summary'!$H$5:$H$28,0)) -> Northeast | D12: =INDEX('Region x Category Summary'!$E$5:$E$28,MATCH(SMALL('Region x Category Summary'!$H$5:$H$28,8),'Region x Category Summary'!$H$5:$H$28,0)) -> -11395.122 | E12: =INDEX('Region x Category Summary'!$F$5:$F$28,MATCH(SMALL('Region x Category Summary'!$H$5:$H$28,8),'Region x Category Summary'!$H$5:$H$28,0)) -> -0.0065968385 | F12: =B12&" - "&C12 -> Home & Kitchen - Northeast
