Workbook

Sheet README
A1: Interactive Budget Workbook — 24-Month Scenario Model
A3: This workbook models a 24-month (2026-2027) budget with a live scenario toggle.
A4: Change the dropdown on the Assumptions tab and every number on Budget Model recalculates —
A5: no copy-pasting between scenarios.
A7: How to use it:
A8: 1. Go to Assumptions and pick a scenario from the dropdown in cell B3.
A9: 2. Budget Model shows the full 24-month P&L for whichever scenario is selected.
A10: 3. Scenario Comparison shows all three scenarios side by side at once, independent
A11: of the toggle, so you don't have to flip through one at a time to compare them.
A13: Color legend:
A14: Blue text an input you can change (assumptions, scenario drivers)
A15: Yellow fill the scenario selector, and other key assumptions worth double-checking
... A22: Scenario Comparison all three scenarios side by side, with a chart

Sheet Assumptions
A1: Budget Assumptions
A3: Scenario: | B3: Base
A5: Shared Assumptions (all scenarios)
A6: Starting Monthly Revenue ($) | B6: 400000
A7: Starting Headcount | B7: 18
A8: Fixed Opex per Month ($) | B8: 45000
A10: Scenario Definitions
A11: Scenario | B11: Monthly Growth Rate | C11: Gross Margin % | D11: Headcount Adds / Qtr | E11: Cost per Head / Month ($)
A12: Conservative | B12: 0.01 | C12: 0.62 | D12: 0 | E12: 9500
A13: Base | B13: 0.025 | C13: 0.65 | D13: 1 | E13: 9500
A14: Aggressive | B14: 0.045 | C14: 0.68 | D14: 3 | E14: 9500
A16: Active Scenario Drivers (auto-updates from B3)
A17: Monthly Growth Rate | B17: =INDEX(B12:B14,MATCH($B$3,$A$12:$A$14,0)) -> 0.025
A18: Gross Margin % | B18: =INDEX(C12:C14,MATCH($B$3,$A$12:$A$14,0)) -> 0.65
A19: Headcount Adds / Qtr | B19: =INDEX(D12:D14,MATCH($B$3,$A$12:$A$14,0)) -> 1
A20: Cost per Head / Month ($) | B20: =INDEX(E12:E14,MATCH($B$3,$A$12:$A$14,0)) -> 9500

Sheet Budget Model
A1: Budget Model — Active Scenario
A2: Active Scenario: | B2: =Assumptions!$B$3 -> Base
A4: Month | B4: Jan-26 | C4: Feb-26 | D4: Mar-26 | E4: Apr-26 | F4: May-26 | G4: Jun-26 | H4: Jul-26 | I4: Aug-26 | J4: Sep-26 | K4: Oct-26 | L4: Nov-26 | M4: Dec-26 | N4: Jan-27 | O4: Feb-27 | P4: Mar-27 | Q4: Apr-27 | R4: May-27 | S4: Jun-27 | T4: Jul-27 | U4: Aug-27 | V4: Sep-27 | W4: Oct-27 | X4: Nov-27 | Y4: Dec-27
A5: Month # | B5: 1 | C5: 2 | D5: 3 | E5: 4 | F5: 5 | G5: 6 | H5: 7 | I5: 8 | J5: 9 | K5: 10 | L5: 11 | M5: 12 | N5: 13 | O5: 14 | P5: 15 | Q5: 16 | R5: 17 | S5: 18 | T5: 19 | U5: 20 | V5: 21 | W5: 22 | X5: 23 | Y5: 24
A6: Headcount | B6: =Assumptions!$B$7+Assumptions!$B$19*(ROUNDUP(B$5/3,0)-1) -> 18 | C6: =Assumptions!$B$7+Assumptions!$B$19*(ROUNDUP(C$5/3,0)-1) -> 18 | D6: =Assumptions!$B$7+Assumptions!$B$19*(ROUNDUP(D$5/3,0)-1) -> 18 | E6: =Assumptions!$B$7+Assumptions!$B$19*(ROUNDUP(E$5/3,0)-1) -> 19 | F6: =Assumptions!$B$7+Assumptions!$B$19*(ROUNDUP(F$5/3,0)-1) -> 19 | G6: =Assumptions!$B$7+Assumptions!$B$19*(ROUNDUP(G$5/3,0)-1) -> 19 | H6: =Assumptions!$B$7+Assumptions!$B$19*(ROUNDUP(H$5/3,0)-1) -> 20 | I6: =Assumptions!$B$7+Assumptions!$B$19*(ROUNDUP(I$5/3,0)-1) -> 20 | ... Y6: =Assumptions!$B$7+Assumptions!$B$19*(ROUNDUP(Y$5/3,0)-1) -> 25
A7: Revenue ($) | B7: =Assumptions!$B$6 -> 400000 | C7: =B$7*(1+Assumptions!$B$17) -> 410000 | D7: =C$7*(1+Assumptions!$B$17) -> 420250 | E7: =D$7*(1+Assumptions!$B$17) -> 430756.25 | F7: =E$7*(1+Assumptions!$B$17) -> 441525.16 | G7: =F$7*(1+Assumptions!$B$17) -> 452563.29 | H7: =G$7*(1+Assumptions!$B$17) -> 463877.37 | I7: =H$7*(1+Assumptions!$B$17) -> 475474.3 | J7: =I$7*(1+Assumptions!$B$17) -> 487361.16 | ... Y7: =X$7*(1+Assumptions!$B$17) -> 705844.27
A8: COGS ($) | B8: =B$7*(1-Assumptions!$B$18) -> 140000 | C8: =C$7*(1-Assumptions!$B$18) -> 143500 | D8: =D$7*(1-Assumptions!$B$18) -> 147087.5 | E8: =E$7*(1-Assumptions!$B$18) -> 150764.69 | F8: =F$7*(1-Assumptions!$B$18) -> 154533.8 | G8: =G$7*(1-Assumptions!$B$18) -> 158397.15 | H8: =H$7*(1-Assumptions!$B$18) -> 162357.08 | I8: =I$7*(1-Assumptions!$B$18) -> 166416.01 | ... Y8: =Y$7*(1-Assumptions!$B$18) -> 247045.5
A9: Gross Profit ($) | B9: =B$7-B$8 -> 260000 | C9: =C$7-C$8 -> 266500 | D9: =D$7-D$8 -> 273162.5 | E9: =E$7-E$8 -> 279991.56 | F9: =F$7-F$8 -> 286991.35 | G9: =G$7-G$8 -> 294166.14 | H9: =H$7-H$8 -> 301520.29 | I9: =I$7-I$8 -> 309058.3 | ... Y9: =Y$7-Y$8 -> 458798.78
A10: Opex ($) | B10: =Assumptions!$B$8+B$6*Assumptions!$B$20 -> 216000 | C10: =Assumptions!$B$8+C$6*Assumptions!$B$20 -> 216000 | D10: =Assumptions!$B$8+D$6*Assumptions!$B$20 -> 216000 | E10: =Assumptions!$B$8+E$6*Assumptions!$B$20 -> 225500 | F10: =Assumptions!$B$8+F$6*Assumptions!$B$20 -> 225500 | G10: =Assumptions!$B$8+G$6*Assumptions!$B$20 -> 225500 | H10: =Assumptions!$B$8+H$6*Assumptions!$B$20 -> 235000 | I10: =Assumptions!$B$8+I$6*Assumptions!$B$20 -> 235000 | ... Y10: =Assumptions!$B$8+Y$6*Assumptions!$B$20 -> 282500
A11: EBITDA ($) | B11: =B$9-B$10 -> 44000 | C11: =C$9-C$10 -> 50500 | D11: =D$9-D$10 -> 57162.5 | E11: =E$9-E$10 -> 54491.562 | F11: =F$9-F$10 -> 61491.352 | G11: =G$9-G$10 -> 68666.135 | H11: =H$9-H$10 -> 66520.289 | I11: =I$9-I$10 -> 74058.296 | ... Y11: =Y$9-Y$10 -> 176298.78
A12: EBITDA Margin % | B12: =IFERROR(B$11/B$7,0) -> 0.11 | C12: =IFERROR(C$11/C$7,0) -> 0.12317073 | D12: =IFERROR(D$11/D$7,0) -> 0.13602023 | E12: =IFERROR(E$11/E$7,0) -> 0.12650208 | F12: =IFERROR(F$11/F$7,0) -> 0.13927032 | G12: =IFERROR(G$11/G$7,0) -> 0.15172715 | H12: =IFERROR(H$11/H$7,0) -> 0.14340059 | I12: =IFERROR(I$11/I$7,0) -> 0.15575667 | ... Y12: =IFERROR(Y$11/Y$7,0) -> 0.24977008
A14: Annual Summary
B15: Year 1 (2026) | C15: Year 2 (2027)
A16: Revenue ($) | B16: =SUM(B7:M7) -> 5518221.2 | C16: =SUM(N7:Y7) -> 7421394
A17: EBITDA ($) | B17: =SUM(B11:M11) -> 823843.77 | C17: =SUM(N11:Y11) -> 1604906.1
A18: EBITDA Margin % | B18: =IFERROR(B17/B16,0) -> 0.14929517 | C18: =IFERROR(C17/C16,0) -> 0.216254

Sheet Scenario Comparison
A1: Scenario Comparison — quarterly, all three scenarios at once
A2: Independent of the Assumptions toggle -- each column pulls its own scenario row directly.
C3: Revenue ($) | F3: EBITDA ($)
A4: Quarter | B4: Conservative | C4: Base | D4: Aggressive | E4: Conservative | F4: Base | G4: Aggressive
A5: Q1 | B5: =Assumptions!$B$6*(1+Assumptions!$B$12)^(3-1) -> 408040 | C5: =Assumptions!$B$6*(1+Assumptions!$B$13)^(3-1) -> 420250 | D5: =Assumptions!$B$6*(1+Assumptions!$B$14)^(3-1) -> 436810 | E5: =B5*Assumptions!$C$12-(Assumptions!$B$8+(Assumptions!$B$7+Assumptions!$D$12*(1-1))*Assumptions!$E$12) -> 36984.8 | F5: =C5*Assumptions!$C$13-(Assumptions!$B$8+(Assumptions!$B$7+Assumptions!$D$13*(1-1))*Assumptions!$E$13) -> 57162.5 | G5: =D5*Assumptions!$C$14-(Assumptions!$B$8+(Assumptions!$B$7+Assumptions!$D$14*(1-1))*Assumptions!$E$14) -> 81030.8
A6: Q2 | B6: =Assumptions!$B$6*(1+Assumptions!$B$12)^(6-1) -> 420404.02 | C6: =Assumptions!$B$6*(1+Assumptions!$B$13)^(6-1) -> 452563.29 | D6: =Assumptions!$B$6*(1+Assumptions!$B$14)^(6-1) -> 498472.78 | E6: =B6*Assumptions!$C$12-(Assumptions!$B$8+(Assumptions!$B$7+Assumptions!$D$12*(2-1))*Assumptions!$E$12) -> 44650.492 | F6: =C6*Assumptions!$C$13-(Assumptions!$B$8+(Assumptions!$B$7+Assumptions!$D$13*(2-1))*Assumptions!$E$13) -> 68666.135 | G6: =D6*Assumptions!$C$14-(Assumptions!$B$8+(Assumptions!$B$7+Assumptions!$D$14*(2-1))*Assumptions!$E$14) -> 94461.487
A7: Q3 | B7: =Assumptions!$B$6*(1+Assumptions!$B$12)^(9-1) -> 433142.68 | C7: =Assumptions!$B$6*(1+Assumptions!$B$13)^(9-1) -> 487361.16 | D7: =Assumptions!$B$6*(1+Assumptions!$B$14)^(9-1) -> 568840.25 | E7: =B7*Assumptions!$C$12-(Assumptions!$B$8+(Assumptions!$B$7+Assumptions!$D$12*(3-1))*Assumptions!$E$12) -> 52548.463 | F7: =C7*Assumptions!$C$13-(Assumptions!$B$8+(Assumptions!$B$7+Assumptions!$D$13*(3-1))*Assumptions!$E$13) -> 81784.753 | G7: =D7*Assumptions!$C$14-(Assumptions!$B$8+(Assumptions!$B$7+Assumptions!$D$14*(3-1))*Assumptions!$E$14) -> 113811.37
A8: Q4 | B8: =Assumptions!$B$6*(1+Assumptions!$B$12)^(12-1) -> 446267.34 | C8: =Assumptions!$B$6*(1+Assumptions!$B$13)^(12-1) -> 524834.66 | D8: =Assumptions!$B$6*(1+Assumptions!$B$14)^(12-1) -> 649141.22 | E8: =B8*Assumptions!$C$12-(Assumptions!$B$8+(Assumptions!$B$7+Assumptions!$D$12*(4-1))*Assumptions!$E$12) -> 60685.75 | F8: =C8*Assumptions!$C$13-(Assumptions!$B$8+(Assumptions!$B$7+Assumptions!$D$13*(4-1))*Assumptions!$E$13) -> 96642.531 | G8: =D8*Assumptions!$C$14-(Assumptions!$B$8+(Assumptions!$B$7+Assumptions!$D$14*(4-1))*Assumptions!$E$14) -> 139916.03
A9: Q5 | B9: =Assumptions!$B$6*(1+Assumptions!$B$12)^(15-1) -> 459789.69 | C9: =Assumptions!$B$6*(1+Assumptions!$B$13)^(15-1) -> 565189.53 | D9: =Assumptions!$B$6*(1+Assumptions!$B$14)^(15-1) -> 740777.97 | E9: =B9*Assumptions!$C$12-(Assumptions!$B$8+(Assumptions!$B$7+Assumptions!$D$12*(5-1))*Assumptions!$E$12) -> 69069.605 | F9: =C9*Assumptions!$C$13-(Assumptions!$B$8+(Assumptions!$B$7+Assumptions!$D$13*(5-1))*Assumptions!$E$13) -> 113373.19 | G9: =D9*Assumptions!$C$14-(Assumptions!$B$8+(Assumptions!$B$7+Assumptions!$D$14*(5-1))*Assumptions!$E$14) -> 173729.02
A10: Q6 | B10: =Assumptions!$B$6*(1+Assumptions!$B$12)^(18-1) -> 473721.77 | C10: =Assumptions!$B$6*(1+Assumptions!$B$13)^(18-1) -> 608647.3 | D10: =Assumptions!$B$6*(1+Assumptions!$B$14)^(18-1) -> 845350.72 | E10: =B10*Assumptions!$C$12-(Assumptions!$B$8+(Assumptions!$B$7+Assumptions!$D$12*(6-1))*Assumptions!$E$12) -> 77707.499 | F10: =C10*Assumptions!$C$13-(Assumptions!$B$8+(Assumptions!$B$7+Assumptions!$D$13*(6-1))*Assumptions!$E$13) -> 132120.75 | G10: =D10*Assumptions!$C$14-(Assumptions!$B$8+(Assumptions!$B$7+Assumptions!$D$14*(6-1))*Assumptions!$E$14) -> 216338.49
A11: Q7 | B11: =Assumptions!$B$6*(1+Assumptions!$B$12)^(21-1) -> 488076.02 | C11: =Assumptions!$B$6*(1+Assumptions!$B$13)^(21-1) -> 655446.58 | D11: =Assumptions!$B$6*(1+Assumptions!$B$14)^(21-1) -> 964685.61 | E11: =B11*Assumptions!$C$12-(Assumptions!$B$8+(Assumptions!$B$7+Assumptions!$D$12*(7-1))*Assumptions!$E$12) -> 86607.13 | F11: =C11*Assumptions!$C$13-(Assumptions!$B$8+(Assumptions!$B$7+Assumptions!$D$13*(7-1))*Assumptions!$E$13) -> 153040.27 | G11: =D11*Assumptions!$C$14-(Assumptions!$B$8+(Assumptions!$B$7+Assumptions!$D$14*(7-1))*Assumptions!$E$14) -> 268986.21
A12: Q8 | B12: =Assumptions!$B$6*(1+Assumptions!$B$12)^(24-1) -> 502865.21 | C12: =Assumptions!$B$6*(1+Assumptions!$B$13)^(24-1) -> 705844.27 | D12: =Assumptions!$B$6*(1+Assumptions!$B$14)^(24-1) -> 1100866.5 | E12: =B12*Assumptions!$C$12-(Assumptions!$B$8+(Assumptions!$B$7+Assumptions!$D$12*(8-1))*Assumptions!$E$12) -> 95776.429 | F12: =C12*Assumptions!$C$13-(Assumptions!$B$8+(Assumptions!$B$7+Assumptions!$D$13*(8-1))*Assumptions!$E$13) -> 176298.78 | G12: =D12*Assumptions!$C$14-(Assumptions!$B$8+(Assumptions!$B$7+Assumptions!$D$14*(8-1))*Assumptions!$E$14) -> 333089.25
A14: Year 2 Exit (Q8) Summary
A15: Scenario | B15: Revenue ($) | C15: EBITDA ($) | D15: EBITDA Margin %
A16: Conservative | B16: =B12 -> 502865.21 | C16: =E12 -> 95776.429 | D16: =IFERROR(C16/B16,0) -> 0.19046143
A17: Base | B17: =C12 -> 705844.27 | C17: =F12 -> 176298.78 | D17: =IFERROR(C17/B17,0) -> 0.24977008
A18: Aggressive | B18: =D12 -> 1100866.5 | C18: =G12 -> 333089.25 | D18: =IFERROR(C18/B18,0) -> 0.30257005
