Workbook

Sheet Overview
B2: Case 01 — AP Invoice Cycle-Time Analysis
B4: Supports the Process Improvement Charter. Brightpath Distribution's AP invoice approval process is flat: every invoice $500+ requires the same three sequential approvals regardless of size. This workbook measures the current-state cost of that in one month of observed data, then models a tiered, tool-assisted future state.
B6: Color legend
B7: Blue text | C7: Hardcoded input / assumption you can change
B8: Yellow fill | C8: Key assumption — worth double-checking before relying on the output
B9: Black text | C9: Formula — recalculates automatically
B10: Green text | C10: Link pulled from another sheet
B12: Sheets
B13: • Invoice Sample — 120 observed invoices from one month, current-state process
B14: • Bottleneck Analysis — where the time actually goes, by stage and by tier
B15: • Future-State Model — tiered approvals + routing tool, projected row by row
B16: • Summary — headline before/after KPIs

Sheet Invoice Sample
A1: Invoice ID | B1: Vendor | C1: Vendor Type | D1: Department | E1: Amount | F1: Payment Terms | G1: Days: Data Entry | H1: Days: Dept Mgr Approval | I1: Days: Finance Mgr Approval | J1: Days: Controller Approval | K1: Days: Payment Processing | L1: Total Cycle Days | M1: Tier | N1: Discount Eligible? | O1: Discount Captured? | P1: Late Fee Incurred? | Q1: Discount $ Missed | R1: Late Fee $ Incurred
A2: INV-2031 | B2: Cascade Freight Partners | C2: Recurring | D2: Sales & Marketing | E2: 13377.69 | F2: Net 30 | G2: 1.3 | H2: 6.3 | I2: 5.1 | J2: 4.6 | K2: 1.4 | L2: =SUM(G2:K2) -> 18.7 | M2: =IF(E2<500,"Tier 0 (<$500)",IF(E2<10000,"Tier 1 ($500-$10K)",IF(E2<50000,"Tier 2 ($10K-$50K)","Tier 3 (>$50K)"))) -> Tier 2 ($10K-$50K) | N2: =IF(F2="2/10 Net 30","Yes","No") -> No | O2: =IF(AND(N2="Yes",(G2+H2+I2+J2)<=10),"Yes","No") -> No | P2: =IF(L2>30,"Yes","No") -> No | Q2: =IF(AND(N2="Yes",O2="No"),E2*0.02,0) -> 0 | R2: =IF(P2="Yes",E2*0.015,0) -> 0
A3: INV-2032 | B3: Meridian Cleaning Supply | C3: Recurring | D3: Fleet & Logistics | E3: 9287.72 | F3: Net 30 | G3: 0.7 | H3: 5.1 | I3: 3.5 | J3: 1.6 | K3: 0.7 | L3: =SUM(G3:K3) -> 11.6 | M3: =IF(E3<500,"Tier 0 (<$500)",IF(E3<10000,"Tier 1 ($500-$10K)",IF(E3<50000,"Tier 2 ($10K-$50K)","Tier 3 (>$50K)"))) -> Tier 1 ($500-$10K) | N3: =IF(F3="2/10 Net 30","Yes","No") -> No | O3: =IF(AND(N3="Yes",(G3+H3+I3+J3)<=10),"Yes","No") -> No | P3: =IF(L3>30,"Yes","No") -> No | Q3: =IF(AND(N3="Yes",O3="No"),E3*0.02,0) -> 0 | R3: =IF(P3="Yes",E3*0.015,0) -> 0
A4: INV-2033 | B4: Blackstone Facility Repair | C4: One-off | D4: Warehouse Ops | E4: 29465.85 | F4: Net 30 | G4: 1.7 | H4: 2.5 | I4: 0.6 | J4: 4.4 | K4: 0.8 | L4: =SUM(G4:K4) -> 10 | M4: =IF(E4<500,"Tier 0 (<$500)",IF(E4<10000,"Tier 1 ($500-$10K)",IF(E4<50000,"Tier 2 ($10K-$50K)","Tier 3 (>$50K)"))) -> Tier 2 ($10K-$50K) | N4: =IF(F4="2/10 Net 30","Yes","No") -> No | O4: =IF(AND(N4="Yes",(G4+H4+I4+J4)<=10),"Yes","No") -> No | P4: =IF(L4>30,"Yes","No") -> No | Q4: =IF(AND(N4="Yes",O4="No"),E4*0.02,0) -> 0 | R4: =IF(P4="Yes",E4*0.015,0) -> 0
A5: INV-2034 | B5: Norwood Uniform Services | C5: Recurring | D5: Facilities | E5: 705.29 | F5: Net 30 | G5: 1.3 | H5: 3.8 | I5: 2.2 | J5: 1.3 | K5: 0.9 | L5: =SUM(G5:K5) -> 9.5 | M5: =IF(E5<500,"Tier 0 (<$500)",IF(E5<10000,"Tier 1 ($500-$10K)",IF(E5<50000,"Tier 2 ($10K-$50K)","Tier 3 (>$50K)"))) -> Tier 1 ($500-$10K) | N5: =IF(F5="2/10 Net 30","Yes","No") -> No | O5: =IF(AND(N5="Yes",(G5+H5+I5+J5)<=10),"Yes","No") -> No | P5: =IF(L5>30,"Yes","No") -> No | Q5: =IF(AND(N5="Yes",O5="No"),E5*0.02,0) -> 0 | R5: =IF(P5="Yes",E5*0.015,0) -> 0
A6: INV-2035 | B6: Delmar Industrial Supply | C6: Recurring | D6: Sales & Marketing | E6: 384.61 | F6: Net 30 | G6: 1.5 | H6: 3.3 | I6: 0 | J6: 0 | K6: 0.6 | L6: =SUM(G6:K6) -> 5.4 | M6: =IF(E6<500,"Tier 0 (<$500)",IF(E6<10000,"Tier 1 ($500-$10K)",IF(E6<50000,"Tier 2 ($10K-$50K)","Tier 3 (>$50K)"))) -> Tier 0 (<$500) | N6: =IF(F6="2/10 Net 30","Yes","No") -> No | O6: =IF(AND(N6="Yes",(G6+H6+I6+J6)<=10),"Yes","No") -> No | P6: =IF(L6>30,"Yes","No") -> No | Q6: =IF(AND(N6="Yes",O6="No"),E6*0.02,0) -> 0 | R6: =IF(P6="Yes",E6*0.015,0) -> 0
A7: INV-2036 | B7: Cascade Freight Partners | C7: Recurring | D7: Sales & Marketing | E7: 75964.56 | F7: Net 30 | G7: 1.5 | H7: 2.7 | I7: 5.2 | J7: 4.6 | K7: 1 | L7: =SUM(G7:K7) -> 15 | M7: =IF(E7<500,"Tier 0 (<$500)",IF(E7<10000,"Tier 1 ($500-$10K)",IF(E7<50000,"Tier 2 ($10K-$50K)","Tier 3 (>$50K)"))) -> Tier 3 (>$50K) | N7: =IF(F7="2/10 Net 30","Yes","No") -> No | O7: =IF(AND(N7="Yes",(G7+H7+I7+J7)<=10),"Yes","No") -> No | P7: =IF(L7>30,"Yes","No") -> No | Q7: =IF(AND(N7="Yes",O7="No"),E7*0.02,0) -> 0 | R7: =IF(P7="Yes",E7*0.015,0) -> 0
A8: INV-2037 | B8: Overton Safety Gear | C8: Recurring | D8: Finance | E8: 16584.15 | F8: 2/10 Net 30 | G8: 0.8 | H8: 2.1 | I8: 4.1 | J8: 6.5 | K8: 1 | L8: =SUM(G8:K8) -> 14.5 | M8: =IF(E8<500,"Tier 0 (<$500)",IF(E8<10000,"Tier 1 ($500-$10K)",IF(E8<50000,"Tier 2 ($10K-$50K)","Tier 3 (>$50K)"))) -> Tier 2 ($10K-$50K) | N8: =IF(F8="2/10 Net 30","Yes","No") -> Yes | O8: =IF(AND(N8="Yes",(G8+H8+I8+J8)<=10),"Yes","No") -> No | P8: =IF(L8>30,"Yes","No") -> No | Q8: =IF(AND(N8="Yes",O8="No"),E8*0.02,0) -> 331.683 | R8: =IF(P8="Yes",E8*0.015,0) -> 0
A9: INV-2038 | B9: Blackstone Facility Repair | C9: One-off | D9: Sales & Marketing | E9: 22636.85 | F9: Net 30 | G9: 1.5 | H9: 5.9 | I9: 4.4 | J9: 6.5 | K9: 1.1 | L9: =SUM(G9:K9) -> 19.4 | M9: =IF(E9<500,"Tier 0 (<$500)",IF(E9<10000,"Tier 1 ($500-$10K)",IF(E9<50000,"Tier 2 ($10K-$50K)","Tier 3 (>$50K)"))) -> Tier 2 ($10K-$50K) | N9: =IF(F9="2/10 Net 30","Yes","No") -> No | O9: =IF(AND(N9="Yes",(G9+H9+I9+J9)<=10),"Yes","No") -> No | P9: =IF(L9>30,"Yes","No") -> No | Q9: =IF(AND(N9="Yes",O9="No"),E9*0.02,0) -> 0 | R9: =IF(P9="Yes",E9*0.015,0) -> 0
A10: INV-2039 | B10: Juniper Equipment Rental | C10: One-off | D10: Fleet & Logistics | E10: 131.44 | F10: Net 30 | G10: 1.5 | H10: 3.5 | I10: 0 | J10: 0 | K10: 1.4 | L10: =SUM(G10:K10) -> 6.4 | M10: =IF(E10<500,"Tier 0 (<$500)",IF(E10<10000,"Tier 1 ($500-$10K)",IF(E10<50000,"Tier 2 ($10K-$50K)","Tier 3 (>$50K)"))) -> Tier 0 (<$500) | N10: =IF(F10="2/10 Net 30","Yes","No") -> No | O10: =IF(AND(N10="Yes",(G10+H10+I10+J10)<=10),"Yes","No") -> No | P10: =IF(L10>30,"Yes","No") -> No | Q10: =IF(AND(N10="Yes",O10="No"),E10*0.02,0) -> 0 | R10: =IF(P10="Yes",E10*0.015,0) -> 0
A11: INV-2040 | B11: Blackstone Facility Repair | C11: One-off | D11: Fleet & Logistics | E11: 3447.76 | F11: Net 30 | G11: 1.5 | H11: 4.1 | I11: 3.6 | J11: 4.5 | K11: 1.4 | L11: =SUM(G11:K11) -> 15.1 | M11: =IF(E11<500,"Tier 0 (<$500)",IF(E11<10000,"Tier 1 ($500-$10K)",IF(E11<50000,"Tier 2 ($10K-$50K)","Tier 3 (>$50K)"))) -> Tier 1 ($500-$10K) | N11: =IF(F11="2/10 Net 30","Yes","No") -> No | O11: =IF(AND(N11="Yes",(G11+H11+I11+J11)<=10),"Yes","No") -> No | P11: =IF(L11>30,"Yes","No") -> No | Q11: =IF(AND(N11="Yes",O11="No"),E11*0.02,0) -> 0 | R11: =IF(P11="Yes",E11*0.015,0) -> 0
A12: INV-2041 | B12: Ashford Packaging Co. | C12: Recurring | D12: IT | E12: 1657.29 | F12: Net 30 | G12: 0.9 | H12: 2.1 | I12: 2.5 | J12: 3.5 | K12: 1.3 | L12: =SUM(G12:K12) -> 10.3 | M12: =IF(E12<500,"Tier 0 (<$500)",IF(E12<10000,"Tier 1 ($500-$10K)",IF(E12<50000,"Tier 2 ($10K-$50K)","Tier 3 (>$50K)"))) -> Tier 1 ($500-$10K) | N12: =IF(F12="2/10 Net 30","Yes","No") -> No | O12: =IF(AND(N12="Yes",(G12+H12+I12+J12)<=10),"Yes","No") -> No | P12: =IF(L12>30,"Yes","No") -> No | Q12: =IF(AND(N12="Yes",O12="No"),E12*0.02,0) -> 0 | R12: =IF(P12="Yes",E12*0.015,0) -> 0
A13: INV-2042 | B13: Meridian Cleaning Supply | C13: Recurring | D13: Warehouse Ops | E13: 14950.03 | F13: Net 30 | G13: 1 | H13: 3.6 | I13: 5.3 | J13: 4.9 | K13: 1.4 | L13: =SUM(G13:K13) -> 16.2 | M13: =IF(E13<500,"Tier 0 (<$500)",IF(E13<10000,"Tier 1 ($500-$10K)",IF(E13<50000,"Tier 2 ($10K-$50K)","Tier 3 (>$50K)"))) -> Tier 2 ($10K-$50K) | N13: =IF(F13="2/10 Net 30","Yes","No") -> No | O13: =IF(AND(N13="Yes",(G13+H13+I13+J13)<=10),"Yes","No") -> No | P13: =IF(L13>30,"Yes","No") -> No | Q13: =IF(AND(N13="Yes",O13="No"),E13*0.02,0) -> 0 | R13: =IF(P13="Yes",E13*0.015,0) -> 0
... A121: INV-2150 | B121: Harlow Fasteners Inc. | C121: Recurring | D121: Sales & Marketing | E121: 8318.89 | F121: 2/10 Net 30 | G121: 1.1 | H121: 0.7 | I121: 2.5 | J121: 3.6 | K121: 0.8 | L121: =SUM(G121:K121) -> 8.7 | M121: =IF(E121<500,"Tier 0 (<$500)",IF(E121<10000,"Tier 1 ($500-$10K)",IF(E121<50000,"Tier 2 ($10K-$50K)","Tier 3 (>$50K)"))) -> Tier 1 ($500-$10K) | N121: =IF(F121="2/10 Net 30","Yes","No") -> Yes | O121: =IF(AND(N121="Yes",(G121+H121+I121+J121)<=10),"Yes","No") -> Yes | P121: =IF(L121>30,"Yes","No") -> No | Q121: =IF(AND(N121="Yes",O121="No"),E121*0.02,0) -> 0 | R121: =IF(P121="Yes",E121*0.015,0) -> 0

Sheet Bottleneck Analysis
B2: Bottleneck Analysis — current state
B4: Average days by stage (all invoices unless noted)
B5: Data entry — recurring vendors | E5: =AVERAGEIFS('Invoice Sample'!G2:G121,'Invoice Sample'!C2:C121,"Recurring") -> 1.1872093
B6: Data entry — one-off vendors | E6: =AVERAGEIFS('Invoice Sample'!G2:G121,'Invoice Sample'!C2:C121,"One-off") -> 1.5735294
B7: Dept Mgr approval (all invoices) | E7: =AVERAGE('Invoice Sample'!H2:H121) -> 4.165
B8: Finance Mgr approval ($500+ only) | E8: =AVERAGEIF('Invoice Sample'!E2:E121,">=500",'Invoice Sample'!I2:I121) -> 3.559596
B9: Controller approval ($500+ only) | E9: =AVERAGEIF('Invoice Sample'!E2:E121,">=500",'Invoice Sample'!J2:J121) -> 4.189899
B10: Payment processing | E10: =AVERAGE('Invoice Sample'!K2:K121) -> 0.98
B13: Invoice mix by tier (this sample)
B14: Tier | C14: Count | D14: % of invoices | E14: Avg amount | F14: Avg total cycle days
B15: Tier 0 (<$500) | C15: =COUNTIF('Invoice Sample'!M2:M121,B15) -> 21 | D15: =C15/120 -> 0.175 | E15: =AVERAGEIF('Invoice Sample'!M2:M121,B15,'Invoice Sample'!E2:E121) -> 231.45143 | F15: =AVERAGEIF('Invoice Sample'!M2:M121,B15,'Invoice Sample'!L2:L121) -> 5.7333333
B16: Tier 1 ($500-$10K) | C16: =COUNTIF('Invoice Sample'!M2:M121,B16) -> 69 | D16: =C16/120 -> 0.575 | E16: =AVERAGEIF('Invoice Sample'!M2:M121,B16,'Invoice Sample'!E2:E121) -> 5153.9878 | F16: =AVERAGEIF('Invoice Sample'!M2:M121,B16,'Invoice Sample'!L2:L121) -> 13.953623
B17: Tier 2 ($10K-$50K) | C17: =COUNTIF('Invoice Sample'!M2:M121,B17) -> 25 | D17: =C17/120 -> 0.20833333 | E17: =AVERAGEIF('Invoice Sample'!M2:M121,B17,'Invoice Sample'!E2:E121) -> 29797.542 | F17: =AVERAGEIF('Invoice Sample'!M2:M121,B17,'Invoice Sample'!L2:L121) -> 15.124
B18: Tier 3 (>$50K) | C18: =COUNTIF('Invoice Sample'!M2:M121,B18) -> 5 | D18: =C18/120 -> 0.041666667 | E18: =AVERAGEIF('Invoice Sample'!M2:M121,B18,'Invoice Sample'!E2:E121) -> 93494.742 | F18: =AVERAGEIF('Invoice Sample'!M2:M121,B18,'Invoice Sample'!L2:L121) -> 15.78
B21: Current-state financial leakage (this sample, one month)
B22: Invoices with discount terms missing the 10-day window | E22: =COUNTIFS('Invoice Sample'!N2:N121,"Yes",'Invoice Sample'!O2:O121,"No") -> 36
B23: Discount $ forfeited this month | E23: =SUM('Invoice Sample'!Q2:Q121) -> 10401.238
B24: Invoices that missed Net 30 (late fee triggered) | E24: =COUNTIF('Invoice Sample'!P2:P121,"Yes") -> 0
B25: Late fee $ incurred this month | E25: =SUM('Invoice Sample'!R2:R121) -> 0

Sheet Future-State Model
B2: Future-State Model — tiered approvals + routing tool
B4: Levers (change these to test other scenarios)
B5: Required approvals — Tier 0 (<$500) | F5: Dept Mgr only (unchanged)
B6: Required approvals — Tier 1 ($500-$10K) | F6: Dept Mgr only
B7: Required approvals — Tier 2 ($10K-$50K) | F7: Dept Mgr + Finance Mgr
B8: Required approvals — Tier 3 (>$50K) | F8: Dept Mgr + Finance Mgr + Controller (unchanged)
B10: OCR/auto-capture time reduction — recurring vendors | F10: 0.8
B11: Data-entry time reduction — one-off / new vendors (not OCR-eligible) | F11: 0
B12: Approval queue-time reduction — routing tool + defined backup approvers | F12: 0.42
B13: Payment-processing time reduction — batch scheduling automation | F13: 0.3
B15: Implementation cost (one-time + Year 1)
B16: Routing/workflow tool — annual subscription | F16: 18000
B17: OCR/invoice-capture tool — annual subscription | F17: 9600
B18: One-time implementation & change-management effort | F18: 22000
B20: Projected stage durations
B21: Stage | C21: Current (obs.) | D21: Reduction | E21: Projected
B22: Data entry — recurring | C22: ='Bottleneck Analysis'!E5 -> 1.1872093 | D22: =F10 -> 0.8 | E22: =C22*(1-D22) -> 0.23744186
B23: Data entry — one-off | C23: ='Bottleneck Analysis'!E6 -> 1.5735294 | D23: =F11 -> 0 | E23: =C23*(1-D23) -> 1.5735294
B24: Dept Mgr approval | C24: ='Bottleneck Analysis'!E7 -> 4.165 | D24: =F12 -> 0.42 | E24: =C24*(1-D24) -> 2.4157
B25: Finance Mgr approval | C25: ='Bottleneck Analysis'!E8 -> 3.559596 | D25: =F12 -> 0.42 | E25: =C25*(1-D25) -> 2.0645657
B26: Controller approval | C26: ='Bottleneck Analysis'!E9 -> 4.189899 | D26: =F12 -> 0.42 | E26: =C26*(1-D26) -> 2.4301414
B27: Payment processing | C27: ='Bottleneck Analysis'!E10 -> 0.98 | D27: =F13 -> 0.3 | E27: =C27*(1-D27) -> 0.686

Sheet Future-State Projection
A1: Invoice ID | B1: Vendor Type | C1: Amount | D1: Tier | E1: Payment Terms | F1: Projected Data Entry | G1: Projected Dept Mgr | H1: Projected Finance Mgr | I1: Projected Controller | J1: Projected Payment | K1: Projected Total Cycle Days | L1: Discount Eligible? | M1: Discount Captured (future)? | N1: Late Fee (future)? | O1: Discount $ Now Captured | P1: Late Fee $ Now Avoided
A2: ='Invoice Sample'!A2 -> INV-2031 | B2: ='Invoice Sample'!C2 -> Recurring | C2: ='Invoice Sample'!E2 -> 13377.69 | D2: ='Invoice Sample'!M2 -> Tier 2 ($10K-$50K) | E2: ='Invoice Sample'!F2 -> Net 30 | F2: =IF(B2="Recurring",'Future-State Model'!E22,'Future-State Model'!E23) -> 0.23744186 | G2: ='Future-State Model'!E24 -> 2.4157 | H2: =IF(OR(D2="Tier 2 ($10K-$50K)",D2="Tier 3 (>$50K)"),'Future-State Model'!E25,0) -> 2.0645657 | I2: =IF(D2="Tier 3 (>$50K)",'Future-State Model'!E26,0) -> 0 | J2: ='Future-State Model'!E27 -> 0.686 | K2: =SUM(F2:J2) -> 5.4037075 | L2: =IF(E2="2/10 Net 30","Yes","No") -> No | M2: =IF(AND(L2="Yes",(F2+G2+H2+I2)<=10),"Yes","No") -> No | N2: =IF(K2>30,"Yes","No") -> No | O2: =IF(AND(L2="Yes",'Invoice Sample'!O2="No",M2="Yes"),C2*0.02,0) -> 0 | P2: =IF(AND('Invoice Sample'!P2="Yes",N2="No"),C2*0.015,0) -> 0
A3: ='Invoice Sample'!A3 -> INV-2032 | B3: ='Invoice Sample'!C3 -> Recurring | C3: ='Invoice Sample'!E3 -> 9287.72 | D3: ='Invoice Sample'!M3 -> Tier 1 ($500-$10K) | E3: ='Invoice Sample'!F3 -> Net 30 | F3: =IF(B3="Recurring",'Future-State Model'!E22,'Future-State Model'!E23) -> 0.23744186 | G3: ='Future-State Model'!E24 -> 2.4157 | H3: =IF(OR(D3="Tier 2 ($10K-$50K)",D3="Tier 3 (>$50K)"),'Future-State Model'!E25,0) -> 0 | I3: =IF(D3="Tier 3 (>$50K)",'Future-State Model'!E26,0) -> 0 | J3: ='Future-State Model'!E27 -> 0.686 | K3: =SUM(F3:J3) -> 3.3391419 | L3: =IF(E3="2/10 Net 30","Yes","No") -> No | M3: =IF(AND(L3="Yes",(F3+G3+H3+I3)<=10),"Yes","No") -> No | N3: =IF(K3>30,"Yes","No") -> No | O3: =IF(AND(L3="Yes",'Invoice Sample'!O3="No",M3="Yes"),C3*0.02,0) -> 0 | P3: =IF(AND('Invoice Sample'!P3="Yes",N3="No"),C3*0.015,0) -> 0
A4: ='Invoice Sample'!A4 -> INV-2033 | B4: ='Invoice Sample'!C4 -> One-off | C4: ='Invoice Sample'!E4 -> 29465.85 | D4: ='Invoice Sample'!M4 -> Tier 2 ($10K-$50K) | E4: ='Invoice Sample'!F4 -> Net 30 | F4: =IF(B4="Recurring",'Future-State Model'!E22,'Future-State Model'!E23) -> 1.5735294 | G4: ='Future-State Model'!E24 -> 2.4157 | H4: =IF(OR(D4="Tier 2 ($10K-$50K)",D4="Tier 3 (>$50K)"),'Future-State Model'!E25,0) -> 2.0645657 | I4: =IF(D4="Tier 3 (>$50K)",'Future-State Model'!E26,0) -> 0 | J4: ='Future-State Model'!E27 -> 0.686 | K4: =SUM(F4:J4) -> 6.7397951 | L4: =IF(E4="2/10 Net 30","Yes","No") -> No | M4: =IF(AND(L4="Yes",(F4+G4+H4+I4)<=10),"Yes","No") -> No | N4: =IF(K4>30,"Yes","No") -> No | O4: =IF(AND(L4="Yes",'Invoice Sample'!O4="No",M4="Yes"),C4*0.02,0) -> 0 | P4: =IF(AND('Invoice Sample'!P4="Yes",N4="No"),C4*0.015,0) -> 0
A5: ='Invoice Sample'!A5 -> INV-2034 | B5: ='Invoice Sample'!C5 -> Recurring | C5: ='Invoice Sample'!E5 -> 705.29 | D5: ='Invoice Sample'!M5 -> Tier 1 ($500-$10K) | E5: ='Invoice Sample'!F5 -> Net 30 | F5: =IF(B5="Recurring",'Future-State Model'!E22,'Future-State Model'!E23) -> 0.23744186 | G5: ='Future-State Model'!E24 -> 2.4157 | H5: =IF(OR(D5="Tier 2 ($10K-$50K)",D5="Tier 3 (>$50K)"),'Future-State Model'!E25,0) -> 0 | I5: =IF(D5="Tier 3 (>$50K)",'Future-State Model'!E26,0) -> 0 | J5: ='Future-State Model'!E27 -> 0.686 | K5: =SUM(F5:J5) -> 3.3391419 | L5: =IF(E5="2/10 Net 30","Yes","No") -> No | M5: =IF(AND(L5="Yes",(F5+G5+H5+I5)<=10),"Yes","No") -> No | N5: =IF(K5>30,"Yes","No") -> No | O5: =IF(AND(L5="Yes",'Invoice Sample'!O5="No",M5="Yes"),C5*0.02,0) -> 0 | P5: =IF(AND('Invoice Sample'!P5="Yes",N5="No"),C5*0.015,0) -> 0
A6: ='Invoice Sample'!A6 -> INV-2035 | B6: ='Invoice Sample'!C6 -> Recurring | C6: ='Invoice Sample'!E6 -> 384.61 | D6: ='Invoice Sample'!M6 -> Tier 0 (<$500) | E6: ='Invoice Sample'!F6 -> Net 30 | F6: =IF(B6="Recurring",'Future-State Model'!E22,'Future-State Model'!E23) -> 0.23744186 | G6: ='Future-State Model'!E24 -> 2.4157 | H6: =IF(OR(D6="Tier 2 ($10K-$50K)",D6="Tier 3 (>$50K)"),'Future-State Model'!E25,0) -> 0 | I6: =IF(D6="Tier 3 (>$50K)",'Future-State Model'!E26,0) -> 0 | J6: ='Future-State Model'!E27 -> 0.686 | K6: =SUM(F6:J6) -> 3.3391419 | L6: =IF(E6="2/10 Net 30","Yes","No") -> No | M6: =IF(AND(L6="Yes",(F6+G6+H6+I6)<=10),"Yes","No") -> No | N6: =IF(K6>30,"Yes","No") -> No | O6: =IF(AND(L6="Yes",'Invoice Sample'!O6="No",M6="Yes"),C6*0.02,0) -> 0 | P6: =IF(AND('Invoice Sample'!P6="Yes",N6="No"),C6*0.015,0) -> 0
A7: ='Invoice Sample'!A7 -> INV-2036 | B7: ='Invoice Sample'!C7 -> Recurring | C7: ='Invoice Sample'!E7 -> 75964.56 | D7: ='Invoice Sample'!M7 -> Tier 3 (>$50K) | E7: ='Invoice Sample'!F7 -> Net 30 | F7: =IF(B7="Recurring",'Future-State Model'!E22,'Future-State Model'!E23) -> 0.23744186 | G7: ='Future-State Model'!E24 -> 2.4157 | H7: =IF(OR(D7="Tier 2 ($10K-$50K)",D7="Tier 3 (>$50K)"),'Future-State Model'!E25,0) -> 2.0645657 | I7: =IF(D7="Tier 3 (>$50K)",'Future-State Model'!E26,0) -> 2.4301414 | J7: ='Future-State Model'!E27 -> 0.686 | K7: =SUM(F7:J7) -> 7.8338489 | L7: =IF(E7="2/10 Net 30","Yes","No") -> No | M7: =IF(AND(L7="Yes",(F7+G7+H7+I7)<=10),"Yes","No") -> No | N7: =IF(K7>30,"Yes","No") -> No | O7: =IF(AND(L7="Yes",'Invoice Sample'!O7="No",M7="Yes"),C7*0.02,0) -> 0 | P7: =IF(AND('Invoice Sample'!P7="Yes",N7="No"),C7*0.015,0) -> 0
A8: ='Invoice Sample'!A8 -> INV-2037 | B8: ='Invoice Sample'!C8 -> Recurring | C8: ='Invoice Sample'!E8 -> 16584.15 | D8: ='Invoice Sample'!M8 -> Tier 2 ($10K-$50K) | E8: ='Invoice Sample'!F8 -> 2/10 Net 30 | F8: =IF(B8="Recurring",'Future-State Model'!E22,'Future-State Model'!E23) -> 0.23744186 | G8: ='Future-State Model'!E24 -> 2.4157 | H8: =IF(OR(D8="Tier 2 ($10K-$50K)",D8="Tier 3 (>$50K)"),'Future-State Model'!E25,0) -> 2.0645657 | I8: =IF(D8="Tier 3 (>$50K)",'Future-State Model'!E26,0) -> 0 | J8: ='Future-State Model'!E27 -> 0.686 | K8: =SUM(F8:J8) -> 5.4037075 | L8: =IF(E8="2/10 Net 30","Yes","No") -> Yes | M8: =IF(AND(L8="Yes",(F8+G8+H8+I8)<=10),"Yes","No") -> Yes | N8: =IF(K8>30,"Yes","No") -> No | O8: =IF(AND(L8="Yes",'Invoice Sample'!O8="No",M8="Yes"),C8*0.02,0) -> 331.683 | P8: =IF(AND('Invoice Sample'!P8="Yes",N8="No"),C8*0.015,0) -> 0
A9: ='Invoice Sample'!A9 -> INV-2038 | B9: ='Invoice Sample'!C9 -> One-off | C9: ='Invoice Sample'!E9 -> 22636.85 | D9: ='Invoice Sample'!M9 -> Tier 2 ($10K-$50K) | E9: ='Invoice Sample'!F9 -> Net 30 | F9: =IF(B9="Recurring",'Future-State Model'!E22,'Future-State Model'!E23) -> 1.5735294 | G9: ='Future-State Model'!E24 -> 2.4157 | H9: =IF(OR(D9="Tier 2 ($10K-$50K)",D9="Tier 3 (>$50K)"),'Future-State Model'!E25,0) -> 2.0645657 | I9: =IF(D9="Tier 3 (>$50K)",'Future-State Model'!E26,0) -> 0 | J9: ='Future-State Model'!E27 -> 0.686 | K9: =SUM(F9:J9) -> 6.7397951 | L9: =IF(E9="2/10 Net 30","Yes","No") -> No | M9: =IF(AND(L9="Yes",(F9+G9+H9+I9)<=10),"Yes","No") -> No | N9: =IF(K9>30,"Yes","No") -> No | O9: =IF(AND(L9="Yes",'Invoice Sample'!O9="No",M9="Yes"),C9*0.02,0) -> 0 | P9: =IF(AND('Invoice Sample'!P9="Yes",N9="No"),C9*0.015,0) -> 0
A10: ='Invoice Sample'!A10 -> INV-2039 | B10: ='Invoice Sample'!C10 -> One-off | C10: ='Invoice Sample'!E10 -> 131.44 | D10: ='Invoice Sample'!M10 -> Tier 0 (<$500) | E10: ='Invoice Sample'!F10 -> Net 30 | F10: =IF(B10="Recurring",'Future-State Model'!E22,'Future-State Model'!E23) -> 1.5735294 | G10: ='Future-State Model'!E24 -> 2.4157 | H10: =IF(OR(D10="Tier 2 ($10K-$50K)",D10="Tier 3 (>$50K)"),'Future-State Model'!E25,0) -> 0 | I10: =IF(D10="Tier 3 (>$50K)",'Future-State Model'!E26,0) -> 0 | J10: ='Future-State Model'!E27 -> 0.686 | K10: =SUM(F10:J10) -> 4.6752294 | L10: =IF(E10="2/10 Net 30","Yes","No") -> No | M10: =IF(AND(L10="Yes",(F10+G10+H10+I10)<=10),"Yes","No") -> No | N10: =IF(K10>30,"Yes","No") -> No | O10: =IF(AND(L10="Yes",'Invoice Sample'!O10="No",M10="Yes"),C10*0.02,0) -> 0 | P10: =IF(AND('Invoice Sample'!P10="Yes",N10="No"),C10*0.015,0) -> 0
A11: ='Invoice Sample'!A11 -> INV-2040 | B11: ='Invoice Sample'!C11 -> One-off | C11: ='Invoice Sample'!E11 -> 3447.76 | D11: ='Invoice Sample'!M11 -> Tier 1 ($500-$10K) | E11: ='Invoice Sample'!F11 -> Net 30 | F11: =IF(B11="Recurring",'Future-State Model'!E22,'Future-State Model'!E23) -> 1.5735294 | G11: ='Future-State Model'!E24 -> 2.4157 | H11: =IF(OR(D11="Tier 2 ($10K-$50K)",D11="Tier 3 (>$50K)"),'Future-State Model'!E25,0) -> 0 | I11: =IF(D11="Tier 3 (>$50K)",'Future-State Model'!E26,0) -> 0 | J11: ='Future-State Model'!E27 -> 0.686 | K11: =SUM(F11:J11) -> 4.6752294 | L11: =IF(E11="2/10 Net 30","Yes","No") -> No | M11: =IF(AND(L11="Yes",(F11+G11+H11+I11)<=10),"Yes","No") -> No | N11: =IF(K11>30,"Yes","No") -> No | O11: =IF(AND(L11="Yes",'Invoice Sample'!O11="No",M11="Yes"),C11*0.02,0) -> 0 | P11: =IF(AND('Invoice Sample'!P11="Yes",N11="No"),C11*0.015,0) -> 0
A12: ='Invoice Sample'!A12 -> INV-2041 | B12: ='Invoice Sample'!C12 -> Recurring | C12: ='Invoice Sample'!E12 -> 1657.29 | D12: ='Invoice Sample'!M12 -> Tier 1 ($500-$10K) | E12: ='Invoice Sample'!F12 -> Net 30 | F12: =IF(B12="Recurring",'Future-State Model'!E22,'Future-State Model'!E23) -> 0.23744186 | G12: ='Future-State Model'!E24 -> 2.4157 | H12: =IF(OR(D12="Tier 2 ($10K-$50K)",D12="Tier 3 (>$50K)"),'Future-State Model'!E25,0) -> 0 | I12: =IF(D12="Tier 3 (>$50K)",'Future-State Model'!E26,0) -> 0 | J12: ='Future-State Model'!E27 -> 0.686 | K12: =SUM(F12:J12) -> 3.3391419 | L12: =IF(E12="2/10 Net 30","Yes","No") -> No | M12: =IF(AND(L12="Yes",(F12+G12+H12+I12)<=10),"Yes","No") -> No | N12: =IF(K12>30,"Yes","No") -> No | O12: =IF(AND(L12="Yes",'Invoice Sample'!O12="No",M12="Yes"),C12*0.02,0) -> 0 | P12: =IF(AND('Invoice Sample'!P12="Yes",N12="No"),C12*0.015,0) -> 0
A13: ='Invoice Sample'!A13 -> INV-2042 | B13: ='Invoice Sample'!C13 -> Recurring | C13: ='Invoice Sample'!E13 -> 14950.03 | D13: ='Invoice Sample'!M13 -> Tier 2 ($10K-$50K) | E13: ='Invoice Sample'!F13 -> Net 30 | F13: =IF(B13="Recurring",'Future-State Model'!E22,'Future-State Model'!E23) -> 0.23744186 | G13: ='Future-State Model'!E24 -> 2.4157 | H13: =IF(OR(D13="Tier 2 ($10K-$50K)",D13="Tier 3 (>$50K)"),'Future-State Model'!E25,0) -> 2.0645657 | I13: =IF(D13="Tier 3 (>$50K)",'Future-State Model'!E26,0) -> 0 | J13: ='Future-State Model'!E27 -> 0.686 | K13: =SUM(F13:J13) -> 5.4037075 | L13: =IF(E13="2/10 Net 30","Yes","No") -> No | M13: =IF(AND(L13="Yes",(F13+G13+H13+I13)<=10),"Yes","No") -> No | N13: =IF(K13>30,"Yes","No") -> No | O13: =IF(AND(L13="Yes",'Invoice Sample'!O13="No",M13="Yes"),C13*0.02,0) -> 0 | P13: =IF(AND('Invoice Sample'!P13="Yes",N13="No"),C13*0.015,0) -> 0
A14: ='Invoice Sample'!A14 -> INV-2043 | B14: ='Invoice Sample'!C14 -> Recurring | C14: ='Invoice Sample'!E14 -> 736.14 | D14: ='Invoice Sample'!M14 -> Tier 1 ($500-$10K) | E14: ='Invoice Sample'!F14 -> Net 30 | F14: =IF(B14="Recurring",'Future-State Model'!E22,'Future-State Model'!E23) -> 0.23744186 | G14: ='Future-State Model'!E24 -> 2.4157 | H14: =IF(OR(D14="Tier 2 ($10K-$50K)",D14="Tier 3 (>$50K)"),'Future-State Model'!E25,0) -> 0 | I14: =IF(D14="Tier 3 (>$50K)",'Future-State Model'!E26,0) -> 0 | J14: ='Future-State Model'!E27 -> 0.686 | K14: =SUM(F14:J14) -> 3.3391419 | L14: =IF(E14="2/10 Net 30","Yes","No") -> No | M14: =IF(AND(L14="Yes",(F14+G14+H14+I14)<=10),"Yes","No") -> No | N14: =IF(K14>30,"Yes","No") -> No | O14: =IF(AND(L14="Yes",'Invoice Sample'!O14="No",M14="Yes"),C14*0.02,0) -> 0 | P14: =IF(AND('Invoice Sample'!P14="Yes",N14="No"),C14*0.015,0) -> 0
A15: ='Invoice Sample'!A15 -> INV-2044 | B15: ='Invoice Sample'!C15 -> Recurring | C15: ='Invoice Sample'!E15 -> 42173.63 | D15: ='Invoice Sample'!M15 -> Tier 2 ($10K-$50K) | E15: ='Invoice Sample'!F15 -> Net 30 | F15: =IF(B15="Recurring",'Future-State Model'!E22,'Future-State Model'!E23) -> 0.23744186 | G15: ='Future-State Model'!E24 -> 2.4157 | H15: =IF(OR(D15="Tier 2 ($10K-$50K)",D15="Tier 3 (>$50K)"),'Future-State Model'!E25,0) -> 2.0645657 | I15: =IF(D15="Tier 3 (>$50K)",'Future-State Model'!E26,0) -> 0 | J15: ='Future-State Model'!E27 -> 0.686 | K15: =SUM(F15:J15) -> 5.4037075 | L15: =IF(E15="2/10 Net 30","Yes","No") -> No | M15: =IF(AND(L15="Yes",(F15+G15+H15+I15)<=10),"Yes","No") -> No | N15: =IF(K15>30,"Yes","No") -> No | O15: =IF(AND(L15="Yes",'Invoice Sample'!O15="No",M15="Yes"),C15*0.02,0) -> 0 | P15: =IF(AND('Invoice Sample'!P15="Yes",N15="No"),C15*0.015,0) -> 0
A16: ='Invoice Sample'!A16 -> INV-2045 | B16: ='Invoice Sample'!C16 -> Recurring | C16: ='Invoice Sample'!E16 -> 6256.54 | D16: ='Invoice Sample'!M16 -> Tier 1 ($500-$10K) | E16: ='Invoice Sample'!F16 -> Net 30 | F16: =IF(B16="Recurring",'Future-State Model'!E22,'Future-State Model'!E23) -> 0.23744186 | G16: ='Future-State Model'!E24 -> 2.4157 | H16: =IF(OR(D16="Tier 2 ($10K-$50K)",D16="Tier 3 (>$50K)"),'Future-State Model'!E25,0) -> 0 | I16: =IF(D16="Tier 3 (>$50K)",'Future-State Model'!E26,0) -> 0 | J16: ='Future-State Model'!E27 -> 0.686 | K16: =SUM(F16:J16) -> 3.3391419 | L16: =IF(E16="2/10 Net 30","Yes","No") -> No | M16: =IF(AND(L16="Yes",(F16+G16+H16+I16)<=10),"Yes","No") -> No | N16: =IF(K16>30,"Yes","No") -> No | O16: =IF(AND(L16="Yes",'Invoice Sample'!O16="No",M16="Yes"),C16*0.02,0) -> 0 | P16: =IF(AND('Invoice Sample'!P16="Yes",N16="No"),C16*0.015,0) -> 0
A17: ='Invoice Sample'!A17 -> INV-2046 | B17: ='Invoice Sample'!C17 -> Recurring | C17: ='Invoice Sample'!E17 -> 2748.06 | D17: ='Invoice Sample'!M17 -> Tier 1 ($500-$10K) | E17: ='Invoice Sample'!F17 -> Net 30 | F17: =IF(B17="Recurring",'Future-State Model'!E22,'Future-State Model'!E23) -> 0.23744186 | G17: ='Future-State Model'!E24 -> 2.4157 | H17: =IF(OR(D17="Tier 2 ($10K-$50K)",D17="Tier 3 (>$50K)"),'Future-State Model'!E25,0) -> 0 | I17: =IF(D17="Tier 3 (>$50K)",'Future-State Model'!E26,0) -> 0 | J17: ='Future-State Model'!E27 -> 0.686 | K17: =SUM(F17:J17) -> 3.3391419 | L17: =IF(E17="2/10 Net 30","Yes","No") -> No | M17: =IF(AND(L17="Yes",(F17+G17+H17+I17)<=10),"Yes","No") -> No | N17: =IF(K17>30,"Yes","No") -> No | O17: =IF(AND(L17="Yes",'Invoice Sample'!O17="No",M17="Yes"),C17*0.02,0) -> 0 | P17: =IF(AND('Invoice Sample'!P17="Yes",N17="No"),C17*0.015,0) -> 0
A18: ='Invoice Sample'!A18 -> INV-2047 | B18: ='Invoice Sample'!C18 -> One-off | C18: ='Invoice Sample'!E18 -> 1866.64 | D18: ='Invoice Sample'!M18 -> Tier 1 ($500-$10K) | E18: ='Invoice Sample'!F18 -> Net 30 | F18: =IF(B18="Recurring",'Future-State Model'!E22,'Future-State Model'!E23) -> 1.5735294 | G18: ='Future-State Model'!E24 -> 2.4157 | H18: =IF(OR(D18="Tier 2 ($10K-$50K)",D18="Tier 3 (>$50K)"),'Future-State Model'!E25,0) -> 0 | I18: =IF(D18="Tier 3 (>$50K)",'Future-State Model'!E26,0) -> 0 | J18: ='Future-State Model'!E27 -> 0.686 | K18: =SUM(F18:J18) -> 4.6752294 | L18: =IF(E18="2/10 Net 30","Yes","No") -> No | M18: =IF(AND(L18="Yes",(F18+G18+H18+I18)<=10),"Yes","No") -> No | N18: =IF(K18>30,"Yes","No") -> No | O18: =IF(AND(L18="Yes",'Invoice Sample'!O18="No",M18="Yes"),C18*0.02,0) -> 0 | P18: =IF(AND('Invoice Sample'!P18="Yes",N18="No"),C18*0.015,0) -> 0
A19: ='Invoice Sample'!A19 -> INV-2048 | B19: ='Invoice Sample'!C19 -> Recurring | C19: ='Invoice Sample'!E19 -> 102.37 | D19: ='Invoice Sample'!M19 -> Tier 0 (<$500) | E19: ='Invoice Sample'!F19 -> Net 30 | F19: =IF(B19="Recurring",'Future-State Model'!E22,'Future-State Model'!E23) -> 0.23744186 | G19: ='Future-State Model'!E24 -> 2.4157 | H19: =IF(OR(D19="Tier 2 ($10K-$50K)",D19="Tier 3 (>$50K)"),'Future-State Model'!E25,0) -> 0 | I19: =IF(D19="Tier 3 (>$50K)",'Future-State Model'!E26,0) -> 0 | J19: ='Future-State Model'!E27 -> 0.686 | K19: =SUM(F19:J19) -> 3.3391419 | L19: =IF(E19="2/10 Net 30","Yes","No") -> No | M19: =IF(AND(L19="Yes",(F19+G19+H19+I19)<=10),"Yes","No") -> No | N19: =IF(K19>30,"Yes","No") -> No | O19: =IF(AND(L19="Yes",'Invoice Sample'!O19="No",M19="Yes"),C19*0.02,0) -> 0 | P19: =IF(AND('Invoice Sample'!P19="Yes",N19="No"),C19*0.015,0) -> 0
A20: ='Invoice Sample'!A20 -> INV-2049 | B20: ='Invoice Sample'!C20 -> Recurring | C20: ='Invoice Sample'!E20 -> 44044.41 | D20: ='Invoice Sample'!M20 -> Tier 2 ($10K-$50K) | E20: ='Invoice Sample'!F20 -> 2/10 Net 30 | F20: =IF(B20="Recurring",'Future-State Model'!E22,'Future-State Model'!E23) -> 0.23744186 | G20: ='Future-State Model'!E24 -> 2.4157 | H20: =IF(OR(D20="Tier 2 ($10K-$50K)",D20="Tier 3 (>$50K)"),'Future-State Model'!E25,0) -> 2.0645657 | I20: =IF(D20="Tier 3 (>$50K)",'Future-State Model'!E26,0) -> 0 | J20: ='Future-State Model'!E27 -> 0.686 | K20: =SUM(F20:J20) -> 5.4037075 | L20: =IF(E20="2/10 Net 30","Yes","No") -> Yes | M20: =IF(AND(L20="Yes",(F20+G20+H20+I20)<=10),"Yes","No") -> Yes | N20: =IF(K20>30,"Yes","No") -> No | O20: =IF(AND(L20="Yes",'Invoice Sample'!O20="No",M20="Yes"),C20*0.02,0) -> 880.8882 | P20: =IF(AND('Invoice Sample'!P20="Yes",N20="No"),C20*0.015,0) -> 0
A21: ='Invoice Sample'!A21 -> INV-2050 | B21: ='Invoice Sample'!C21 -> Recurring | C21: ='Invoice Sample'!E21 -> 1465.78 | D21: ='Invoice Sample'!M21 -> Tier 1 ($500-$10K) | E21: ='Invoice Sample'!F21 -> Net 30 | F21: =IF(B21="Recurring",'Future-State Model'!E22,'Future-State Model'!E23) -> 0.23744186 | G21: ='Future-State Model'!E24 -> 2.4157 | H21: =IF(OR(D21="Tier 2 ($10K-$50K)",D21="Tier 3 (>$50K)"),'Future-State Model'!E25,0) -> 0 | I21: =IF(D21="Tier 3 (>$50K)",'Future-State Model'!E26,0) -> 0 | J21: ='Future-State Model'!E27 -> 0.686 | K21: =SUM(F21:J21) -> 3.3391419 | L21: =IF(E21="2/10 Net 30","Yes","No") -> No | M21: =IF(AND(L21="Yes",(F21+G21+H21+I21)<=10),"Yes","No") -> No | N21: =IF(K21>30,"Yes","No") -> No | O21: =IF(AND(L21="Yes",'Invoice Sample'!O21="No",M21="Yes"),C21*0.02,0) -> 0 | P21: =IF(AND('Invoice Sample'!P21="Yes",N21="No"),C21*0.015,0) -> 0
A22: ='Invoice Sample'!A22 -> INV-2051 | B22: ='Invoice Sample'!C22 -> One-off | C22: ='Invoice Sample'!E22 -> 41178.32 | D22: ='Invoice Sample'!M22 -> Tier 2 ($10K-$50K) | E22: ='Invoice Sample'!F22 -> Net 30 | F22: =IF(B22="Recurring",'Future-State Model'!E22,'Future-State Model'!E23) -> 1.5735294 | G22: ='Future-State Model'!E24 -> 2.4157 | H22: =IF(OR(D22="Tier 2 ($10K-$50K)",D22="Tier 3 (>$50K)"),'Future-State Model'!E25,0) -> 2.0645657 | I22: =IF(D22="Tier 3 (>$50K)",'Future-State Model'!E26,0) -> 0 | J22: ='Future-State Model'!E27 -> 0.686 | K22: =SUM(F22:J22) -> 6.7397951 | L22: =IF(E22="2/10 Net 30","Yes","No") -> No | M22: =IF(AND(L22="Yes",(F22+G22+H22+I22)<=10),"Yes","No") -> No | N22: =IF(K22>30,"Yes","No") -> No | O22: =IF(AND(L22="Yes",'Invoice Sample'!O22="No",M22="Yes"),C22*0.02,0) -> 0 | P22: =IF(AND('Invoice Sample'!P22="Yes",N22="No"),C22*0.015,0) -> 0
A23: ='Invoice Sample'!A23 -> INV-2052 | B23: ='Invoice Sample'!C23 -> Recurring | C23: ='Invoice Sample'!E23 -> 6575.21 | D23: ='Invoice Sample'!M23 -> Tier 1 ($500-$10K) | E23: ='Invoice Sample'!F23 -> 2/10 Net 30 | F23: =IF(B23="Recurring",'Future-State Model'!E22,'Future-State Model'!E23) -> 0.23744186 | G23: ='Future-State Model'!E24 -> 2.4157 | H23: =IF(OR(D23="Tier 2 ($10K-$50K)",D23="Tier 3 (>$50K)"),'Future-State Model'!E25,0) -> 0 | I23: =IF(D23="Tier 3 (>$50K)",'Future-State Model'!E26,0) -> 0 | J23: ='Future-State Model'!E27 -> 0.686 | K23: =SUM(F23:J23) -> 3.3391419 | L23: =IF(E23="2/10 Net 30","Yes","No") -> Yes | M23: =IF(AND(L23="Yes",(F23+G23+H23+I23)<=10),"Yes","No") -> Yes | N23: =IF(K23>30,"Yes","No") -> No | O23: =IF(AND(L23="Yes",'Invoice Sample'!O23="No",M23="Yes"),C23*0.02,0) -> 131.5042 | P23: =IF(AND('Invoice Sample'!P23="Yes",N23="No"),C23*0.015,0) -> 0
A24: ='Invoice Sample'!A24 -> INV-2053 | B24: ='Invoice Sample'!C24 -> Recurring | C24: ='Invoice Sample'!E24 -> 76562.49 | D24: ='Invoice Sample'!M24 -> Tier 3 (>$50K) | E24: ='Invoice Sample'!F24 -> Net 30 | F24: =IF(B24="Recurring",'Future-State Model'!E22,'Future-State Model'!E23) -> 0.23744186 | G24: ='Future-State Model'!E24 -> 2.4157 | H24: =IF(OR(D24="Tier 2 ($10K-$50K)",D24="Tier 3 (>$50K)"),'Future-State Model'!E25,0) -> 2.0645657 | I24: =IF(D24="Tier 3 (>$50K)",'Future-State Model'!E26,0) -> 2.4301414 | J24: ='Future-State Model'!E27 -> 0.686 | K24: =SUM(F24:J24) -> 7.8338489 | L24: =IF(E24="2/10 Net 30","Yes","No") -> No | M24: =IF(AND(L24="Yes",(F24+G24+H24+I24)<=10),"Yes","No") -> No | N24: =IF(K24>30,"Yes","No") -> No | O24: =IF(AND(L24="Yes",'Invoice Sample'!O24="No",M24="Yes"),C24*0.02,0) -> 0 | P24: =IF(AND('Invoice Sample'!P24="Yes",N24="No"),C24*0.015,0) -> 0
A25: ='Invoice Sample'!A25 -> INV-2054 | B25: ='Invoice Sample'!C25 -> Recurring | C25: ='Invoice Sample'!E25 -> 36102.84 | D25: ='Invoice Sample'!M25 -> Tier 2 ($10K-$50K) | E25: ='Invoice Sample'!F25 -> Net 30 | F25: =IF(B25="Recurring",'Future-State Model'!E22,'Future-State Model'!E23) -> 0.23744186 | G25: ='Future-State Model'!E24 -> 2.4157 | H25: =IF(OR(D25="Tier 2 ($10K-$50K)",D25="Tier 3 (>$50K)"),'Future-State Model'!E25,0) -> 2.0645657 | I25: =IF(D25="Tier 3 (>$50K)",'Future-State Model'!E26,0) -> 0 | J25: ='Future-State Model'!E27 -> 0.686 | K25: =SUM(F25:J25) -> 5.4037075 | L25: =IF(E25="2/10 Net 30","Yes","No") -> No | M25: =IF(AND(L25="Yes",(F25+G25+H25+I25)<=10),"Yes","No") -> No | N25: =IF(K25>30,"Yes","No") -> No | O25: =IF(AND(L25="Yes",'Invoice Sample'!O25="No",M25="Yes"),C25*0.02,0) -> 0 | P25: =IF(AND('Invoice Sample'!P25="Yes",N25="No"),C25*0.015,0) -> 0
A26: ='Invoice Sample'!A26 -> INV-2055 | B26: ='Invoice Sample'!C26 -> Recurring | C26: ='Invoice Sample'!E26 -> 15283.98 | D26: ='Invoice Sample'!M26 -> Tier 2 ($10K-$50K) | E26: ='Invoice Sample'!F26 -> Net 30 | F26: =IF(B26="Recurring",'Future-State Model'!E22,'Future-State Model'!E23) -> 0.23744186 | G26: ='Future-State Model'!E24 -> 2.4157 | H26: =IF(OR(D26="Tier 2 ($10K-$50K)",D26="Tier 3 (>$50K)"),'Future-State Model'!E25,0) -> 2.0645657 | I26: =IF(D26="Tier 3 (>$50K)",'Future-State Model'!E26,0) -> 0 | J26: ='Future-State Model'!E27 -> 0.686 | K26: =SUM(F26:J26) -> 5.4037075 | L26: =IF(E26="2/10 Net 30","Yes","No") -> No | M26: =IF(AND(L26="Yes",(F26+G26+H26+I26)<=10),"Yes","No") -> No | N26: =IF(K26>30,"Yes","No") -> No | O26: =IF(AND(L26="Yes",'Invoice Sample'!O26="No",M26="Yes"),C26*0.02,0) -> 0 | P26: =IF(AND('Invoice Sample'!P26="Yes",N26="No"),C26*0.015,0) -> 0
A27: ='Invoice Sample'!A27 -> INV-2056 | B27: ='Invoice Sample'!C27 -> One-off | C27: ='Invoice Sample'!E27 -> 6139.39 | D27: ='Invoice Sample'!M27 -> Tier 1 ($500-$10K) | E27: ='Invoice Sample'!F27 -> Net 30 | F27: =IF(B27="Recurring",'Future-State Model'!E22,'Future-State Model'!E23) -> 1.5735294 | G27: ='Future-State Model'!E24 -> 2.4157 | H27: =IF(OR(D27="Tier 2 ($10K-$50K)",D27="Tier 3 (>$50K)"),'Future-State Model'!E25,0) -> 0 | I27: =IF(D27="Tier 3 (>$50K)",'Future-State Model'!E26,0) -> 0 | J27: ='Future-State Model'!E27 -> 0.686 | K27: =SUM(F27:J27) -> 4.6752294 | L27: =IF(E27="2/10 Net 30","Yes","No") -> No | M27: =IF(AND(L27="Yes",(F27+G27+H27+I27)<=10),"Yes","No") -> No | N27: =IF(K27>30,"Yes","No") -> No | O27: =IF(AND(L27="Yes",'Invoice Sample'!O27="No",M27="Yes"),C27*0.02,0) -> 0 | P27: =IF(AND('Invoice Sample'!P27="Yes",N27="No"),C27*0.015,0) -> 0
A28: ='Invoice Sample'!A28 -> INV-2057 | B28: ='Invoice Sample'!C28 -> Recurring | C28: ='Invoice Sample'!E28 -> 5866.47 | D28: ='Invoice Sample'!M28 -> Tier 1 ($500-$10K) | E28: ='Invoice Sample'!F28 -> Net 30 | F28: =IF(B28="Recurring",'Future-State Model'!E22,'Future-State Model'!E23) -> 0.23744186 | G28: ='Future-State Model'!E24 -> 2.4157 | H28: =IF(OR(D28="Tier 2 ($10K-$50K)",D28="Tier 3 (>$50K)"),'Future-State Model'!E25,0) -> 0 | I28: =IF(D28="Tier 3 (>$50K)",'Future-State Model'!E26,0) -> 0 | J28: ='Future-State Model'!E27 -> 0.686 | K28: =SUM(F28:J28) -> 3.3391419 | L28: =IF(E28="2/10 Net 30","Yes","No") -> No | M28: =IF(AND(L28="Yes",(F28+G28+H28+I28)<=10),"Yes","No") -> No | N28: =IF(K28>30,"Yes","No") -> No | O28: =IF(AND(L28="Yes",'Invoice Sample'!O28="No",M28="Yes"),C28*0.02,0) -> 0 | P28: =IF(AND('Invoice Sample'!P28="Yes",N28="No"),C28*0.015,0) -> 0
A29: ='Invoice Sample'!A29 -> INV-2058 | B29: ='Invoice Sample'!C29 -> Recurring | C29: ='Invoice Sample'!E29 -> 130.17 | D29: ='Invoice Sample'!M29 -> Tier 0 (<$500) | E29: ='Invoice Sample'!F29 -> 2/10 Net 30 | F29: =IF(B29="Recurring",'Future-State Model'!E22,'Future-State Model'!E23) -> 0.23744186 | G29: ='Future-State Model'!E24 -> 2.4157 | H29: =IF(OR(D29="Tier 2 ($10K-$50K)",D29="Tier 3 (>$50K)"),'Future-State Model'!E25,0) -> 0 | I29: =IF(D29="Tier 3 (>$50K)",'Future-State Model'!E26,0) -> 0 | J29: ='Future-State Model'!E27 -> 0.686 | K29: =SUM(F29:J29) -> 3.3391419 | L29: =IF(E29="2/10 Net 30","Yes","No") -> Yes | M29: =IF(AND(L29="Yes",(F29+G29+H29+I29)<=10),"Yes","No") -> Yes | N29: =IF(K29>30,"Yes","No") -> No | O29: =IF(AND(L29="Yes",'Invoice Sample'!O29="No",M29="Yes"),C29*0.02,0) -> 0 | P29: =IF(AND('Invoice Sample'!P29="Yes",N29="No"),C29*0.015,0) -> 0
A30: ='Invoice Sample'!A30 -> INV-2059 | B30: ='Invoice Sample'!C30 -> One-off | C30: ='Invoice Sample'!E30 -> 219.79 | D30: ='Invoice Sample'!M30 -> Tier 0 (<$500) | E30: ='Invoice Sample'!F30 -> Net 30 | F30: =IF(B30="Recurring",'Future-State Model'!E22,'Future-State Model'!E23) -> 1.5735294 | G30: ='Future-State Model'!E24 -> 2.4157 | H30: =IF(OR(D30="Tier 2 ($10K-$50K)",D30="Tier 3 (>$50K)"),'Future-State Model'!E25,0) -> 0 | I30: =IF(D30="Tier 3 (>$50K)",'Future-State Model'!E26,0) -> 0 | J30: ='Future-State Model'!E27 -> 0.686 | K30: =SUM(F30:J30) -> 4.6752294 | L30: =IF(E30="2/10 Net 30","Yes","No") -> No | M30: =IF(AND(L30="Yes",(F30+G30+H30+I30)<=10),"Yes","No") -> No | N30: =IF(K30>30,"Yes","No") -> No | O30: =IF(AND(L30="Yes",'Invoice Sample'!O30="No",M30="Yes"),C30*0.02,0) -> 0 | P30: =IF(AND('Invoice Sample'!P30="Yes",N30="No"),C30*0.015,0) -> 0
A31: ='Invoice Sample'!A31 -> INV-2060 | B31: ='Invoice Sample'!C31 -> Recurring | C31: ='Invoice Sample'!E31 -> 1903.79 | D31: ='Invoice Sample'!M31 -> Tier 1 ($500-$10K) | E31: ='Invoice Sample'!F31 -> Net 30 | F31: =IF(B31="Recurring",'Future-State Model'!E22,'Future-State Model'!E23) -> 0.23744186 | G31: ='Future-State Model'!E24 -> 2.4157 | H31: =IF(OR(D31="Tier 2 ($10K-$50K)",D31="Tier 3 (>$50K)"),'Future-State Model'!E25,0) -> 0 | I31: =IF(D31="Tier 3 (>$50K)",'Future-State Model'!E26,0) -> 0 | J31: ='Future-State Model'!E27 -> 0.686 | K31: =SUM(F31:J31) -> 3.3391419 | L31: =IF(E31="2/10 Net 30","Yes","No") -> No | M31: =IF(AND(L31="Yes",(F31+G31+H31+I31)<=10),"Yes","No") -> No | N31: =IF(K31>30,"Yes","No") -> No | O31: =IF(AND(L31="Yes",'Invoice Sample'!O31="No",M31="Yes"),C31*0.02,0) -> 0 | P31: =IF(AND('Invoice Sample'!P31="Yes",N31="No"),C31*0.015,0) -> 0
A32: ='Invoice Sample'!A32 -> INV-2061 | B32: ='Invoice Sample'!C32 -> One-off | C32: ='Invoice Sample'!E32 -> 25054 | D32: ='Invoice Sample'!M32 -> Tier 2 ($10K-$50K) | E32: ='Invoice Sample'!F32 -> Net 30 | F32: =IF(B32="Recurring",'Future-State Model'!E22,'Future-State Model'!E23) -> 1.5735294 | G32: ='Future-State Model'!E24 -> 2.4157 | H32: =IF(OR(D32="Tier 2 ($10K-$50K)",D32="Tier 3 (>$50K)"),'Future-State Model'!E25,0) -> 2.0645657 | I32: =IF(D32="Tier 3 (>$50K)",'Future-State Model'!E26,0) -> 0 | J32: ='Future-State Model'!E27 -> 0.686 | K32: =SUM(F32:J32) -> 6.7397951 | L32: =IF(E32="2/10 Net 30","Yes","No") -> No | M32: =IF(AND(L32="Yes",(F32+G32+H32+I32)<=10),"Yes","No") -> No | N32: =IF(K32>30,"Yes","No") -> No | O32: =IF(AND(L32="Yes",'Invoice Sample'!O32="No",M32="Yes"),C32*0.02,0) -> 0 | P32: =IF(AND('Invoice Sample'!P32="Yes",N32="No"),C32*0.015,0) -> 0
A33: ='Invoice Sample'!A33 -> INV-2062 | B33: ='Invoice Sample'!C33 -> Recurring | C33: ='Invoice Sample'!E33 -> 98026.75 | D33: ='Invoice Sample'!M33 -> Tier 3 (>$50K) | E33: ='Invoice Sample'!F33 -> 2/10 Net 30 | F33: =IF(B33="Recurring",'Future-State Model'!E22,'Future-State Model'!E23) -> 0.23744186 | G33: ='Future-State Model'!E24 -> 2.4157 | H33: =IF(OR(D33="Tier 2 ($10K-$50K)",D33="Tier 3 (>$50K)"),'Future-State Model'!E25,0) -> 2.0645657 | I33: =IF(D33="Tier 3 (>$50K)",'Future-State Model'!E26,0) -> 2.4301414 | J33: ='Future-State Model'!E27 -> 0.686 | K33: =SUM(F33:J33) -> 7.8338489 | L33: =IF(E33="2/10 Net 30","Yes","No") -> Yes | M33: =IF(AND(L33="Yes",(F33+G33+H33+I33)<=10),"Yes","No") -> Yes | N33: =IF(K33>30,"Yes","No") -> No | O33: =IF(AND(L33="Yes",'Invoice Sample'!O33="No",M33="Yes"),C33*0.02,0) -> 0 | P33: =IF(AND('Invoice Sample'!P33="Yes",N33="No"),C33*0.015,0) -> 0
A34: ='Invoice Sample'!A34 -> INV-2063 | B34: ='Invoice Sample'!C34 -> Recurring | C34: ='Invoice Sample'!E34 -> 7921.51 | D34: ='Invoice Sample'!M34 -> Tier 1 ($500-$10K) | E34: ='Invoice Sample'!F34 -> 2/10 Net 30 | F34: =IF(B34="Recurring",'Future-State Model'!E22,'Future-State Model'!E23) -> 0.23744186 | G34: ='Future-State Model'!E24 -> 2.4157 | H34: =IF(OR(D34="Tier 2 ($10K-$50K)",D34="Tier 3 (>$50K)"),'Future-State Model'!E25,0) -> 0 | I34: =IF(D34="Tier 3 (>$50K)",'Future-State Model'!E26,0) -> 0 | J34: ='Future-State Model'!E27 -> 0.686 | K34: =SUM(F34:J34) -> 3.3391419 | L34: =IF(E34="2/10 Net 30","Yes","No") -> Yes | M34: =IF(AND(L34="Yes",(F34+G34+H34+I34)<=10),"Yes","No") -> Yes | N34: =IF(K34>30,"Yes","No") -> No | O34: =IF(AND(L34="Yes",'Invoice Sample'!O34="No",M34="Yes"),C34*0.02,0) -> 158.4302 | P34: =IF(AND('Invoice Sample'!P34="Yes",N34="No"),C34*0.015,0) -> 0
A35: ='Invoice Sample'!A35 -> INV-2064 | B35: ='Invoice Sample'!C35 -> One-off | C35: ='Invoice Sample'!E35 -> 6675.54 | D35: ='Invoice Sample'!M35 -> Tier 1 ($500-$10K) | E35: ='Invoice Sample'!F35 -> 2/10 Net 30 | F35: =IF(B35="Recurring",'Future-State Model'!E22,'Future-State Model'!E23) -> 1.5735294 | G35: ='Future-State Model'!E24 -> 2.4157 | H35: =IF(OR(D35="Tier 2 ($10K-$50K)",D35="Tier 3 (>$50K)"),'Future-State Model'!E25,0) -> 0 | I35: =IF(D35="Tier 3 (>$50K)",'Future-State Model'!E26,0) -> 0 | J35: ='Future-State Model'!E27 -> 0.686 | K35: =SUM(F35:J35) -> 4.6752294 | L35: =IF(E35="2/10 Net 30","Yes","No") -> Yes | M35: =IF(AND(L35="Yes",(F35+G35+H35+I35)<=10),"Yes","No") -> Yes | N35: =IF(K35>30,"Yes","No") -> No | O35: =IF(AND(L35="Yes",'Invoice Sample'!O35="No",M35="Yes"),C35*0.02,0) -> 133.5108 | P35: =IF(AND('Invoice Sample'!P35="Yes",N35="No"),C35*0.015,0) -> 0
A36: ='Invoice Sample'!A36 -> INV-2065 | B36: ='Invoice Sample'!C36 -> Recurring | C36: ='Invoice Sample'!E36 -> 6733.9 | D36: ='Invoice Sample'!M36 -> Tier 1 ($500-$10K) | E36: ='Invoice Sample'!F36 -> 2/10 Net 30 | F36: =IF(B36="Recurring",'Future-State Model'!E22,'Future-State Model'!E23) -> 0.23744186 | G36: ='Future-State Model'!E24 -> 2.4157 | H36: =IF(OR(D36="Tier 2 ($10K-$50K)",D36="Tier 3 (>$50K)"),'Future-State Model'!E25,0) -> 0 | I36: =IF(D36="Tier 3 (>$50K)",'Future-State Model'!E26,0) -> 0 | J36: ='Future-State Model'!E27 -> 0.686 | K36: =SUM(F36:J36) -> 3.3391419 | L36: =IF(E36="2/10 Net 30","Yes","No") -> Yes | M36: =IF(AND(L36="Yes",(F36+G36+H36+I36)<=10),"Yes","No") -> Yes | N36: =IF(K36>30,"Yes","No") -> No | O36: =IF(AND(L36="Yes",'Invoice Sample'!O36="No",M36="Yes"),C36*0.02,0) -> 0 | P36: =IF(AND('Invoice Sample'!P36="Yes",N36="No"),C36*0.015,0) -> 0
A37: ='Invoice Sample'!A37 -> INV-2066 | B37: ='Invoice Sample'!C37 -> One-off | C37: ='Invoice Sample'!E37 -> 8108.36 | D37: ='Invoice Sample'!M37 -> Tier 1 ($500-$10K) | E37: ='Invoice Sample'!F37 -> Net 30 | F37: =IF(B37="Recurring",'Future-State Model'!E22,'Future-State Model'!E23) -> 1.5735294 | G37: ='Future-State Model'!E24 -> 2.4157 | H37: =IF(OR(D37="Tier 2 ($10K-$50K)",D37="Tier 3 (>$50K)"),'Future-State Model'!E25,0) -> 0 | I37: =IF(D37="Tier 3 (>$50K)",'Future-State Model'!E26,0) -> 0 | J37: ='Future-State Model'!E27 -> 0.686 | K37: =SUM(F37:J37) -> 4.6752294 | L37: =IF(E37="2/10 Net 30","Yes","No") -> No | M37: =IF(AND(L37="Yes",(F37+G37+H37+I37)<=10),"Yes","No") -> No | N37: =IF(K37>30,"Yes","No") -> No | O37: =IF(AND(L37="Yes",'Invoice Sample'!O37="No",M37="Yes"),C37*0.02,0) -> 0 | P37: =IF(AND('Invoice Sample'!P37="Yes",N37="No"),C37*0.015,0) -> 0
A38: ='Invoice Sample'!A38 -> INV-2067 | B38: ='Invoice Sample'!C38 -> Recurring | C38: ='Invoice Sample'!E38 -> 145.03 | D38: ='Invoice Sample'!M38 -> Tier 0 (<$500) | E38: ='Invoice Sample'!F38 -> Net 30 | F38: =IF(B38="Recurring",'Future-State Model'!E22,'Future-State Model'!E23) -> 0.23744186 | G38: ='Future-State Model'!E24 -> 2.4157 | H38: =IF(OR(D38="Tier 2 ($10K-$50K)",D38="Tier 3 (>$50K)"),'Future-State Model'!E25,0) -> 0 | I38: =IF(D38="Tier 3 (>$50K)",'Future-State Model'!E26,0) -> 0 | J38: ='Future-State Model'!E27 -> 0.686 | K38: =SUM(F38:J38) -> 3.3391419 | L38: =IF(E38="2/10 Net 30","Yes","No") -> No | M38: =IF(AND(L38="Yes",(F38+G38+H38+I38)<=10),"Yes","No") -> No | N38: =IF(K38>30,"Yes","No") -> No | O38: =IF(AND(L38="Yes",'Invoice Sample'!O38="No",M38="Yes"),C38*0.02,0) -> 0 | P38: =IF(AND('Invoice Sample'!P38="Yes",N38="No"),C38*0.015,0) -> 0
A39: ='Invoice Sample'!A39 -> INV-2068 | B39: ='Invoice Sample'!C39 -> One-off | C39: ='Invoice Sample'!E39 -> 1017.7 | D39: ='Invoice Sample'!M39 -> Tier 1 ($500-$10K) | E39: ='Invoice Sample'!F39 -> Net 30 | F39: =IF(B39="Recurring",'Future-State Model'!E22,'Future-State Model'!E23) -> 1.5735294 | G39: ='Future-State Model'!E24 -> 2.4157 | H39: =IF(OR(D39="Tier 2 ($10K-$50K)",D39="Tier 3 (>$50K)"),'Future-State Model'!E25,0) -> 0 | I39: =IF(D39="Tier 3 (>$50K)",'Future-State Model'!E26,0) -> 0 | J39: ='Future-State Model'!E27 -> 0.686 | K39: =SUM(F39:J39) -> 4.6752294 | L39: =IF(E39="2/10 Net 30","Yes","No") -> No | M39: =IF(AND(L39="Yes",(F39+G39+H39+I39)<=10),"Yes","No") -> No | N39: =IF(K39>30,"Yes","No") -> No | O39: =IF(AND(L39="Yes",'Invoice Sample'!O39="No",M39="Yes"),C39*0.02,0) -> 0 | P39: =IF(AND('Invoice Sample'!P39="Yes",N39="No"),C39*0.015,0) -> 0
A40: ='Invoice Sample'!A40 -> INV-2069 | B40: ='Invoice Sample'!C40 -> Recurring | C40: ='Invoice Sample'!E40 -> 4855.87 | D40: ='Invoice Sample'!M40 -> Tier 1 ($500-$10K) | E40: ='Invoice Sample'!F40 -> Net 30 | F40: =IF(B40="Recurring",'Future-State Model'!E22,'Future-State Model'!E23) -> 0.23744186 | G40: ='Future-State Model'!E24 -> 2.4157 | H40: =IF(OR(D40="Tier 2 ($10K-$50K)",D40="Tier 3 (>$50K)"),'Future-State Model'!E25,0) -> 0 | I40: =IF(D40="Tier 3 (>$50K)",'Future-State Model'!E26,0) -> 0 | J40: ='Future-State Model'!E27 -> 0.686 | K40: =SUM(F40:J40) -> 3.3391419 | L40: =IF(E40="2/10 Net 30","Yes","No") -> No | M40: =IF(AND(L40="Yes",(F40+G40+H40+I40)<=10),"Yes","No") -> No | N40: =IF(K40>30,"Yes","No") -> No | O40: =IF(AND(L40="Yes",'Invoice Sample'!O40="No",M40="Yes"),C40*0.02,0) -> 0 | P40: =IF(AND('Invoice Sample'!P40="Yes",N40="No"),C40*0.015,0) -> 0
A41: ='Invoice Sample'!A41 -> INV-2070 | B41: ='Invoice Sample'!C41 -> Recurring | C41: ='Invoice Sample'!E41 -> 6667.07 | D41: ='Invoice Sample'!M41 -> Tier 1 ($500-$10K) | E41: ='Invoice Sample'!F41 -> Net 30 | F41: =IF(B41="Recurring",'Future-State Model'!E22,'Future-State Model'!E23) -> 0.23744186 | G41: ='Future-State Model'!E24 -> 2.4157 | H41: =IF(OR(D41="Tier 2 ($10K-$50K)",D41="Tier 3 (>$50K)"),'Future-State Model'!E25,0) -> 0 | I41: =IF(D41="Tier 3 (>$50K)",'Future-State Model'!E26,0) -> 0 | J41: ='Future-State Model'!E27 -> 0.686 | K41: =SUM(F41:J41) -> 3.3391419 | L41: =IF(E41="2/10 Net 30","Yes","No") -> No | M41: =IF(AND(L41="Yes",(F41+G41+H41+I41)<=10),"Yes","No") -> No | N41: =IF(K41>30,"Yes","No") -> No | O41: =IF(AND(L41="Yes",'Invoice Sample'!O41="No",M41="Yes"),C41*0.02,0) -> 0 | P41: =IF(AND('Invoice Sample'!P41="Yes",N41="No"),C41*0.015,0) -> 0
A42: ='Invoice Sample'!A42 -> INV-2071 | B42: ='Invoice Sample'!C42 -> Recurring | C42: ='Invoice Sample'!E42 -> 3394.39 | D42: ='Invoice Sample'!M42 -> Tier 1 ($500-$10K) | E42: ='Invoice Sample'!F42 -> Net 30 | F42: =IF(B42="Recurring",'Future-State Model'!E22,'Future-State Model'!E23) -> 0.23744186 | G42: ='Future-State Model'!E24 -> 2.4157 | H42: =IF(OR(D42="Tier 2 ($10K-$50K)",D42="Tier 3 (>$50K)"),'Future-State Model'!E25,0) -> 0 | I42: =IF(D42="Tier 3 (>$50K)",'Future-State Model'!E26,0) -> 0 | J42: ='Future-State Model'!E27 -> 0.686 | K42: =SUM(F42:J42) -> 3.3391419 | L42: =IF(E42="2/10 Net 30","Yes","No") -> No | M42: =IF(AND(L42="Yes",(F42+G42+H42+I42)<=10),"Yes","No") -> No | N42: =IF(K42>30,"Yes","No") -> No | O42: =IF(AND(L42="Yes",'Invoice Sample'!O42="No",M42="Yes"),C42*0.02,0) -> 0 | P42: =IF(AND('Invoice Sample'!P42="Yes",N42="No"),C42*0.015,0) -> 0
A43: ='Invoice Sample'!A43 -> INV-2072 | B43: ='Invoice Sample'!C43 -> Recurring | C43: ='Invoice Sample'!E43 -> 11442.36 | D43: ='Invoice Sample'!M43 -> Tier 2 ($10K-$50K) | E43: ='Invoice Sample'!F43 -> Net 30 | F43: =IF(B43="Recurring",'Future-State Model'!E22,'Future-State Model'!E23) -> 0.23744186 | G43: ='Future-State Model'!E24 -> 2.4157 | H43: =IF(OR(D43="Tier 2 ($10K-$50K)",D43="Tier 3 (>$50K)"),'Future-State Model'!E25,0) -> 2.0645657 | I43: =IF(D43="Tier 3 (>$50K)",'Future-State Model'!E26,0) -> 0 | J43: ='Future-State Model'!E27 -> 0.686 | K43: =SUM(F43:J43) -> 5.4037075 | L43: =IF(E43="2/10 Net 30","Yes","No") -> No | M43: =IF(AND(L43="Yes",(F43+G43+H43+I43)<=10),"Yes","No") -> No | N43: =IF(K43>30,"Yes","No") -> No | O43: =IF(AND(L43="Yes",'Invoice Sample'!O43="No",M43="Yes"),C43*0.02,0) -> 0 | P43: =IF(AND('Invoice Sample'!P43="Yes",N43="No"),C43*0.015,0) -> 0
A44: ='Invoice Sample'!A44 -> INV-2073 | B44: ='Invoice Sample'!C44 -> Recurring | C44: ='Invoice Sample'!E44 -> 3503.72 | D44: ='Invoice Sample'!M44 -> Tier 1 ($500-$10K) | E44: ='Invoice Sample'!F44 -> Net 30 | F44: =IF(B44="Recurring",'Future-State Model'!E22,'Future-State Model'!E23) -> 0.23744186 | G44: ='Future-State Model'!E24 -> 2.4157 | H44: =IF(OR(D44="Tier 2 ($10K-$50K)",D44="Tier 3 (>$50K)"),'Future-State Model'!E25,0) -> 0 | I44: =IF(D44="Tier 3 (>$50K)",'Future-State Model'!E26,0) -> 0 | J44: ='Future-State Model'!E27 -> 0.686 | K44: =SUM(F44:J44) -> 3.3391419 | L44: =IF(E44="2/10 Net 30","Yes","No") -> No | M44: =IF(AND(L44="Yes",(F44+G44+H44+I44)<=10),"Yes","No") -> No | N44: =IF(K44>30,"Yes","No") -> No | O44: =IF(AND(L44="Yes",'Invoice Sample'!O44="No",M44="Yes"),C44*0.02,0) -> 0 | P44: =IF(AND('Invoice Sample'!P44="Yes",N44="No"),C44*0.015,0) -> 0
A45: ='Invoice Sample'!A45 -> INV-2074 | B45: ='Invoice Sample'!C45 -> Recurring | C45: ='Invoice Sample'!E45 -> 9249.12 | D45: ='Invoice Sample'!M45 -> Tier 1 ($500-$10K) | E45: ='Invoice Sample'!F45 -> Net 30 | F45: =IF(B45="Recurring",'Future-State Model'!E22,'Future-State Model'!E23) -> 0.23744186 | G45: ='Future-State Model'!E24 -> 2.4157 | H45: =IF(OR(D45="Tier 2 ($10K-$50K)",D45="Tier 3 (>$50K)"),'Future-State Model'!E25,0) -> 0 | I45: =IF(D45="Tier 3 (>$50K)",'Future-State Model'!E26,0) -> 0 | J45: ='Future-State Model'!E27 -> 0.686 | K45: =SUM(F45:J45) -> 3.3391419 | L45: =IF(E45="2/10 Net 30","Yes","No") -> No | M45: =IF(AND(L45="Yes",(F45+G45+H45+I45)<=10),"Yes","No") -> No | N45: =IF(K45>30,"Yes","No") -> No | O45: =IF(AND(L45="Yes",'Invoice Sample'!O45="No",M45="Yes"),C45*0.02,0) -> 0 | P45: =IF(AND('Invoice Sample'!P45="Yes",N45="No"),C45*0.015,0) -> 0
A46: ='Invoice Sample'!A46 -> INV-2075 | B46: ='Invoice Sample'!C46 -> One-off | C46: ='Invoice Sample'!E46 -> 21224.18 | D46: ='Invoice Sample'!M46 -> Tier 2 ($10K-$50K) | E46: ='Invoice Sample'!F46 -> 2/10 Net 30 | F46: =IF(B46="Recurring",'Future-State Model'!E22,'Future-State Model'!E23) -> 1.5735294 | G46: ='Future-State Model'!E24 -> 2.4157 | H46: =IF(OR(D46="Tier 2 ($10K-$50K)",D46="Tier 3 (>$50K)"),'Future-State Model'!E25,0) -> 2.0645657 | I46: =IF(D46="Tier 3 (>$50K)",'Future-State Model'!E26,0) -> 0 | J46: ='Future-State Model'!E27 -> 0.686 | K46: =SUM(F46:J46) -> 6.7397951 | L46: =IF(E46="2/10 Net 30","Yes","No") -> Yes | M46: =IF(AND(L46="Yes",(F46+G46+H46+I46)<=10),"Yes","No") -> Yes | N46: =IF(K46>30,"Yes","No") -> No | O46: =IF(AND(L46="Yes",'Invoice Sample'!O46="No",M46="Yes"),C46*0.02,0) -> 424.4836 | P46: =IF(AND('Invoice Sample'!P46="Yes",N46="No"),C46*0.015,0) -> 0
A47: ='Invoice Sample'!A47 -> INV-2076 | B47: ='Invoice Sample'!C47 -> One-off | C47: ='Invoice Sample'!E47 -> 16144.36 | D47: ='Invoice Sample'!M47 -> Tier 2 ($10K-$50K) | E47: ='Invoice Sample'!F47 -> Net 30 | F47: =IF(B47="Recurring",'Future-State Model'!E22,'Future-State Model'!E23) -> 1.5735294 | G47: ='Future-State Model'!E24 -> 2.4157 | H47: =IF(OR(D47="Tier 2 ($10K-$50K)",D47="Tier 3 (>$50K)"),'Future-State Model'!E25,0) -> 2.0645657 | I47: =IF(D47="Tier 3 (>$50K)",'Future-State Model'!E26,0) -> 0 | J47: ='Future-State Model'!E27 -> 0.686 | K47: =SUM(F47:J47) -> 6.7397951 | L47: =IF(E47="2/10 Net 30","Yes","No") -> No | M47: =IF(AND(L47="Yes",(F47+G47+H47+I47)<=10),"Yes","No") -> No | N47: =IF(K47>30,"Yes","No") -> No | O47: =IF(AND(L47="Yes",'Invoice Sample'!O47="No",M47="Yes"),C47*0.02,0) -> 0 | P47: =IF(AND('Invoice Sample'!P47="Yes",N47="No"),C47*0.015,0) -> 0
A48: ='Invoice Sample'!A48 -> INV-2077 | B48: ='Invoice Sample'!C48 -> Recurring | C48: ='Invoice Sample'!E48 -> 7200.66 | D48: ='Invoice Sample'!M48 -> Tier 1 ($500-$10K) | E48: ='Invoice Sample'!F48 -> 2/10 Net 30 | F48: =IF(B48="Recurring",'Future-State Model'!E22,'Future-State Model'!E23) -> 0.23744186 | G48: ='Future-State Model'!E24 -> 2.4157 | H48: =IF(OR(D48="Tier 2 ($10K-$50K)",D48="Tier 3 (>$50K)"),'Future-State Model'!E25,0) -> 0 | I48: =IF(D48="Tier 3 (>$50K)",'Future-State Model'!E26,0) -> 0 | J48: ='Future-State Model'!E27 -> 0.686 | K48: =SUM(F48:J48) -> 3.3391419 | L48: =IF(E48="2/10 Net 30","Yes","No") -> Yes | M48: =IF(AND(L48="Yes",(F48+G48+H48+I48)<=10),"Yes","No") -> Yes | N48: =IF(K48>30,"Yes","No") -> No | O48: =IF(AND(L48="Yes",'Invoice Sample'!O48="No",M48="Yes"),C48*0.02,0) -> 144.0132 | P48: =IF(AND('Invoice Sample'!P48="Yes",N48="No"),C48*0.015,0) -> 0
A49: ='Invoice Sample'!A49 -> INV-2078 | B49: ='Invoice Sample'!C49 -> Recurring | C49: ='Invoice Sample'!E49 -> 9895.77 | D49: ='Invoice Sample'!M49 -> Tier 1 ($500-$10K) | E49: ='Invoice Sample'!F49 -> Net 30 | F49: =IF(B49="Recurring",'Future-State Model'!E22,'Future-State Model'!E23) -> 0.23744186 | G49: ='Future-State Model'!E24 -> 2.4157 | H49: =IF(OR(D49="Tier 2 ($10K-$50K)",D49="Tier 3 (>$50K)"),'Future-State Model'!E25,0) -> 0 | I49: =IF(D49="Tier 3 (>$50K)",'Future-State Model'!E26,0) -> 0 | J49: ='Future-State Model'!E27 -> 0.686 | K49: =SUM(F49:J49) -> 3.3391419 | L49: =IF(E49="2/10 Net 30","Yes","No") -> No | M49: =IF(AND(L49="Yes",(F49+G49+H49+I49)<=10),"Yes","No") -> No | N49: =IF(K49>30,"Yes","No") -> No | O49: =IF(AND(L49="Yes",'Invoice Sample'!O49="No",M49="Yes"),C49*0.02,0) -> 0 | P49: =IF(AND('Invoice Sample'!P49="Yes",N49="No"),C49*0.015,0) -> 0
A50: ='Invoice Sample'!A50 -> INV-2079 | B50: ='Invoice Sample'!C50 -> Recurring | C50: ='Invoice Sample'!E50 -> 4620.47 | D50: ='Invoice Sample'!M50 -> Tier 1 ($500-$10K) | E50: ='Invoice Sample'!F50 -> Net 30 | F50: =IF(B50="Recurring",'Future-State Model'!E22,'Future-State Model'!E23) -> 0.23744186 | G50: ='Future-State Model'!E24 -> 2.4157 | H50: =IF(OR(D50="Tier 2 ($10K-$50K)",D50="Tier 3 (>$50K)"),'Future-State Model'!E25,0) -> 0 | I50: =IF(D50="Tier 3 (>$50K)",'Future-State Model'!E26,0) -> 0 | J50: ='Future-State Model'!E27 -> 0.686 | K50: =SUM(F50:J50) -> 3.3391419 | L50: =IF(E50="2/10 Net 30","Yes","No") -> No | M50: =IF(AND(L50="Yes",(F50+G50+H50+I50)<=10),"Yes","No") -> No | N50: =IF(K50>30,"Yes","No") -> No | O50: =IF(AND(L50="Yes",'Invoice Sample'!O50="No",M50="Yes"),C50*0.02,0) -> 0 | P50: =IF(AND('Invoice Sample'!P50="Yes",N50="No"),C50*0.015,0) -> 0
A51: ='Invoice Sample'!A51 -> INV-2080 | B51: ='Invoice Sample'!C51 -> Recurring | C51: ='Invoice Sample'!E51 -> 325.72 | D51: ='Invoice Sample'!M51 -> Tier 0 (<$500) | E51: ='Invoice Sample'!F51 -> Net 30 | F51: =IF(B51="Recurring",'Future-State Model'!E22,'Future-State Model'!E23) -> 0.23744186 | G51: ='Future-State Model'!E24 -> 2.4157 | H51: =IF(OR(D51="Tier 2 ($10K-$50K)",D51="Tier 3 (>$50K)"),'Future-State Model'!E25,0) -> 0 | I51: =IF(D51="Tier 3 (>$50K)",'Future-State Model'!E26,0) -> 0 | J51: ='Future-State Model'!E27 -> 0.686 | K51: =SUM(F51:J51) -> 3.3391419 | L51: =IF(E51="2/10 Net 30","Yes","No") -> No | M51: =IF(AND(L51="Yes",(F51+G51+H51+I51)<=10),"Yes","No") -> No | N51: =IF(K51>30,"Yes","No") -> No | O51: =IF(AND(L51="Yes",'Invoice Sample'!O51="No",M51="Yes"),C51*0.02,0) -> 0 | P51: =IF(AND('Invoice Sample'!P51="Yes",N51="No"),C51*0.015,0) -> 0
A52: ='Invoice Sample'!A52 -> INV-2081 | B52: ='Invoice Sample'!C52 -> Recurring | C52: ='Invoice Sample'!E52 -> 6866.26 | D52: ='Invoice Sample'!M52 -> Tier 1 ($500-$10K) | E52: ='Invoice Sample'!F52 -> Net 30 | F52: =IF(B52="Recurring",'Future-State Model'!E22,'Future-State Model'!E23) -> 0.23744186 | G52: ='Future-State Model'!E24 -> 2.4157 | H52: =IF(OR(D52="Tier 2 ($10K-$50K)",D52="Tier 3 (>$50K)"),'Future-State Model'!E25,0) -> 0 | I52: =IF(D52="Tier 3 (>$50K)",'Future-State Model'!E26,0) -> 0 | J52: ='Future-State Model'!E27 -> 0.686 | K52: =SUM(F52:J52) -> 3.3391419 | L52: =IF(E52="2/10 Net 30","Yes","No") -> No | M52: =IF(AND(L52="Yes",(F52+G52+H52+I52)<=10),"Yes","No") -> No | N52: =IF(K52>30,"Yes","No") -> No | O52: =IF(AND(L52="Yes",'Invoice Sample'!O52="No",M52="Yes"),C52*0.02,0) -> 0 | P52: =IF(AND('Invoice Sample'!P52="Yes",N52="No"),C52*0.015,0) -> 0
A53: ='Invoice Sample'!A53 -> INV-2082 | B53: ='Invoice Sample'!C53 -> Recurring | C53: ='Invoice Sample'!E53 -> 436.99 | D53: ='Invoice Sample'!M53 -> Tier 0 (<$500) | E53: ='Invoice Sample'!F53 -> Net 30 | F53: =IF(B53="Recurring",'Future-State Model'!E22,'Future-State Model'!E23) -> 0.23744186 | G53: ='Future-State Model'!E24 -> 2.4157 | H53: =IF(OR(D53="Tier 2 ($10K-$50K)",D53="Tier 3 (>$50K)"),'Future-State Model'!E25,0) -> 0 | I53: =IF(D53="Tier 3 (>$50K)",'Future-State Model'!E26,0) -> 0 | J53: ='Future-State Model'!E27 -> 0.686 | K53: =SUM(F53:J53) -> 3.3391419 | L53: =IF(E53="2/10 Net 30","Yes","No") -> No | M53: =IF(AND(L53="Yes",(F53+G53+H53+I53)<=10),"Yes","No") -> No | N53: =IF(K53>30,"Yes","No") -> No | O53: =IF(AND(L53="Yes",'Invoice Sample'!O53="No",M53="Yes"),C53*0.02,0) -> 0 | P53: =IF(AND('Invoice Sample'!P53="Yes",N53="No"),C53*0.015,0) -> 0
A54: ='Invoice Sample'!A54 -> INV-2083 | B54: ='Invoice Sample'!C54 -> Recurring | C54: ='Invoice Sample'!E54 -> 31255.91 | D54: ='Invoice Sample'!M54 -> Tier 2 ($10K-$50K) | E54: ='Invoice Sample'!F54 -> 2/10 Net 30 | F54: =IF(B54="Recurring",'Future-State Model'!E22,'Future-State Model'!E23) -> 0.23744186 | G54: ='Future-State Model'!E24 -> 2.4157 | H54: =IF(OR(D54="Tier 2 ($10K-$50K)",D54="Tier 3 (>$50K)"),'Future-State Model'!E25,0) -> 2.0645657 | I54: =IF(D54="Tier 3 (>$50K)",'Future-State Model'!E26,0) -> 0 | J54: ='Future-State Model'!E27 -> 0.686 | K54: =SUM(F54:J54) -> 5.4037075 | L54: =IF(E54="2/10 Net 30","Yes","No") -> Yes | M54: =IF(AND(L54="Yes",(F54+G54+H54+I54)<=10),"Yes","No") -> Yes | N54: =IF(K54>30,"Yes","No") -> No | O54: =IF(AND(L54="Yes",'Invoice Sample'!O54="No",M54="Yes"),C54*0.02,0) -> 625.1182 | P54: =IF(AND('Invoice Sample'!P54="Yes",N54="No"),C54*0.015,0) -> 0
A55: ='Invoice Sample'!A55 -> INV-2084 | B55: ='Invoice Sample'!C55 -> Recurring | C55: ='Invoice Sample'!E55 -> 9309.95 | D55: ='Invoice Sample'!M55 -> Tier 1 ($500-$10K) | E55: ='Invoice Sample'!F55 -> Net 30 | F55: =IF(B55="Recurring",'Future-State Model'!E22,'Future-State Model'!E23) -> 0.23744186 | G55: ='Future-State Model'!E24 -> 2.4157 | H55: =IF(OR(D55="Tier 2 ($10K-$50K)",D55="Tier 3 (>$50K)"),'Future-State Model'!E25,0) -> 0 | I55: =IF(D55="Tier 3 (>$50K)",'Future-State Model'!E26,0) -> 0 | J55: ='Future-State Model'!E27 -> 0.686 | K55: =SUM(F55:J55) -> 3.3391419 | L55: =IF(E55="2/10 Net 30","Yes","No") -> No | M55: =IF(AND(L55="Yes",(F55+G55+H55+I55)<=10),"Yes","No") -> No | N55: =IF(K55>30,"Yes","No") -> No | O55: =IF(AND(L55="Yes",'Invoice Sample'!O55="No",M55="Yes"),C55*0.02,0) -> 0 | P55: =IF(AND('Invoice Sample'!P55="Yes",N55="No"),C55*0.015,0) -> 0
A56: ='Invoice Sample'!A56 -> INV-2085 | B56: ='Invoice Sample'!C56 -> Recurring | C56: ='Invoice Sample'!E56 -> 6392.78 | D56: ='Invoice Sample'!M56 -> Tier 1 ($500-$10K) | E56: ='Invoice Sample'!F56 -> Net 30 | F56: =IF(B56="Recurring",'Future-State Model'!E22,'Future-State Model'!E23) -> 0.23744186 | G56: ='Future-State Model'!E24 -> 2.4157 | H56: =IF(OR(D56="Tier 2 ($10K-$50K)",D56="Tier 3 (>$50K)"),'Future-State Model'!E25,0) -> 0 | I56: =IF(D56="Tier 3 (>$50K)",'Future-State Model'!E26,0) -> 0 | J56: ='Future-State Model'!E27 -> 0.686 | K56: =SUM(F56:J56) -> 3.3391419 | L56: =IF(E56="2/10 Net 30","Yes","No") -> No | M56: =IF(AND(L56="Yes",(F56+G56+H56+I56)<=10),"Yes","No") -> No | N56: =IF(K56>30,"Yes","No") -> No | O56: =IF(AND(L56="Yes",'Invoice Sample'!O56="No",M56="Yes"),C56*0.02,0) -> 0 | P56: =IF(AND('Invoice Sample'!P56="Yes",N56="No"),C56*0.015,0) -> 0
A57: ='Invoice Sample'!A57 -> INV-2086 | B57: ='Invoice Sample'!C57 -> One-off | C57: ='Invoice Sample'!E57 -> 39295.81 | D57: ='Invoice Sample'!M57 -> Tier 2 ($10K-$50K) | E57: ='Invoice Sample'!F57 -> Net 30 | F57: =IF(B57="Recurring",'Future-State Model'!E22,'Future-State Model'!E23) -> 1.5735294 | G57: ='Future-State Model'!E24 -> 2.4157 | H57: =IF(OR(D57="Tier 2 ($10K-$50K)",D57="Tier 3 (>$50K)"),'Future-State Model'!E25,0) -> 2.0645657 | I57: =IF(D57="Tier 3 (>$50K)",'Future-State Model'!E26,0) -> 0 | J57: ='Future-State Model'!E27 -> 0.686 | K57: =SUM(F57:J57) -> 6.7397951 | L57: =IF(E57="2/10 Net 30","Yes","No") -> No | M57: =IF(AND(L57="Yes",(F57+G57+H57+I57)<=10),"Yes","No") -> No | N57: =IF(K57>30,"Yes","No") -> No | O57: =IF(AND(L57="Yes",'Invoice Sample'!O57="No",M57="Yes"),C57*0.02,0) -> 0 | P57: =IF(AND('Invoice Sample'!P57="Yes",N57="No"),C57*0.015,0) -> 0
A58: ='Invoice Sample'!A58 -> INV-2087 | B58: ='Invoice Sample'!C58 -> Recurring | C58: ='Invoice Sample'!E58 -> 3791.34 | D58: ='Invoice Sample'!M58 -> Tier 1 ($500-$10K) | E58: ='Invoice Sample'!F58 -> 2/10 Net 30 | F58: =IF(B58="Recurring",'Future-State Model'!E22,'Future-State Model'!E23) -> 0.23744186 | G58: ='Future-State Model'!E24 -> 2.4157 | H58: =IF(OR(D58="Tier 2 ($10K-$50K)",D58="Tier 3 (>$50K)"),'Future-State Model'!E25,0) -> 0 | I58: =IF(D58="Tier 3 (>$50K)",'Future-State Model'!E26,0) -> 0 | J58: ='Future-State Model'!E27 -> 0.686 | K58: =SUM(F58:J58) -> 3.3391419 | L58: =IF(E58="2/10 Net 30","Yes","No") -> Yes | M58: =IF(AND(L58="Yes",(F58+G58+H58+I58)<=10),"Yes","No") -> Yes | N58: =IF(K58>30,"Yes","No") -> No | O58: =IF(AND(L58="Yes",'Invoice Sample'!O58="No",M58="Yes"),C58*0.02,0) -> 75.8268 | P58: =IF(AND('Invoice Sample'!P58="Yes",N58="No"),C58*0.015,0) -> 0
A59: ='Invoice Sample'!A59 -> INV-2088 | B59: ='Invoice Sample'!C59 -> One-off | C59: ='Invoice Sample'!E59 -> 8039.19 | D59: ='Invoice Sample'!M59 -> Tier 1 ($500-$10K) | E59: ='Invoice Sample'!F59 -> 2/10 Net 30 | F59: =IF(B59="Recurring",'Future-State Model'!E22,'Future-State Model'!E23) -> 1.5735294 | G59: ='Future-State Model'!E24 -> 2.4157 | H59: =IF(OR(D59="Tier 2 ($10K-$50K)",D59="Tier 3 (>$50K)"),'Future-State Model'!E25,0) -> 0 | I59: =IF(D59="Tier 3 (>$50K)",'Future-State Model'!E26,0) -> 0 | J59: ='Future-State Model'!E27 -> 0.686 | K59: =SUM(F59:J59) -> 4.6752294 | L59: =IF(E59="2/10 Net 30","Yes","No") -> Yes | M59: =IF(AND(L59="Yes",(F59+G59+H59+I59)<=10),"Yes","No") -> Yes | N59: =IF(K59>30,"Yes","No") -> No | O59: =IF(AND(L59="Yes",'Invoice Sample'!O59="No",M59="Yes"),C59*0.02,0) -> 160.7838 | P59: =IF(AND('Invoice Sample'!P59="Yes",N59="No"),C59*0.015,0) -> 0
A60: ='Invoice Sample'!A60 -> INV-2089 | B60: ='Invoice Sample'!C60 -> Recurring | C60: ='Invoice Sample'!E60 -> 125.79 | D60: ='Invoice Sample'!M60 -> Tier 0 (<$500) | E60: ='Invoice Sample'!F60 -> Net 30 | F60: =IF(B60="Recurring",'Future-State Model'!E22,'Future-State Model'!E23) -> 0.23744186 | G60: ='Future-State Model'!E24 -> 2.4157 | H60: =IF(OR(D60="Tier 2 ($10K-$50K)",D60="Tier 3 (>$50K)"),'Future-State Model'!E25,0) -> 0 | I60: =IF(D60="Tier 3 (>$50K)",'Future-State Model'!E26,0) -> 0 | J60: ='Future-State Model'!E27 -> 0.686 | K60: =SUM(F60:J60) -> 3.3391419 | L60: =IF(E60="2/10 Net 30","Yes","No") -> No | M60: =IF(AND(L60="Yes",(F60+G60+H60+I60)<=10),"Yes","No") -> No | N60: =IF(K60>30,"Yes","No") -> No | O60: =IF(AND(L60="Yes",'Invoice Sample'!O60="No",M60="Yes"),C60*0.02,0) -> 0 | P60: =IF(AND('Invoice Sample'!P60="Yes",N60="No"),C60*0.015,0) -> 0
A61: ='Invoice Sample'!A61 -> INV-2090 | B61: ='Invoice Sample'!C61 -> Recurring | C61: ='Invoice Sample'!E61 -> 100.52 | D61: ='Invoice Sample'!M61 -> Tier 0 (<$500) | E61: ='Invoice Sample'!F61 -> 2/10 Net 30 | F61: =IF(B61="Recurring",'Future-State Model'!E22,'Future-State Model'!E23) -> 0.23744186 | G61: ='Future-State Model'!E24 -> 2.4157 | H61: =IF(OR(D61="Tier 2 ($10K-$50K)",D61="Tier 3 (>$50K)"),'Future-State Model'!E25,0) -> 0 | I61: =IF(D61="Tier 3 (>$50K)",'Future-State Model'!E26,0) -> 0 | J61: ='Future-State Model'!E27 -> 0.686 | K61: =SUM(F61:J61) -> 3.3391419 | L61: =IF(E61="2/10 Net 30","Yes","No") -> Yes | M61: =IF(AND(L61="Yes",(F61+G61+H61+I61)<=10),"Yes","No") -> Yes | N61: =IF(K61>30,"Yes","No") -> No | O61: =IF(AND(L61="Yes",'Invoice Sample'!O61="No",M61="Yes"),C61*0.02,0) -> 0 | P61: =IF(AND('Invoice Sample'!P61="Yes",N61="No"),C61*0.015,0) -> 0
A62: ='Invoice Sample'!A62 -> INV-2091 | B62: ='Invoice Sample'!C62 -> Recurring | C62: ='Invoice Sample'!E62 -> 781.24 | D62: ='Invoice Sample'!M62 -> Tier 1 ($500-$10K) | E62: ='Invoice Sample'!F62 -> Net 30 | F62: =IF(B62="Recurring",'Future-State Model'!E22,'Future-State Model'!E23) -> 0.23744186 | G62: ='Future-State Model'!E24 -> 2.4157 | H62: =IF(OR(D62="Tier 2 ($10K-$50K)",D62="Tier 3 (>$50K)"),'Future-State Model'!E25,0) -> 0 | I62: =IF(D62="Tier 3 (>$50K)",'Future-State Model'!E26,0) -> 0 | J62: ='Future-State Model'!E27 -> 0.686 | K62: =SUM(F62:J62) -> 3.3391419 | L62: =IF(E62="2/10 Net 30","Yes","No") -> No | M62: =IF(AND(L62="Yes",(F62+G62+H62+I62)<=10),"Yes","No") -> No | N62: =IF(K62>30,"Yes","No") -> No | O62: =IF(AND(L62="Yes",'Invoice Sample'!O62="No",M62="Yes"),C62*0.02,0) -> 0 | P62: =IF(AND('Invoice Sample'!P62="Yes",N62="No"),C62*0.015,0) -> 0
A63: ='Invoice Sample'!A63 -> INV-2092 | B63: ='Invoice Sample'!C63 -> One-off | C63: ='Invoice Sample'!E63 -> 6107.45 | D63: ='Invoice Sample'!M63 -> Tier 1 ($500-$10K) | E63: ='Invoice Sample'!F63 -> 2/10 Net 30 | F63: =IF(B63="Recurring",'Future-State Model'!E22,'Future-State Model'!E23) -> 1.5735294 | G63: ='Future-State Model'!E24 -> 2.4157 | H63: =IF(OR(D63="Tier 2 ($10K-$50K)",D63="Tier 3 (>$50K)"),'Future-State Model'!E25,0) -> 0 | I63: =IF(D63="Tier 3 (>$50K)",'Future-State Model'!E26,0) -> 0 | J63: ='Future-State Model'!E27 -> 0.686 | K63: =SUM(F63:J63) -> 4.6752294 | L63: =IF(E63="2/10 Net 30","Yes","No") -> Yes | M63: =IF(AND(L63="Yes",(F63+G63+H63+I63)<=10),"Yes","No") -> Yes | N63: =IF(K63>30,"Yes","No") -> No | O63: =IF(AND(L63="Yes",'Invoice Sample'!O63="No",M63="Yes"),C63*0.02,0) -> 122.149 | P63: =IF(AND('Invoice Sample'!P63="Yes",N63="No"),C63*0.015,0) -> 0
A64: ='Invoice Sample'!A64 -> INV-2093 | B64: ='Invoice Sample'!C64 -> Recurring | C64: ='Invoice Sample'!E64 -> 9987.06 | D64: ='Invoice Sample'!M64 -> Tier 1 ($500-$10K) | E64: ='Invoice Sample'!F64 -> 2/10 Net 30 | F64: =IF(B64="Recurring",'Future-State Model'!E22,'Future-State Model'!E23) -> 0.23744186 | G64: ='Future-State Model'!E24 -> 2.4157 | H64: =IF(OR(D64="Tier 2 ($10K-$50K)",D64="Tier 3 (>$50K)"),'Future-State Model'!E25,0) -> 0 | I64: =IF(D64="Tier 3 (>$50K)",'Future-State Model'!E26,0) -> 0 | J64: ='Future-State Model'!E27 -> 0.686 | K64: =SUM(F64:J64) -> 3.3391419 | L64: =IF(E64="2/10 Net 30","Yes","No") -> Yes | M64: =IF(AND(L64="Yes",(F64+G64+H64+I64)<=10),"Yes","No") -> Yes | N64: =IF(K64>30,"Yes","No") -> No | O64: =IF(AND(L64="Yes",'Invoice Sample'!O64="No",M64="Yes"),C64*0.02,0) -> 199.7412 | P64: =IF(AND('Invoice Sample'!P64="Yes",N64="No"),C64*0.015,0) -> 0
A65: ='Invoice Sample'!A65 -> INV-2094 | B65: ='Invoice Sample'!C65 -> One-off | C65: ='Invoice Sample'!E65 -> 15374.54 | D65: ='Invoice Sample'!M65 -> Tier 2 ($10K-$50K) | E65: ='Invoice Sample'!F65 -> 2/10 Net 30 | F65: =IF(B65="Recurring",'Future-State Model'!E22,'Future-State Model'!E23) -> 1.5735294 | G65: ='Future-State Model'!E24 -> 2.4157 | H65: =IF(OR(D65="Tier 2 ($10K-$50K)",D65="Tier 3 (>$50K)"),'Future-State Model'!E25,0) -> 2.0645657 | I65: =IF(D65="Tier 3 (>$50K)",'Future-State Model'!E26,0) -> 0 | J65: ='Future-State Model'!E27 -> 0.686 | K65: =SUM(F65:J65) -> 6.7397951 | L65: =IF(E65="2/10 Net 30","Yes","No") -> Yes | M65: =IF(AND(L65="Yes",(F65+G65+H65+I65)<=10),"Yes","No") -> Yes | N65: =IF(K65>30,"Yes","No") -> No | O65: =IF(AND(L65="Yes",'Invoice Sample'!O65="No",M65="Yes"),C65*0.02,0) -> 307.4908 | P65: =IF(AND('Invoice Sample'!P65="Yes",N65="No"),C65*0.015,0) -> 0
A66: ='Invoice Sample'!A66 -> INV-2095 | B66: ='Invoice Sample'!C66 -> Recurring | C66: ='Invoice Sample'!E66 -> 9611.53 | D66: ='Invoice Sample'!M66 -> Tier 1 ($500-$10K) | E66: ='Invoice Sample'!F66 -> Net 30 | F66: =IF(B66="Recurring",'Future-State Model'!E22,'Future-State Model'!E23) -> 0.23744186 | G66: ='Future-State Model'!E24 -> 2.4157 | H66: =IF(OR(D66="Tier 2 ($10K-$50K)",D66="Tier 3 (>$50K)"),'Future-State Model'!E25,0) -> 0 | I66: =IF(D66="Tier 3 (>$50K)",'Future-State Model'!E26,0) -> 0 | J66: ='Future-State Model'!E27 -> 0.686 | K66: =SUM(F66:J66) -> 3.3391419 | L66: =IF(E66="2/10 Net 30","Yes","No") -> No | M66: =IF(AND(L66="Yes",(F66+G66+H66+I66)<=10),"Yes","No") -> No | N66: =IF(K66>30,"Yes","No") -> No | O66: =IF(AND(L66="Yes",'Invoice Sample'!O66="No",M66="Yes"),C66*0.02,0) -> 0 | P66: =IF(AND('Invoice Sample'!P66="Yes",N66="No"),C66*0.015,0) -> 0
A67: ='Invoice Sample'!A67 -> INV-2096 | B67: ='Invoice Sample'!C67 -> One-off | C67: ='Invoice Sample'!E67 -> 7551.28 | D67: ='Invoice Sample'!M67 -> Tier 1 ($500-$10K) | E67: ='Invoice Sample'!F67 -> Net 30 | F67: =IF(B67="Recurring",'Future-State Model'!E22,'Future-State Model'!E23) -> 1.5735294 | G67: ='Future-State Model'!E24 -> 2.4157 | H67: =IF(OR(D67="Tier 2 ($10K-$50K)",D67="Tier 3 (>$50K)"),'Future-State Model'!E25,0) -> 0 | I67: =IF(D67="Tier 3 (>$50K)",'Future-State Model'!E26,0) -> 0 | J67: ='Future-State Model'!E27 -> 0.686 | K67: =SUM(F67:J67) -> 4.6752294 | L67: =IF(E67="2/10 Net 30","Yes","No") -> No | M67: =IF(AND(L67="Yes",(F67+G67+H67+I67)<=10),"Yes","No") -> No | N67: =IF(K67>30,"Yes","No") -> No | O67: =IF(AND(L67="Yes",'Invoice Sample'!O67="No",M67="Yes"),C67*0.02,0) -> 0 | P67: =IF(AND('Invoice Sample'!P67="Yes",N67="No"),C67*0.015,0) -> 0
A68: ='Invoice Sample'!A68 -> INV-2097 | B68: ='Invoice Sample'!C68 -> One-off | C68: ='Invoice Sample'!E68 -> 5833.59 | D68: ='Invoice Sample'!M68 -> Tier 1 ($500-$10K) | E68: ='Invoice Sample'!F68 -> Net 30 | F68: =IF(B68="Recurring",'Future-State Model'!E22,'Future-State Model'!E23) -> 1.5735294 | G68: ='Future-State Model'!E24 -> 2.4157 | H68: =IF(OR(D68="Tier 2 ($10K-$50K)",D68="Tier 3 (>$50K)"),'Future-State Model'!E25,0) -> 0 | I68: =IF(D68="Tier 3 (>$50K)",'Future-State Model'!E26,0) -> 0 | J68: ='Future-State Model'!E27 -> 0.686 | K68: =SUM(F68:J68) -> 4.6752294 | L68: =IF(E68="2/10 Net 30","Yes","No") -> No | M68: =IF(AND(L68="Yes",(F68+G68+H68+I68)<=10),"Yes","No") -> No | N68: =IF(K68>30,"Yes","No") -> No | O68: =IF(AND(L68="Yes",'Invoice Sample'!O68="No",M68="Yes"),C68*0.02,0) -> 0 | P68: =IF(AND('Invoice Sample'!P68="Yes",N68="No"),C68*0.015,0) -> 0
A69: ='Invoice Sample'!A69 -> INV-2098 | B69: ='Invoice Sample'!C69 -> One-off | C69: ='Invoice Sample'!E69 -> 7981.32 | D69: ='Invoice Sample'!M69 -> Tier 1 ($500-$10K) | E69: ='Invoice Sample'!F69 -> 2/10 Net 30 | F69: =IF(B69="Recurring",'Future-State Model'!E22,'Future-State Model'!E23) -> 1.5735294 | G69: ='Future-State Model'!E24 -> 2.4157 | H69: =IF(OR(D69="Tier 2 ($10K-$50K)",D69="Tier 3 (>$50K)"),'Future-State Model'!E25,0) -> 0 | I69: =IF(D69="Tier 3 (>$50K)",'Future-State Model'!E26,0) -> 0 | J69: ='Future-State Model'!E27 -> 0.686 | K69: =SUM(F69:J69) -> 4.6752294 | L69: =IF(E69="2/10 Net 30","Yes","No") -> Yes | M69: =IF(AND(L69="Yes",(F69+G69+H69+I69)<=10),"Yes","No") -> Yes | N69: =IF(K69>30,"Yes","No") -> No | O69: =IF(AND(L69="Yes",'Invoice Sample'!O69="No",M69="Yes"),C69*0.02,0) -> 159.6264 | P69: =IF(AND('Invoice Sample'!P69="Yes",N69="No"),C69*0.015,0) -> 0
A70: ='Invoice Sample'!A70 -> INV-2099 | B70: ='Invoice Sample'!C70 -> Recurring | C70: ='Invoice Sample'!E70 -> 482.15 | D70: ='Invoice Sample'!M70 -> Tier 0 (<$500) | E70: ='Invoice Sample'!F70 -> 2/10 Net 30 | F70: =IF(B70="Recurring",'Future-State Model'!E22,'Future-State Model'!E23) -> 0.23744186 | G70: ='Future-State Model'!E24 -> 2.4157 | H70: =IF(OR(D70="Tier 2 ($10K-$50K)",D70="Tier 3 (>$50K)"),'Future-State Model'!E25,0) -> 0 | I70: =IF(D70="Tier 3 (>$50K)",'Future-State Model'!E26,0) -> 0 | J70: ='Future-State Model'!E27 -> 0.686 | K70: =SUM(F70:J70) -> 3.3391419 | L70: =IF(E70="2/10 Net 30","Yes","No") -> Yes | M70: =IF(AND(L70="Yes",(F70+G70+H70+I70)<=10),"Yes","No") -> Yes | N70: =IF(K70>30,"Yes","No") -> No | O70: =IF(AND(L70="Yes",'Invoice Sample'!O70="No",M70="Yes"),C70*0.02,0) -> 0 | P70: =IF(AND('Invoice Sample'!P70="Yes",N70="No"),C70*0.015,0) -> 0
A71: ='Invoice Sample'!A71 -> INV-2100 | B71: ='Invoice Sample'!C71 -> Recurring | C71: ='Invoice Sample'!E71 -> 3469.1 | D71: ='Invoice Sample'!M71 -> Tier 1 ($500-$10K) | E71: ='Invoice Sample'!F71 -> 2/10 Net 30 | F71: =IF(B71="Recurring",'Future-State Model'!E22,'Future-State Model'!E23) -> 0.23744186 | G71: ='Future-State Model'!E24 -> 2.4157 | H71: =IF(OR(D71="Tier 2 ($10K-$50K)",D71="Tier 3 (>$50K)"),'Future-State Model'!E25,0) -> 0 | I71: =IF(D71="Tier 3 (>$50K)",'Future-State Model'!E26,0) -> 0 | J71: ='Future-State Model'!E27 -> 0.686 | K71: =SUM(F71:J71) -> 3.3391419 | L71: =IF(E71="2/10 Net 30","Yes","No") -> Yes | M71: =IF(AND(L71="Yes",(F71+G71+H71+I71)<=10),"Yes","No") -> Yes | N71: =IF(K71>30,"Yes","No") -> No | O71: =IF(AND(L71="Yes",'Invoice Sample'!O71="No",M71="Yes"),C71*0.02,0) -> 69.382 | P71: =IF(AND('Invoice Sample'!P71="Yes",N71="No"),C71*0.015,0) -> 0
A72: ='Invoice Sample'!A72 -> INV-2101 | B72: ='Invoice Sample'!C72 -> Recurring | C72: ='Invoice Sample'!E72 -> 4457.37 | D72: ='Invoice Sample'!M72 -> Tier 1 ($500-$10K) | E72: ='Invoice Sample'!F72 -> 2/10 Net 30 | F72: =IF(B72="Recurring",'Future-State Model'!E22,'Future-State Model'!E23) -> 0.23744186 | G72: ='Future-State Model'!E24 -> 2.4157 | H72: =IF(OR(D72="Tier 2 ($10K-$50K)",D72="Tier 3 (>$50K)"),'Future-State Model'!E25,0) -> 0 | I72: =IF(D72="Tier 3 (>$50K)",'Future-State Model'!E26,0) -> 0 | J72: ='Future-State Model'!E27 -> 0.686 | K72: =SUM(F72:J72) -> 3.3391419 | L72: =IF(E72="2/10 Net 30","Yes","No") -> Yes | M72: =IF(AND(L72="Yes",(F72+G72+H72+I72)<=10),"Yes","No") -> Yes | N72: =IF(K72>30,"Yes","No") -> No | O72: =IF(AND(L72="Yes",'Invoice Sample'!O72="No",M72="Yes"),C72*0.02,0) -> 89.1474 | P72: =IF(AND('Invoice Sample'!P72="Yes",N72="No"),C72*0.015,0) -> 0
A73: ='Invoice Sample'!A73 -> INV-2102 | B73: ='Invoice Sample'!C73 -> Recurring | C73: ='Invoice Sample'!E73 -> 7914.74 | D73: ='Invoice Sample'!M73 -> Tier 1 ($500-$10K) | E73: ='Invoice Sample'!F73 -> Net 30 | F73: =IF(B73="Recurring",'Future-State Model'!E22,'Future-State Model'!E23) -> 0.23744186 | G73: ='Future-State Model'!E24 -> 2.4157 | H73: =IF(OR(D73="Tier 2 ($10K-$50K)",D73="Tier 3 (>$50K)"),'Future-State Model'!E25,0) -> 0 | I73: =IF(D73="Tier 3 (>$50K)",'Future-State Model'!E26,0) -> 0 | J73: ='Future-State Model'!E27 -> 0.686 | K73: =SUM(F73:J73) -> 3.3391419 | L73: =IF(E73="2/10 Net 30","Yes","No") -> No | M73: =IF(AND(L73="Yes",(F73+G73+H73+I73)<=10),"Yes","No") -> No | N73: =IF(K73>30,"Yes","No") -> No | O73: =IF(AND(L73="Yes",'Invoice Sample'!O73="No",M73="Yes"),C73*0.02,0) -> 0 | P73: =IF(AND('Invoice Sample'!P73="Yes",N73="No"),C73*0.015,0) -> 0
A74: ='Invoice Sample'!A74 -> INV-2103 | B74: ='Invoice Sample'!C74 -> Recurring | C74: ='Invoice Sample'!E74 -> 47214.45 | D74: ='Invoice Sample'!M74 -> Tier 2 ($10K-$50K) | E74: ='Invoice Sample'!F74 -> 2/10 Net 30 | F74: =IF(B74="Recurring",'Future-State Model'!E22,'Future-State Model'!E23) -> 0.23744186 | G74: ='Future-State Model'!E24 -> 2.4157 | H74: =IF(OR(D74="Tier 2 ($10K-$50K)",D74="Tier 3 (>$50K)"),'Future-State Model'!E25,0) -> 2.0645657 | I74: =IF(D74="Tier 3 (>$50K)",'Future-State Model'!E26,0) -> 0 | J74: ='Future-State Model'!E27 -> 0.686 | K74: =SUM(F74:J74) -> 5.4037075 | L74: =IF(E74="2/10 Net 30","Yes","No") -> Yes | M74: =IF(AND(L74="Yes",(F74+G74+H74+I74)<=10),"Yes","No") -> Yes | N74: =IF(K74>30,"Yes","No") -> No | O74: =IF(AND(L74="Yes",'Invoice Sample'!O74="No",M74="Yes"),C74*0.02,0) -> 944.289 | P74: =IF(AND('Invoice Sample'!P74="Yes",N74="No"),C74*0.015,0) -> 0
A75: ='Invoice Sample'!A75 -> INV-2104 | B75: ='Invoice Sample'!C75 -> One-off | C75: ='Invoice Sample'!E75 -> 2288.87 | D75: ='Invoice Sample'!M75 -> Tier 1 ($500-$10K) | E75: ='Invoice Sample'!F75 -> 2/10 Net 30 | F75: =IF(B75="Recurring",'Future-State Model'!E22,'Future-State Model'!E23) -> 1.5735294 | G75: ='Future-State Model'!E24 -> 2.4157 | H75: =IF(OR(D75="Tier 2 ($10K-$50K)",D75="Tier 3 (>$50K)"),'Future-State Model'!E25,0) -> 0 | I75: =IF(D75="Tier 3 (>$50K)",'Future-State Model'!E26,0) -> 0 | J75: ='Future-State Model'!E27 -> 0.686 | K75: =SUM(F75:J75) -> 4.6752294 | L75: =IF(E75="2/10 Net 30","Yes","No") -> Yes | M75: =IF(AND(L75="Yes",(F75+G75+H75+I75)<=10),"Yes","No") -> Yes | N75: =IF(K75>30,"Yes","No") -> No | O75: =IF(AND(L75="Yes",'Invoice Sample'!O75="No",M75="Yes"),C75*0.02,0) -> 45.7774 | P75: =IF(AND('Invoice Sample'!P75="Yes",N75="No"),C75*0.015,0) -> 0
A76: ='Invoice Sample'!A76 -> INV-2105 | B76: ='Invoice Sample'!C76 -> One-off | C76: ='Invoice Sample'!E76 -> 437.56 | D76: ='Invoice Sample'!M76 -> Tier 0 (<$500) | E76: ='Invoice Sample'!F76 -> Net 30 | F76: =IF(B76="Recurring",'Future-State Model'!E22,'Future-State Model'!E23) -> 1.5735294 | G76: ='Future-State Model'!E24 -> 2.4157 | H76: =IF(OR(D76="Tier 2 ($10K-$50K)",D76="Tier 3 (>$50K)"),'Future-State Model'!E25,0) -> 0 | I76: =IF(D76="Tier 3 (>$50K)",'Future-State Model'!E26,0) -> 0 | J76: ='Future-State Model'!E27 -> 0.686 | K76: =SUM(F76:J76) -> 4.6752294 | L76: =IF(E76="2/10 Net 30","Yes","No") -> No | M76: =IF(AND(L76="Yes",(F76+G76+H76+I76)<=10),"Yes","No") -> No | N76: =IF(K76>30,"Yes","No") -> No | O76: =IF(AND(L76="Yes",'Invoice Sample'!O76="No",M76="Yes"),C76*0.02,0) -> 0 | P76: =IF(AND('Invoice Sample'!P76="Yes",N76="No"),C76*0.015,0) -> 0
A77: ='Invoice Sample'!A77 -> INV-2106 | B77: ='Invoice Sample'!C77 -> Recurring | C77: ='Invoice Sample'!E77 -> 4816.89 | D77: ='Invoice Sample'!M77 -> Tier 1 ($500-$10K) | E77: ='Invoice Sample'!F77 -> Net 30 | F77: =IF(B77="Recurring",'Future-State Model'!E22,'Future-State Model'!E23) -> 0.23744186 | G77: ='Future-State Model'!E24 -> 2.4157 | H77: =IF(OR(D77="Tier 2 ($10K-$50K)",D77="Tier 3 (>$50K)"),'Future-State Model'!E25,0) -> 0 | I77: =IF(D77="Tier 3 (>$50K)",'Future-State Model'!E26,0) -> 0 | J77: ='Future-State Model'!E27 -> 0.686 | K77: =SUM(F77:J77) -> 3.3391419 | L77: =IF(E77="2/10 Net 30","Yes","No") -> No | M77: =IF(AND(L77="Yes",(F77+G77+H77+I77)<=10),"Yes","No") -> No | N77: =IF(K77>30,"Yes","No") -> No | O77: =IF(AND(L77="Yes",'Invoice Sample'!O77="No",M77="Yes"),C77*0.02,0) -> 0 | P77: =IF(AND('Invoice Sample'!P77="Yes",N77="No"),C77*0.015,0) -> 0
A78: ='Invoice Sample'!A78 -> INV-2107 | B78: ='Invoice Sample'!C78 -> Recurring | C78: ='Invoice Sample'!E78 -> 4432.83 | D78: ='Invoice Sample'!M78 -> Tier 1 ($500-$10K) | E78: ='Invoice Sample'!F78 -> 2/10 Net 30 | F78: =IF(B78="Recurring",'Future-State Model'!E22,'Future-State Model'!E23) -> 0.23744186 | G78: ='Future-State Model'!E24 -> 2.4157 | H78: =IF(OR(D78="Tier 2 ($10K-$50K)",D78="Tier 3 (>$50K)"),'Future-State Model'!E25,0) -> 0 | I78: =IF(D78="Tier 3 (>$50K)",'Future-State Model'!E26,0) -> 0 | J78: ='Future-State Model'!E27 -> 0.686 | K78: =SUM(F78:J78) -> 3.3391419 | L78: =IF(E78="2/10 Net 30","Yes","No") -> Yes | M78: =IF(AND(L78="Yes",(F78+G78+H78+I78)<=10),"Yes","No") -> Yes | N78: =IF(K78>30,"Yes","No") -> No | O78: =IF(AND(L78="Yes",'Invoice Sample'!O78="No",M78="Yes"),C78*0.02,0) -> 88.6566 | P78: =IF(AND('Invoice Sample'!P78="Yes",N78="No"),C78*0.015,0) -> 0
A79: ='Invoice Sample'!A79 -> INV-2108 | B79: ='Invoice Sample'!C79 -> Recurring | C79: ='Invoice Sample'!E79 -> 7515.78 | D79: ='Invoice Sample'!M79 -> Tier 1 ($500-$10K) | E79: ='Invoice Sample'!F79 -> 2/10 Net 30 | F79: =IF(B79="Recurring",'Future-State Model'!E22,'Future-State Model'!E23) -> 0.23744186 | G79: ='Future-State Model'!E24 -> 2.4157 | H79: =IF(OR(D79="Tier 2 ($10K-$50K)",D79="Tier 3 (>$50K)"),'Future-State Model'!E25,0) -> 0 | I79: =IF(D79="Tier 3 (>$50K)",'Future-State Model'!E26,0) -> 0 | J79: ='Future-State Model'!E27 -> 0.686 | K79: =SUM(F79:J79) -> 3.3391419 | L79: =IF(E79="2/10 Net 30","Yes","No") -> Yes | M79: =IF(AND(L79="Yes",(F79+G79+H79+I79)<=10),"Yes","No") -> Yes | N79: =IF(K79>30,"Yes","No") -> No | O79: =IF(AND(L79="Yes",'Invoice Sample'!O79="No",M79="Yes"),C79*0.02,0) -> 150.3156 | P79: =IF(AND('Invoice Sample'!P79="Yes",N79="No"),C79*0.015,0) -> 0
A80: ='Invoice Sample'!A80 -> INV-2109 | B80: ='Invoice Sample'!C80 -> Recurring | C80: ='Invoice Sample'!E80 -> 9920.87 | D80: ='Invoice Sample'!M80 -> Tier 1 ($500-$10K) | E80: ='Invoice Sample'!F80 -> 2/10 Net 30 | F80: =IF(B80="Recurring",'Future-State Model'!E22,'Future-State Model'!E23) -> 0.23744186 | G80: ='Future-State Model'!E24 -> 2.4157 | H80: =IF(OR(D80="Tier 2 ($10K-$50K)",D80="Tier 3 (>$50K)"),'Future-State Model'!E25,0) -> 0 | I80: =IF(D80="Tier 3 (>$50K)",'Future-State Model'!E26,0) -> 0 | J80: ='Future-State Model'!E27 -> 0.686 | K80: =SUM(F80:J80) -> 3.3391419 | L80: =IF(E80="2/10 Net 30","Yes","No") -> Yes | M80: =IF(AND(L80="Yes",(F80+G80+H80+I80)<=10),"Yes","No") -> Yes | N80: =IF(K80>30,"Yes","No") -> No | O80: =IF(AND(L80="Yes",'Invoice Sample'!O80="No",M80="Yes"),C80*0.02,0) -> 198.4174 | P80: =IF(AND('Invoice Sample'!P80="Yes",N80="No"),C80*0.015,0) -> 0
A81: ='Invoice Sample'!A81 -> INV-2110 | B81: ='Invoice Sample'!C81 -> One-off | C81: ='Invoice Sample'!E81 -> 34871.06 | D81: ='Invoice Sample'!M81 -> Tier 2 ($10K-$50K) | E81: ='Invoice Sample'!F81 -> 2/10 Net 30 | F81: =IF(B81="Recurring",'Future-State Model'!E22,'Future-State Model'!E23) -> 1.5735294 | G81: ='Future-State Model'!E24 -> 2.4157 | H81: =IF(OR(D81="Tier 2 ($10K-$50K)",D81="Tier 3 (>$50K)"),'Future-State Model'!E25,0) -> 2.0645657 | I81: =IF(D81="Tier 3 (>$50K)",'Future-State Model'!E26,0) -> 0 | J81: ='Future-State Model'!E27 -> 0.686 | K81: =SUM(F81:J81) -> 6.7397951 | L81: =IF(E81="2/10 Net 30","Yes","No") -> Yes | M81: =IF(AND(L81="Yes",(F81+G81+H81+I81)<=10),"Yes","No") -> Yes | N81: =IF(K81>30,"Yes","No") -> No | O81: =IF(AND(L81="Yes",'Invoice Sample'!O81="No",M81="Yes"),C81*0.02,0) -> 697.4212 | P81: =IF(AND('Invoice Sample'!P81="Yes",N81="No"),C81*0.015,0) -> 0
A82: ='Invoice Sample'!A82 -> INV-2111 | B82: ='Invoice Sample'!C82 -> Recurring | C82: ='Invoice Sample'!E82 -> 2696.93 | D82: ='Invoice Sample'!M82 -> Tier 1 ($500-$10K) | E82: ='Invoice Sample'!F82 -> Net 30 | F82: =IF(B82="Recurring",'Future-State Model'!E22,'Future-State Model'!E23) -> 0.23744186 | G82: ='Future-State Model'!E24 -> 2.4157 | H82: =IF(OR(D82="Tier 2 ($10K-$50K)",D82="Tier 3 (>$50K)"),'Future-State Model'!E25,0) -> 0 | I82: =IF(D82="Tier 3 (>$50K)",'Future-State Model'!E26,0) -> 0 | J82: ='Future-State Model'!E27 -> 0.686 | K82: =SUM(F82:J82) -> 3.3391419 | L82: =IF(E82="2/10 Net 30","Yes","No") -> No | M82: =IF(AND(L82="Yes",(F82+G82+H82+I82)<=10),"Yes","No") -> No | N82: =IF(K82>30,"Yes","No") -> No | O82: =IF(AND(L82="Yes",'Invoice Sample'!O82="No",M82="Yes"),C82*0.02,0) -> 0 | P82: =IF(AND('Invoice Sample'!P82="Yes",N82="No"),C82*0.015,0) -> 0
A83: ='Invoice Sample'!A83 -> INV-2112 | B83: ='Invoice Sample'!C83 -> Recurring | C83: ='Invoice Sample'!E83 -> 7704.25 | D83: ='Invoice Sample'!M83 -> Tier 1 ($500-$10K) | E83: ='Invoice Sample'!F83 -> Net 30 | F83: =IF(B83="Recurring",'Future-State Model'!E22,'Future-State Model'!E23) -> 0.23744186 | G83: ='Future-State Model'!E24 -> 2.4157 | H83: =IF(OR(D83="Tier 2 ($10K-$50K)",D83="Tier 3 (>$50K)"),'Future-State Model'!E25,0) -> 0 | I83: =IF(D83="Tier 3 (>$50K)",'Future-State Model'!E26,0) -> 0 | J83: ='Future-State Model'!E27 -> 0.686 | K83: =SUM(F83:J83) -> 3.3391419 | L83: =IF(E83="2/10 Net 30","Yes","No") -> No | M83: =IF(AND(L83="Yes",(F83+G83+H83+I83)<=10),"Yes","No") -> No | N83: =IF(K83>30,"Yes","No") -> No | O83: =IF(AND(L83="Yes",'Invoice Sample'!O83="No",M83="Yes"),C83*0.02,0) -> 0 | P83: =IF(AND('Invoice Sample'!P83="Yes",N83="No"),C83*0.015,0) -> 0
A84: ='Invoice Sample'!A84 -> INV-2113 | B84: ='Invoice Sample'!C84 -> Recurring | C84: ='Invoice Sample'!E84 -> 45585.37 | D84: ='Invoice Sample'!M84 -> Tier 2 ($10K-$50K) | E84: ='Invoice Sample'!F84 -> 2/10 Net 30 | F84: =IF(B84="Recurring",'Future-State Model'!E22,'Future-State Model'!E23) -> 0.23744186 | G84: ='Future-State Model'!E24 -> 2.4157 | H84: =IF(OR(D84="Tier 2 ($10K-$50K)",D84="Tier 3 (>$50K)"),'Future-State Model'!E25,0) -> 2.0645657 | I84: =IF(D84="Tier 3 (>$50K)",'Future-State Model'!E26,0) -> 0 | J84: ='Future-State Model'!E27 -> 0.686 | K84: =SUM(F84:J84) -> 5.4037075 | L84: =IF(E84="2/10 Net 30","Yes","No") -> Yes | M84: =IF(AND(L84="Yes",(F84+G84+H84+I84)<=10),"Yes","No") -> Yes | N84: =IF(K84>30,"Yes","No") -> No | O84: =IF(AND(L84="Yes",'Invoice Sample'!O84="No",M84="Yes"),C84*0.02,0) -> 911.7074 | P84: =IF(AND('Invoice Sample'!P84="Yes",N84="No"),C84*0.015,0) -> 0
A85: ='Invoice Sample'!A85 -> INV-2114 | B85: ='Invoice Sample'!C85 -> One-off | C85: ='Invoice Sample'!E85 -> 168.89 | D85: ='Invoice Sample'!M85 -> Tier 0 (<$500) | E85: ='Invoice Sample'!F85 -> Net 30 | F85: =IF(B85="Recurring",'Future-State Model'!E22,'Future-State Model'!E23) -> 1.5735294 | G85: ='Future-State Model'!E24 -> 2.4157 | H85: =IF(OR(D85="Tier 2 ($10K-$50K)",D85="Tier 3 (>$50K)"),'Future-State Model'!E25,0) -> 0 | I85: =IF(D85="Tier 3 (>$50K)",'Future-State Model'!E26,0) -> 0 | J85: ='Future-State Model'!E27 -> 0.686 | K85: =SUM(F85:J85) -> 4.6752294 | L85: =IF(E85="2/10 Net 30","Yes","No") -> No | M85: =IF(AND(L85="Yes",(F85+G85+H85+I85)<=10),"Yes","No") -> No | N85: =IF(K85>30,"Yes","No") -> No | O85: =IF(AND(L85="Yes",'Invoice Sample'!O85="No",M85="Yes"),C85*0.02,0) -> 0 | P85: =IF(AND('Invoice Sample'!P85="Yes",N85="No"),C85*0.015,0) -> 0
A86: ='Invoice Sample'!A86 -> INV-2115 | B86: ='Invoice Sample'!C86 -> Recurring | C86: ='Invoice Sample'!E86 -> 386.35 | D86: ='Invoice Sample'!M86 -> Tier 0 (<$500) | E86: ='Invoice Sample'!F86 -> Net 30 | F86: =IF(B86="Recurring",'Future-State Model'!E22,'Future-State Model'!E23) -> 0.23744186 | G86: ='Future-State Model'!E24 -> 2.4157 | H86: =IF(OR(D86="Tier 2 ($10K-$50K)",D86="Tier 3 (>$50K)"),'Future-State Model'!E25,0) -> 0 | I86: =IF(D86="Tier 3 (>$50K)",'Future-State Model'!E26,0) -> 0 | J86: ='Future-State Model'!E27 -> 0.686 | K86: =SUM(F86:J86) -> 3.3391419 | L86: =IF(E86="2/10 Net 30","Yes","No") -> No | M86: =IF(AND(L86="Yes",(F86+G86+H86+I86)<=10),"Yes","No") -> No | N86: =IF(K86>30,"Yes","No") -> No | O86: =IF(AND(L86="Yes",'Invoice Sample'!O86="No",M86="Yes"),C86*0.02,0) -> 0 | P86: =IF(AND('Invoice Sample'!P86="Yes",N86="No"),C86*0.015,0) -> 0
A87: ='Invoice Sample'!A87 -> INV-2116 | B87: ='Invoice Sample'!C87 -> One-off | C87: ='Invoice Sample'!E87 -> 121.84 | D87: ='Invoice Sample'!M87 -> Tier 0 (<$500) | E87: ='Invoice Sample'!F87 -> 2/10 Net 30 | F87: =IF(B87="Recurring",'Future-State Model'!E22,'Future-State Model'!E23) -> 1.5735294 | G87: ='Future-State Model'!E24 -> 2.4157 | H87: =IF(OR(D87="Tier 2 ($10K-$50K)",D87="Tier 3 (>$50K)"),'Future-State Model'!E25,0) -> 0 | I87: =IF(D87="Tier 3 (>$50K)",'Future-State Model'!E26,0) -> 0 | J87: ='Future-State Model'!E27 -> 0.686 | K87: =SUM(F87:J87) -> 4.6752294 | L87: =IF(E87="2/10 Net 30","Yes","No") -> Yes | M87: =IF(AND(L87="Yes",(F87+G87+H87+I87)<=10),"Yes","No") -> Yes | N87: =IF(K87>30,"Yes","No") -> No | O87: =IF(AND(L87="Yes",'Invoice Sample'!O87="No",M87="Yes"),C87*0.02,0) -> 0 | P87: =IF(AND('Invoice Sample'!P87="Yes",N87="No"),C87*0.015,0) -> 0
A88: ='Invoice Sample'!A88 -> INV-2117 | B88: ='Invoice Sample'!C88 -> Recurring | C88: ='Invoice Sample'!E88 -> 8931.04 | D88: ='Invoice Sample'!M88 -> Tier 1 ($500-$10K) | E88: ='Invoice Sample'!F88 -> 2/10 Net 30 | F88: =IF(B88="Recurring",'Future-State Model'!E22,'Future-State Model'!E23) -> 0.23744186 | G88: ='Future-State Model'!E24 -> 2.4157 | H88: =IF(OR(D88="Tier 2 ($10K-$50K)",D88="Tier 3 (>$50K)"),'Future-State Model'!E25,0) -> 0 | I88: =IF(D88="Tier 3 (>$50K)",'Future-State Model'!E26,0) -> 0 | J88: ='Future-State Model'!E27 -> 0.686 | K88: =SUM(F88:J88) -> 3.3391419 | L88: =IF(E88="2/10 Net 30","Yes","No") -> Yes | M88: =IF(AND(L88="Yes",(F88+G88+H88+I88)<=10),"Yes","No") -> Yes | N88: =IF(K88>30,"Yes","No") -> No | O88: =IF(AND(L88="Yes",'Invoice Sample'!O88="No",M88="Yes"),C88*0.02,0) -> 178.6208 | P88: =IF(AND('Invoice Sample'!P88="Yes",N88="No"),C88*0.015,0) -> 0
A89: ='Invoice Sample'!A89 -> INV-2118 | B89: ='Invoice Sample'!C89 -> One-off | C89: ='Invoice Sample'!E89 -> 2368.85 | D89: ='Invoice Sample'!M89 -> Tier 1 ($500-$10K) | E89: ='Invoice Sample'!F89 -> 2/10 Net 30 | F89: =IF(B89="Recurring",'Future-State Model'!E22,'Future-State Model'!E23) -> 1.5735294 | G89: ='Future-State Model'!E24 -> 2.4157 | H89: =IF(OR(D89="Tier 2 ($10K-$50K)",D89="Tier 3 (>$50K)"),'Future-State Model'!E25,0) -> 0 | I89: =IF(D89="Tier 3 (>$50K)",'Future-State Model'!E26,0) -> 0 | J89: ='Future-State Model'!E27 -> 0.686 | K89: =SUM(F89:J89) -> 4.6752294 | L89: =IF(E89="2/10 Net 30","Yes","No") -> Yes | M89: =IF(AND(L89="Yes",(F89+G89+H89+I89)<=10),"Yes","No") -> Yes | N89: =IF(K89>30,"Yes","No") -> No | O89: =IF(AND(L89="Yes",'Invoice Sample'!O89="No",M89="Yes"),C89*0.02,0) -> 47.377 | P89: =IF(AND('Invoice Sample'!P89="Yes",N89="No"),C89*0.015,0) -> 0
A90: ='Invoice Sample'!A90 -> INV-2119 | B90: ='Invoice Sample'!C90 -> One-off | C90: ='Invoice Sample'!E90 -> 121.45 | D90: ='Invoice Sample'!M90 -> Tier 0 (<$500) | E90: ='Invoice Sample'!F90 -> Net 30 | F90: =IF(B90="Recurring",'Future-State Model'!E22,'Future-State Model'!E23) -> 1.5735294 | G90: ='Future-State Model'!E24 -> 2.4157 | H90: =IF(OR(D90="Tier 2 ($10K-$50K)",D90="Tier 3 (>$50K)"),'Future-State Model'!E25,0) -> 0 | I90: =IF(D90="Tier 3 (>$50K)",'Future-State Model'!E26,0) -> 0 | J90: ='Future-State Model'!E27 -> 0.686 | K90: =SUM(F90:J90) -> 4.6752294 | L90: =IF(E90="2/10 Net 30","Yes","No") -> No | M90: =IF(AND(L90="Yes",(F90+G90+H90+I90)<=10),"Yes","No") -> No | N90: =IF(K90>30,"Yes","No") -> No | O90: =IF(AND(L90="Yes",'Invoice Sample'!O90="No",M90="Yes"),C90*0.02,0) -> 0 | P90: =IF(AND('Invoice Sample'!P90="Yes",N90="No"),C90*0.015,0) -> 0
A91: ='Invoice Sample'!A91 -> INV-2120 | B91: ='Invoice Sample'!C91 -> Recurring | C91: ='Invoice Sample'!E91 -> 4949.49 | D91: ='Invoice Sample'!M91 -> Tier 1 ($500-$10K) | E91: ='Invoice Sample'!F91 -> 2/10 Net 30 | F91: =IF(B91="Recurring",'Future-State Model'!E22,'Future-State Model'!E23) -> 0.23744186 | G91: ='Future-State Model'!E24 -> 2.4157 | H91: =IF(OR(D91="Tier 2 ($10K-$50K)",D91="Tier 3 (>$50K)"),'Future-State Model'!E25,0) -> 0 | I91: =IF(D91="Tier 3 (>$50K)",'Future-State Model'!E26,0) -> 0 | J91: ='Future-State Model'!E27 -> 0.686 | K91: =SUM(F91:J91) -> 3.3391419 | L91: =IF(E91="2/10 Net 30","Yes","No") -> Yes | M91: =IF(AND(L91="Yes",(F91+G91+H91+I91)<=10),"Yes","No") -> Yes | N91: =IF(K91>30,"Yes","No") -> No | O91: =IF(AND(L91="Yes",'Invoice Sample'!O91="No",M91="Yes"),C91*0.02,0) -> 98.9898 | P91: =IF(AND('Invoice Sample'!P91="Yes",N91="No"),C91*0.015,0) -> 0
A92: ='Invoice Sample'!A92 -> INV-2121 | B92: ='Invoice Sample'!C92 -> Recurring | C92: ='Invoice Sample'!E92 -> 203.51 | D92: ='Invoice Sample'!M92 -> Tier 0 (<$500) | E92: ='Invoice Sample'!F92 -> Net 30 | F92: =IF(B92="Recurring",'Future-State Model'!E22,'Future-State Model'!E23) -> 0.23744186 | G92: ='Future-State Model'!E24 -> 2.4157 | H92: =IF(OR(D92="Tier 2 ($10K-$50K)",D92="Tier 3 (>$50K)"),'Future-State Model'!E25,0) -> 0 | I92: =IF(D92="Tier 3 (>$50K)",'Future-State Model'!E26,0) -> 0 | J92: ='Future-State Model'!E27 -> 0.686 | K92: =SUM(F92:J92) -> 3.3391419 | L92: =IF(E92="2/10 Net 30","Yes","No") -> No | M92: =IF(AND(L92="Yes",(F92+G92+H92+I92)<=10),"Yes","No") -> No | N92: =IF(K92>30,"Yes","No") -> No | O92: =IF(AND(L92="Yes",'Invoice Sample'!O92="No",M92="Yes"),C92*0.02,0) -> 0 | P92: =IF(AND('Invoice Sample'!P92="Yes",N92="No"),C92*0.015,0) -> 0
A93: ='Invoice Sample'!A93 -> INV-2122 | B93: ='Invoice Sample'!C93 -> One-off | C93: ='Invoice Sample'!E93 -> 1182.24 | D93: ='Invoice Sample'!M93 -> Tier 1 ($500-$10K) | E93: ='Invoice Sample'!F93 -> 2/10 Net 30 | F93: =IF(B93="Recurring",'Future-State Model'!E22,'Future-State Model'!E23) -> 1.5735294 | G93: ='Future-State Model'!E24 -> 2.4157 | H93: =IF(OR(D93="Tier 2 ($10K-$50K)",D93="Tier 3 (>$50K)"),'Future-State Model'!E25,0) -> 0 | I93: =IF(D93="Tier 3 (>$50K)",'Future-State Model'!E26,0) -> 0 | J93: ='Future-State Model'!E27 -> 0.686 | K93: =SUM(F93:J93) -> 4.6752294 | L93: =IF(E93="2/10 Net 30","Yes","No") -> Yes | M93: =IF(AND(L93="Yes",(F93+G93+H93+I93)<=10),"Yes","No") -> Yes | N93: =IF(K93>30,"Yes","No") -> No | O93: =IF(AND(L93="Yes",'Invoice Sample'!O93="No",M93="Yes"),C93*0.02,0) -> 0 | P93: =IF(AND('Invoice Sample'!P93="Yes",N93="No"),C93*0.015,0) -> 0
A94: ='Invoice Sample'!A94 -> INV-2123 | B94: ='Invoice Sample'!C94 -> Recurring | C94: ='Invoice Sample'!E94 -> 2905.67 | D94: ='Invoice Sample'!M94 -> Tier 1 ($500-$10K) | E94: ='Invoice Sample'!F94 -> 2/10 Net 30 | F94: =IF(B94="Recurring",'Future-State Model'!E22,'Future-State Model'!E23) -> 0.23744186 | G94: ='Future-State Model'!E24 -> 2.4157 | H94: =IF(OR(D94="Tier 2 ($10K-$50K)",D94="Tier 3 (>$50K)"),'Future-State Model'!E25,0) -> 0 | I94: =IF(D94="Tier 3 (>$50K)",'Future-State Model'!E26,0) -> 0 | J94: ='Future-State Model'!E27 -> 0.686 | K94: =SUM(F94:J94) -> 3.3391419 | L94: =IF(E94="2/10 Net 30","Yes","No") -> Yes | M94: =IF(AND(L94="Yes",(F94+G94+H94+I94)<=10),"Yes","No") -> Yes | N94: =IF(K94>30,"Yes","No") -> No | O94: =IF(AND(L94="Yes",'Invoice Sample'!O94="No",M94="Yes"),C94*0.02,0) -> 58.1134 | P94: =IF(AND('Invoice Sample'!P94="Yes",N94="No"),C94*0.015,0) -> 0
A95: ='Invoice Sample'!A95 -> INV-2124 | B95: ='Invoice Sample'!C95 -> Recurring | C95: ='Invoice Sample'!E95 -> 7836.58 | D95: ='Invoice Sample'!M95 -> Tier 1 ($500-$10K) | E95: ='Invoice Sample'!F95 -> 2/10 Net 30 | F95: =IF(B95="Recurring",'Future-State Model'!E22,'Future-State Model'!E23) -> 0.23744186 | G95: ='Future-State Model'!E24 -> 2.4157 | H95: =IF(OR(D95="Tier 2 ($10K-$50K)",D95="Tier 3 (>$50K)"),'Future-State Model'!E25,0) -> 0 | I95: =IF(D95="Tier 3 (>$50K)",'Future-State Model'!E26,0) -> 0 | J95: ='Future-State Model'!E27 -> 0.686 | K95: =SUM(F95:J95) -> 3.3391419 | L95: =IF(E95="2/10 Net 30","Yes","No") -> Yes | M95: =IF(AND(L95="Yes",(F95+G95+H95+I95)<=10),"Yes","No") -> Yes | N95: =IF(K95>30,"Yes","No") -> No | O95: =IF(AND(L95="Yes",'Invoice Sample'!O95="No",M95="Yes"),C95*0.02,0) -> 156.7316 | P95: =IF(AND('Invoice Sample'!P95="Yes",N95="No"),C95*0.015,0) -> 0
A96: ='Invoice Sample'!A96 -> INV-2125 | B96: ='Invoice Sample'!C96 -> One-off | C96: ='Invoice Sample'!E96 -> 4428.48 | D96: ='Invoice Sample'!M96 -> Tier 1 ($500-$10K) | E96: ='Invoice Sample'!F96 -> Net 30 | F96: =IF(B96="Recurring",'Future-State Model'!E22,'Future-State Model'!E23) -> 1.5735294 | G96: ='Future-State Model'!E24 -> 2.4157 | H96: =IF(OR(D96="Tier 2 ($10K-$50K)",D96="Tier 3 (>$50K)"),'Future-State Model'!E25,0) -> 0 | I96: =IF(D96="Tier 3 (>$50K)",'Future-State Model'!E26,0) -> 0 | J96: ='Future-State Model'!E27 -> 0.686 | K96: =SUM(F96:J96) -> 4.6752294 | L96: =IF(E96="2/10 Net 30","Yes","No") -> No | M96: =IF(AND(L96="Yes",(F96+G96+H96+I96)<=10),"Yes","No") -> No | N96: =IF(K96>30,"Yes","No") -> No | O96: =IF(AND(L96="Yes",'Invoice Sample'!O96="No",M96="Yes"),C96*0.02,0) -> 0 | P96: =IF(AND('Invoice Sample'!P96="Yes",N96="No"),C96*0.015,0) -> 0
A97: ='Invoice Sample'!A97 -> INV-2126 | B97: ='Invoice Sample'!C97 -> Recurring | C97: ='Invoice Sample'!E97 -> 2031.75 | D97: ='Invoice Sample'!M97 -> Tier 1 ($500-$10K) | E97: ='Invoice Sample'!F97 -> Net 30 | F97: =IF(B97="Recurring",'Future-State Model'!E22,'Future-State Model'!E23) -> 0.23744186 | G97: ='Future-State Model'!E24 -> 2.4157 | H97: =IF(OR(D97="Tier 2 ($10K-$50K)",D97="Tier 3 (>$50K)"),'Future-State Model'!E25,0) -> 0 | I97: =IF(D97="Tier 3 (>$50K)",'Future-State Model'!E26,0) -> 0 | J97: ='Future-State Model'!E27 -> 0.686 | K97: =SUM(F97:J97) -> 3.3391419 | L97: =IF(E97="2/10 Net 30","Yes","No") -> No | M97: =IF(AND(L97="Yes",(F97+G97+H97+I97)<=10),"Yes","No") -> No | N97: =IF(K97>30,"Yes","No") -> No | O97: =IF(AND(L97="Yes",'Invoice Sample'!O97="No",M97="Yes"),C97*0.02,0) -> 0 | P97: =IF(AND('Invoice Sample'!P97="Yes",N97="No"),C97*0.015,0) -> 0
A98: ='Invoice Sample'!A98 -> INV-2127 | B98: ='Invoice Sample'!C98 -> Recurring | C98: ='Invoice Sample'!E98 -> 1751.54 | D98: ='Invoice Sample'!M98 -> Tier 1 ($500-$10K) | E98: ='Invoice Sample'!F98 -> 2/10 Net 30 | F98: =IF(B98="Recurring",'Future-State Model'!E22,'Future-State Model'!E23) -> 0.23744186 | G98: ='Future-State Model'!E24 -> 2.4157 | H98: =IF(OR(D98="Tier 2 ($10K-$50K)",D98="Tier 3 (>$50K)"),'Future-State Model'!E25,0) -> 0 | I98: =IF(D98="Tier 3 (>$50K)",'Future-State Model'!E26,0) -> 0 | J98: ='Future-State Model'!E27 -> 0.686 | K98: =SUM(F98:J98) -> 3.3391419 | L98: =IF(E98="2/10 Net 30","Yes","No") -> Yes | M98: =IF(AND(L98="Yes",(F98+G98+H98+I98)<=10),"Yes","No") -> Yes | N98: =IF(K98>30,"Yes","No") -> No | O98: =IF(AND(L98="Yes",'Invoice Sample'!O98="No",M98="Yes"),C98*0.02,0) -> 35.0308 | P98: =IF(AND('Invoice Sample'!P98="Yes",N98="No"),C98*0.015,0) -> 0
A99: ='Invoice Sample'!A99 -> INV-2128 | B99: ='Invoice Sample'!C99 -> Recurring | C99: ='Invoice Sample'!E99 -> 92.59 | D99: ='Invoice Sample'!M99 -> Tier 0 (<$500) | E99: ='Invoice Sample'!F99 -> 2/10 Net 30 | F99: =IF(B99="Recurring",'Future-State Model'!E22,'Future-State Model'!E23) -> 0.23744186 | G99: ='Future-State Model'!E24 -> 2.4157 | H99: =IF(OR(D99="Tier 2 ($10K-$50K)",D99="Tier 3 (>$50K)"),'Future-State Model'!E25,0) -> 0 | I99: =IF(D99="Tier 3 (>$50K)",'Future-State Model'!E26,0) -> 0 | J99: ='Future-State Model'!E27 -> 0.686 | K99: =SUM(F99:J99) -> 3.3391419 | L99: =IF(E99="2/10 Net 30","Yes","No") -> Yes | M99: =IF(AND(L99="Yes",(F99+G99+H99+I99)<=10),"Yes","No") -> Yes | N99: =IF(K99>30,"Yes","No") -> No | O99: =IF(AND(L99="Yes",'Invoice Sample'!O99="No",M99="Yes"),C99*0.02,0) -> 0 | P99: =IF(AND('Invoice Sample'!P99="Yes",N99="No"),C99*0.015,0) -> 0
A100: ='Invoice Sample'!A100 -> INV-2129 | B100: ='Invoice Sample'!C100 -> Recurring | C100: ='Invoice Sample'!E100 -> 302.86 | D100: ='Invoice Sample'!M100 -> Tier 0 (<$500) | E100: ='Invoice Sample'!F100 -> 2/10 Net 30 | F100: =IF(B100="Recurring",'Future-State Model'!E22,'Future-State Model'!E23) -> 0.23744186 | G100: ='Future-State Model'!E24 -> 2.4157 | H100: =IF(OR(D100="Tier 2 ($10K-$50K)",D100="Tier 3 (>$50K)"),'Future-State Model'!E25,0) -> 0 | I100: =IF(D100="Tier 3 (>$50K)",'Future-State Model'!E26,0) -> 0 | J100: ='Future-State Model'!E27 -> 0.686 | K100: =SUM(F100:J100) -> 3.3391419 | L100: =IF(E100="2/10 Net 30","Yes","No") -> Yes | M100: =IF(AND(L100="Yes",(F100+G100+H100+I100)<=10),"Yes","No") -> Yes | N100: =IF(K100>30,"Yes","No") -> No | O100: =IF(AND(L100="Yes",'Invoice Sample'!O100="No",M100="Yes"),C100*0.02,0) -> 0 | P100: =IF(AND('Invoice Sample'!P100="Yes",N100="No"),C100*0.015,0) -> 0
...

Sheet Summary
B2: Summary — before / after
B4: Blended cycle time (population-weighted across this sample)
B5: Current state — avg total cycle days | E5: =AVERAGE('Invoice Sample'!L2:L121) -> 12.835
B6: Future state — avg total cycle days | E6: =AVERAGE('Future-State Projection'!K2:K121) -> 4.3350973
B7: Reduction | E7: =(E5-E6)/E5 -> 0.66224407
B9: Annualized financial impact (monthly sample × 12)
B10: Months per year | F10: 12
B11: Discount $ captured / year (newly captured, future state) | E11: =SUM('Future-State Projection'!O2:O121)*F10 -> 124814.86
B12: Late fee $ avoided / year | E12: =SUM('Future-State Projection'!P2:P121)*F10 -> 0
B13: Total annual benefit | E13: =E11+E12 -> 124814.86
B15: Implementation cost
B16: Routing tool (annual) | E16: ='Future-State Model'!F16 -> 18000
B17: OCR tool (annual) | E17: ='Future-State Model'!F17 -> 9600
B18: One-time implementation (Year 1 only) | E18: ='Future-State Model'!F18 -> 22000
B19: Total Year 1 cost | E19: =E16+E17+E18 -> 49600
B21: Net benefit — Year 1 | E21: =E13-E19 -> 75214.856
B22: Net benefit — Year 2+ (subscriptions only, no re-implementation) | E22: =E13-E16-E17 -> 97214.856
