Workbook

Sheet Overview
B2: Case 04 — Order-Entry Automation: Cost-Benefit Analysis
B4: Supports the Business Case. Brightpath Distribution's inbound sales-order entry team manually keys orders from fax, email PDF, and an EDI portal into the ERP. Order volume is growing 15%/year. This workbook compares two ways to keep pace over 3 years: keep hiring at current productivity (Option B), or invest in OCR/RPA automation (Option C).
B6: Color legend
B7: Blue text | C7: Hardcoded input / assumption
B8: Yellow fill | C8: Key assumption
B9: Black text | C9: Formula
B10: Green text | C10: Link from another sheet

Sheet Assumptions
B2: Assumptions
B4: Current annual order volume | F4: 66500
B5: Volume growth rate / year | F5: 0.15
B6: Current headcount (data-entry clerks) | F6: 7
B7: Orders processed / clerk / year (manual) | F7: 9500
B8: Fully loaded cost / clerk / year | F8: 52000
B9: One-time hiring & onboarding cost / new hire | F9: 8000
B10: Manual order error rate (needs correction/rework) | F10: 0.025
B11: Automated (OCR-validated) order error rate | F11: 0.006
B12: Average cost per order error (rework, reship, CS time) | F12: 35
B13: RPA/OCR platform subscription / year | F13: 85000
B14: One-time implementation cost (Year 1 only) | F14: 120000
B15: Ongoing template/maintenance cost / year | F15: 15000
... B19: Discount rate (WACC) | F19: 0.08

Sheet Option B - Hire
B2: Option B — Hire to Keep Pace
B4: Year | C4: Order volume | D4: Headcount needed | E4: New hires | F4: Labor cost | G4: Hiring cost | H4: Total cost
B5: 1 | C5: =Assumptions!$F$4*(1+Assumptions!$F$5) -> 76475 | D5: =CEILING(C5/Assumptions!$F$7,1) -> 9 | E5: =D5-Assumptions!$F$6 -> 2 | F5: =D5*Assumptions!$F$8 -> 468000 | G5: =E5*Assumptions!$F$9 -> 16000 | H5: =F5+G5 -> 484000
B6: 2 | C6: =C5*(1+Assumptions!$F$5) -> 87946.25 | D6: =CEILING(C6/Assumptions!$F$7,1) -> 10 | E6: =D6-D5 -> 1 | F6: =D6*Assumptions!$F$8 -> 520000 | G6: =E6*Assumptions!$F$9 -> 8000 | H6: =F6+G6 -> 528000
B7: 3 | C7: =C6*(1+Assumptions!$F$5) -> 101138.19 | D7: =CEILING(C7/Assumptions!$F$7,1) -> 11 | E7: =D7-D6 -> 1 | F7: =D7*Assumptions!$F$8 -> 572000 | G7: =E7*Assumptions!$F$9 -> 8000 | H7: =F7+G7 -> 580000
B9: 3-year total | H9: =SUM(H5:H7) -> 1592000

Sheet Option C - Automate
B2: Option C — Invest in OCR/RPA Automation
B4: Year | C4: Order volume | D4: Auto-processed | E4: Manual | F4: Headcount (floor: no layoffs) | G4: Labor cost | H4: Subscription | I4: Implementation | J4: Maintenance | K4: Total cost
B5: 1 | C5: ='Option B - Hire'!C5 -> 76475 | D5: =C5*Assumptions!$F$16 -> 49708.75 | E5: =C5-D5 -> 26766.25 | F5: =MAX(Assumptions!$F$6,CEILING(E5/Assumptions!$F$7,1)) -> 7 | G5: =F5*Assumptions!$F$8 -> 364000 | H5: =Assumptions!$F$13 -> 85000 | I5: =Assumptions!$F$14 -> 120000 | J5: =Assumptions!$F$15 -> 15000 | K5: =G5+H5+I5+J5 -> 584000
B6: 2 | C6: ='Option B - Hire'!C6 -> 87946.25 | D6: =C6*Assumptions!$F$17 -> 65959.688 | E6: =C6-D6 -> 21986.562 | F6: =MAX(Assumptions!$F$6,CEILING(E6/Assumptions!$F$7,1)) -> 7 | G6: =F6*Assumptions!$F$8 -> 364000 | H6: =Assumptions!$F$13 -> 85000 | I6: 0 | J6: =Assumptions!$F$15 -> 15000 | K6: =G6+H6+I6+J6 -> 464000
B7: 3 | C7: ='Option B - Hire'!C7 -> 101138.19 | D7: =C7*Assumptions!$F$18 -> 80910.55 | E7: =C7-D7 -> 20227.638 | F7: =MAX(Assumptions!$F$6,CEILING(E7/Assumptions!$F$7,1)) -> 7 | G7: =F7*Assumptions!$F$8 -> 364000 | H7: =Assumptions!$F$13 -> 85000 | I7: 0 | J7: =Assumptions!$F$15 -> 15000 | K7: =G7+H7+I7+J7 -> 464000
B9: 3-year total | K9: =SUM(K5:K7) -> 1512000
B11: Error cost — Option C (auto share + manual share, blended rates)
B12: Year | C12: Auto-processed errors ($) | D12: Manual errors ($) | E12: Total error cost
B13: 1 | C13: =D5*Assumptions!$F$11*Assumptions!$F$12 -> 10438.837 | D13: =E5*Assumptions!$F$10*Assumptions!$F$12 -> 23420.469 | E13: =C13+D13 -> 33859.306
B14: 2 | C14: =D6*Assumptions!$F$11*Assumptions!$F$12 -> 13851.534 | D14: =E6*Assumptions!$F$10*Assumptions!$F$12 -> 19238.242 | E14: =C14+D14 -> 33089.777
B15: 3 | C15: =D7*Assumptions!$F$11*Assumptions!$F$12 -> 16991.215 | D15: =E7*Assumptions!$F$10*Assumptions!$F$12 -> 17699.183 | E15: =C15+D15 -> 34690.398

Sheet NPV & Payback
B2: Net Benefit of Automating (Option C) vs. Hiring (Option B)
B4: Year | C4: Option B cost | D4: Option C cost | E4: Cost avoided (B-C) | F4: Error cost — Option B (all-manual baseline) | G4: Error cost — Option C | H4: Error cost avoided | I4: Net benefit
B5: 1 | C5: ='Option B - Hire'!H5 -> 484000 | D5: ='Option C - Automate'!K5 -> 584000 | E5: =C5-D5 -> -100000 | F5: ='Option C - Automate'!C5*Assumptions!$F$10*Assumptions!$F$12 -> 66915.625 | G5: ='Option C - Automate'!E13 -> 33859.306 | H5: =F5-G5 -> 33056.319 | I5: =E5+H5 -> -66943.681
B6: 2 | C6: ='Option B - Hire'!H6 -> 528000 | D6: ='Option C - Automate'!K6 -> 464000 | E6: =C6-D6 -> 64000 | F6: ='Option C - Automate'!C6*Assumptions!$F$10*Assumptions!$F$12 -> 76952.969 | G6: ='Option C - Automate'!E14 -> 33089.777 | H6: =F6-G6 -> 43863.192 | I6: =E6+H6 -> 107863.19
B7: 3 | C7: ='Option B - Hire'!H7 -> 580000 | D7: ='Option C - Automate'!K7 -> 464000 | E7: =C7-D7 -> 116000 | F7: ='Option C - Automate'!C7*Assumptions!$F$10*Assumptions!$F$12 -> 88495.914 | G7: ='Option C - Automate'!E15 -> 34690.398 | H7: =F7-G7 -> 53805.516 | I7: =E7+H7 -> 169805.52
B9: 3-year total net benefit | I9: =SUM(I5:I7) -> 210725.03
B12: Discounted cash flow (NPV)
B13: Year | C13: Net benefit | D13: Discount factor | E13: Present value | F13: Cumulative PV
B14: 1 | C14: =I5 -> -66943.681 | D14: =1/(1+Assumptions!$F$19)^B14 -> 0.92592593 | E14: =C14*D14 -> -61984.89 | F14: =E14 -> -61984.89
B15: 2 | C15: =I6 -> 107863.19 | D15: =1/(1+Assumptions!$F$19)^B15 -> 0.85733882 | E15: =C15*D15 -> 92475.302 | F15: =F14+E15 -> 30490.412
B16: 3 | C16: =I7 -> 169805.52 | D16: =1/(1+Assumptions!$F$19)^B16 -> 0.79383224 | E16: =C16*D16 -> 134797.09 | F16: =F15+E16 -> 165287.51
B18: 3-year NPV @ discount rate | E18: =SUM(E14:E16) -> 165287.51
B20: Simple payback (undiscounted, using cumulative net benefit)
B21: Cumulative net benefit through Year 1 | E21: =I5 -> -66943.681
B22: Cumulative net benefit through Year 2 | E22: =E21+I6 -> 40919.511
B23: Cumulative net benefit through Year 3 | E23: =E22+I7 -> 210725.03
B25: Payback period (years) | E25: =IF(E21>=0,-E21/I5+1,IF(E22>=0,1+(-E21)/I6,IF(E23>=0,2+(-E22)/I7,"beyond 3 years"))) -> 1.6206351

Sheet Summary
B2: Summary
B4: Option B — 3-year total cost (hire to keep pace) | E4: ='Option B - Hire'!H9 -> 1592000
B5: Option C — 3-year total cost (automate) | E5: ='Option C - Automate'!K9 -> 1512000
B6: 3-year net benefit of automating (cost + error-avoidance) | E6: ='NPV & Payback'!I9 -> 210725.03
B7: 3-year NPV @ discount rate | E7: ='NPV & Payback'!E18 -> 165287.51
B8: Payback period (years) | E8: ='NPV & Payback'!E25 -> 1.6206351
